Workbook

Sheet Back-End Page
A1: Year | B1: MONTHLY OVERVIEW TOTAL | G1: =UPPER(TEXT('Setup Page'!$AC18,"mmm yy")) -> JUL 23 | H1: =UPPER(TEXT('Setup Page'!$AC19,"mmm yy")) -> AUG 23 | I1: =UPPER(TEXT('Setup Page'!$AC20,"mmm yy")) -> SEP 23 | J1: =UPPER(TEXT('Setup Page'!$AC21,"mmm yy")) -> OCT 23 | K1: =UPPER(TEXT('Setup Page'!$AC22,"mmm yy")) -> NOV 23 | L1: =UPPER(TEXT('Setup Page'!$AC23,"mmm yy")) -> DEC 23 | M1: =UPPER(TEXT('Setup Page'!$AC24,"mmm yy")) -> JAN 24 | N1: =UPPER(TEXT('Setup Page'!$AC25,"mmm yy")) -> FEB 24 | O1: =UPPER(TEXT('Setup Page'!$AC26,"mmm yy")) -> MAR 24 | P1: =UPPER(TEXT('Setup Page'!$AC27,"mmm yy")) -> APR 24 | Q1: =UPPER(TEXT('Setup Page'!$AC28,"mmm yy")) -> MAY 24 | R1: =UPPER(TEXT('Setup Page'!$AC29,"mmm yy")) -> JUN 24
A2: 1960 | B2: INCOME CATEGORIES | C2: TOTAL AMOUNT | D2: NET | E2: TAX | F2: M O N T H L Y P R O F I T | G2: =Annual!M113 -> 4987.04 | H2: =Annual!R113 -> 6535.6 | I2: =Annual!W113 -> 4980 | J2: =Annual!AB113 -> 8471.2 | K2: =Annual!AG113 -> 6890.2 | L2: =Annual!AL113 -> 2510.27 | M2: =Annual!AQ113 -> 12713.25 | N2: =Annual!AV113 -> 12196.61 | O2: =Annual!BA113 -> 20276.84 | P2: =Annual!BF113 -> 12970.2 | Q2: =Annual!BK113 -> 8771.2 | R2: =Annual!BP113 -> 5870.2
A3: 1961 | B3: ='Setup Page'!C18 -> Investment | C3: =SUMIFS('Income Entry'!$F$11:$F1000,'Income Entry'!$L$11:$L1000,B3,'Income Entry'!$S$11:$S1000,Monthly!$K$10,'Income Entry'!$T$11:$T1000,Monthly!$S$10) -> 0 | D3: =SUMIFS('Income Entry'!$H$11:$H1000,'Income Entry'!$L$11:$L1000,B3,'Income Entry'!$S$11:$S1000,Monthly!$K$10,'Income Entry'!$T$11:$T1000,Monthly!$S$10) -> 0 | E3: =SUMIFS('Income Entry'!$I$11:$I1000,'Income Entry'!$L$11:$L1000,B3,'Income Entry'!$S$11:$S1000,Monthly!$K$10,'Income Entry'!$T$11:$T1000,Monthly!$S$10) -> 0 | F3: M O N T H L Y P R O F I T G O A L | G3: =Annual!M114 -> 0 | H3: =Annual!R114 -> 0 | I3: =Annual!W114 -> 2400 | J3: =Annual!AB114 -> 2400 | K3: =Annual!AG114 -> 2400 | L3: =Annual!AL114 -> 6000 | M3: =Annual!AQ114 -> 6000 | N3: =Annual!AV114 -> 6000 | O3: =Annual!BA114 -> 6000 | P3: =Annual!BF114 -> 6000 | Q3: =Annual!BK114 -> 6000 | R3: =Annual!BP114 -> 6000
A4: 1962 | B4: ='Setup Page'!C19 -> Fines | C4: =SUMIFS('Income Entry'!$F$11:$F1000,'Income Entry'!$L$11:$L1000,B4,'Income Entry'!$S$11:$S1000,Monthly!$K$10,'Income Entry'!$T$11:$T1000,Monthly!$S$10) -> 0 | D4: =SUMIFS('Income Entry'!$H$11:$H1000,'Income Entry'!$L$11:$L1000,B4,'Income Entry'!$S$11:$S1000,Monthly!$K$10,'Income Entry'!$T$11:$T1000,Monthly!$S$10) -> 0 | E4: =SUMIFS('Income Entry'!$I$11:$I1000,'Income Entry'!$L$11:$L1000,B4,'Income Entry'!$S$11:$S1000,Monthly!$K$10,'Income Entry'!$T$11:$T1000,Monthly!$S$10) -> 0
A5: 1963 | B5: ='Setup Page'!C20 | C5: =SUMIFS('Income Entry'!$F$11:$F1000,'Income Entry'!$L$11:$L1000,B5,'Income Entry'!$S$11:$S1000,Monthly!$K$10,'Income Entry'!$T$11:$T1000,Monthly!$S$10) -> 0 | D5: =SUMIFS('Income Entry'!$H$11:$H1000,'Income Entry'!$L$11:$L1000,B5,'Income Entry'!$S$11:$S1000,Monthly!$K$10,'Income Entry'!$T$11:$T1000,Monthly!$S$10) -> 0 | E5: =SUMIFS('Income Entry'!$I$11:$I1000,'Income Entry'!$L$11:$L1000,B5,'Income Entry'!$S$11:$S1000,Monthly!$K$10,'Income Entry'!$T$11:$T1000,Monthly!$S$10) -> 0 | F5: I N C O M E | G5: =Annual!M61 -> 5000 | H5: =Annual!R61 -> 6550 | I5: =Annual!W61 -> 5000 | J5: =Annual!AB61 -> 8500 | K5: =Annual!AG61 -> 6920 | L5: =Annual!AL61 -> 5192.76 | M5: =Annual!AQ61 -> 12550 | N5: =Annual!AV61 -> 12100 | O5: =Annual!BA61 -> 20276.84 | P5: =Annual!BF61 -> 0 | Q5: =Annual!BK61 -> 0 | R5: =Annual!BP61 -> 0
A6: 1964 | B6: ='Setup Page'!C21 | C6: =SUMIFS('Income Entry'!$F$11:$F1000,'Income Entry'!$L$11:$L1000,B6,'Income Entry'!$S$11:$S1000,Monthly!$K$10,'Income Entry'!$T$11:$T1000,Monthly!$S$10) -> 0 | D6: =SUMIFS('Income Entry'!$H$11:$H1000,'Income Entry'!$L$11:$L1000,B6,'Income Entry'!$S$11:$S1000,Monthly!$K$10,'Income Entry'!$T$11:$T1000,Monthly!$S$10) -> 0 | E6: =SUMIFS('Income Entry'!$I$11:$I1000,'Income Entry'!$L$11:$L1000,B6,'Income Entry'!$S$11:$S1000,Monthly!$K$10,'Income Entry'!$T$11:$T1000,Monthly!$S$10) -> 0 | F6: E X P E N S E S | G6: =Annual!M106 -> 12.96 | H6: =Annual!R106 -> 14.4 | I6: =Annual!W106 -> 20 | J6: =Annual!AB106 -> 28.8 | K6: =Annual!AG106 -> 28.8 | L6: =Annual!AL106 -> 28.8 | M6: =Annual!AQ106 -> 28.8 | N6: =Annual!AV106 -> 127.8 | O6: =Annual!BA106 -> 0 | P6: =Annual!BF106 -> 28.8 | Q6: =Annual!BK106 -> 28.8 | R6: =Annual!BP106 -> 28.8
A7: 1965 | B7: ='Setup Page'!C22 | C7: =SUMIFS('Income Entry'!$F$11:$F1000,'Income Entry'!$L$11:$L1000,B7,'Income Entry'!$S$11:$S1000,Monthly!$K$10,'Income Entry'!$T$11:$T1000,Monthly!$S$10) -> 0 | D7: =SUMIFS('Income Entry'!$H$11:$H1000,'Income Entry'!$L$11:$L1000,B7,'Income Entry'!$S$11:$S1000,Monthly!$K$10,'Income Entry'!$T$11:$T1000,Monthly!$S$10) -> 0 | E7: =SUMIFS('Income Entry'!$I$11:$I1000,'Income Entry'!$L$11:$L1000,B7,'Income Entry'!$S$11:$S1000,Monthly!$K$10,'Income Entry'!$T$11:$T1000,Monthly!$S$10) -> 0
A8: 1966 | B8: ='Setup Page'!C23 | C8: =SUMIFS('Income Entry'!$F$11:$F1000,'Income Entry'!$L$11:$L1000,B8,'Income Entry'!$S$11:$S1000,Monthly!$K$10,'Income Entry'!$T$11:$T1000,Monthly!$S$10) -> 0 | D8: =SUMIFS('Income Entry'!$H$11:$H1000,'Income Entry'!$L$11:$L1000,B8,'Income Entry'!$S$11:$S1000,Monthly!$K$10,'Income Entry'!$T$11:$T1000,Monthly!$S$10) -> 0 | E8: =SUMIFS('Income Entry'!$I$11:$I1000,'Income Entry'!$L$11:$L1000,B8,'Income Entry'!$S$11:$S1000,Monthly!$K$10,'Income Entry'!$T$11:$T1000,Monthly!$S$10) -> 0 | F8: PAYMENT METHODS
A9: 1967 | B9: ='Setup Page'!C24 | C9: =SUMIFS('Income Entry'!$F$11:$F1000,'Income Entry'!$L$11:$L1000,B9,'Income Entry'!$S$11:$S1000,Monthly!$K$10,'Income Entry'!$T$11:$T1000,Monthly!$S$10) -> 0 | D9: =SUMIFS('Income Entry'!$H$11:$H1000,'Income Entry'!$L$11:$L1000,B9,'Income Entry'!$S$11:$S1000,Monthly!$K$10,'Income Entry'!$T$11:$T1000,Monthly!$S$10) -> 0 | E9: =SUMIFS('Income Entry'!$I$11:$I1000,'Income Entry'!$L$11:$L1000,B9,'Income Entry'!$S$11:$S1000,Monthly!$K$10,'Income Entry'!$T$11:$T1000,Monthly!$S$10) -> 0 | F9: ='Setup Page'!E10 -> Cash
A10: 1968 | B10: ='Setup Page'!C25 | C10: =SUMIFS('Income Entry'!$F$11:$F1000,'Income Entry'!$L$11:$L1000,B10,'Income Entry'!$S$11:$S1000,Monthly!$K$10,'Income Entry'!$T$11:$T1000,Monthly!$S$10) -> 0 | D10: =SUMIFS('Income Entry'!$H$11:$H1000,'Income Entry'!$L$11:$L1000,B10,'Income Entry'!$S$11:$S1000,Monthly!$K$10,'Income Entry'!$T$11:$T1000,Monthly!$S$10) -> 0 | E10: =SUMIFS('Income Entry'!$I$11:$I1000,'Income Entry'!$L$11:$L1000,B10,'Income Entry'!$S$11:$S1000,Monthly!$K$10,'Income Entry'!$T$11:$T1000,Monthly!$S$10) -> 0 | F10: ='Setup Page'!E11 -> Credit Card
A11: 1969 | B11: ='Setup Page'!C26 | C11: =SUMIFS('Income Entry'!$F$11:$F1000,'Income Entry'!$L$11:$L1000,B11,'Income Entry'!$S$11:$S1000,Monthly!$K$10,'Income Entry'!$T$11:$T1000,Monthly!$S$10) -> 0 | D11: =SUMIFS('Income Entry'!$H$11:$H1000,'Income Entry'!$L$11:$L1000,B11,'Income Entry'!$S$11:$S1000,Monthly!$K$10,'Income Entry'!$T$11:$T1000,Monthly!$S$10) -> 0 | E11: =SUMIFS('Income Entry'!$I$11:$I1000,'Income Entry'!$L$11:$L1000,B11,'Income Entry'!$S$11:$S1000,Monthly!$K$10,'Income Entry'!$T$11:$T1000,Monthly!$S$10) -> 0 | F11: ='Setup Page'!E12 -> Bank Account
A12: 1970 | B12: ='Setup Page'!C27 | C12: =SUMIFS('Income Entry'!$F$11:$F1000,'Income Entry'!$L$11:$L1000,B12,'Income Entry'!$S$11:$S1000,Monthly!$K$10,'Income Entry'!$T$11:$T1000,Monthly!$S$10) -> 0 | D12: =SUMIFS('Income Entry'!$H$11:$H1000,'Income Entry'!$L$11:$L1000,B12,'Income Entry'!$S$11:$S1000,Monthly!$K$10,'Income Entry'!$T$11:$T1000,Monthly!$S$10) -> 0 | E12: =SUMIFS('Income Entry'!$I$11:$I1000,'Income Entry'!$L$11:$L1000,B12,'Income Entry'!$S$11:$S1000,Monthly!$K$10,'Income Entry'!$T$11:$T1000,Monthly!$S$10) -> 0 | F12: ='Setup Page'!O10 -> Zelle
A13: 1971 | B13: ='Setup Page'!C28 | C13: =SUMIFS('Income Entry'!$F$11:$F1000,'Income Entry'!$L$11:$L1000,B13,'Income Entry'!$S$11:$S1000,Monthly!$K$10,'Income Entry'!$T$11:$T1000,Monthly!$S$10) -> 0 | D13: =SUMIFS('Income Entry'!$H$11:$H1000,'Income Entry'!$L$11:$L1000,B13,'Income Entry'!$S$11:$S1000,Monthly!$K$10,'Income Entry'!$T$11:$T1000,Monthly!$S$10) -> 0 | E13: =SUMIFS('Income Entry'!$I$11:$I1000,'Income Entry'!$L$11:$L1000,B13,'Income Entry'!$S$11:$S1000,Monthly!$K$10,'Income Entry'!$T$11:$T1000,Monthly!$S$10) -> 0 | F13: ='Setup Page'!O11
A14: 1972 | B14: ='Setup Page'!C29 | C14: =SUMIFS('Income Entry'!$F$11:$F1000,'Income Entry'!$L$11:$L1000,B14,'Income Entry'!$S$11:$S1000,Monthly!$K$10,'Income Entry'!$T$11:$T1000,Monthly!$S$10) -> 0 | D14: =SUMIFS('Income Entry'!$H$11:$H1000,'Income Entry'!$L$11:$L1000,B14,'Income Entry'!$S$11:$S1000,Monthly!$K$10,'Income Entry'!$T$11:$T1000,Monthly!$S$10) -> 0 | E14: =SUMIFS('Income Entry'!$I$11:$I1000,'Income Entry'!$L$11:$L1000,B14,'Income Entry'!$S$11:$S1000,Monthly!$K$10,'Income Entry'!$T$11:$T1000,Monthly!$S$10) -> 0 | F14: ='Setup Page'!O12
A15: 1973 | B15: ='Setup Page'!C30 | C15: =SUMIFS('Income Entry'!$F$11:$F1000,'Income Entry'!$L$11:$L1000,B15,'Income Entry'!$S$11:$S1000,Monthly!$K$10,'Income Entry'!$T$11:$T1000,Monthly!$S$10) -> 0 | D15: =SUMIFS('Income Entry'!$H$11:$H1000,'Income Entry'!$L$11:$L1000,B15,'Income Entry'!$S$11:$S1000,Monthly!$K$10,'Income Entry'!$T$11:$T1000,Monthly!$S$10) -> 0 | E15: =SUMIFS('Income Entry'!$I$11:$I1000,'Income Entry'!$L$11:$L1000,B15,'Income Entry'!$S$11:$S1000,Monthly!$K$10,'Income Entry'!$T$11:$T1000,Monthly!$S$10) -> 0 | F15: ='Setup Page'!Y10
A16: 1974 | B16: ='Setup Page'!C31 | C16: =SUMIFS('Income Entry'!$F$11:$F1000,'Income Entry'!$L$11:$L1000,B16,'Income Entry'!$S$11:$S1000,Monthly!$K$10,'Income Entry'!$T$11:$T1000,Monthly!$S$10) -> 0 | D16: =SUMIFS('Income Entry'!$H$11:$H1000,'Income Entry'!$L$11:$L1000,B16,'Income Entry'!$S$11:$S1000,Monthly!$K$10,'Income Entry'!$T$11:$T1000,Monthly!$S$10) -> 0 | E16: =SUMIFS('Income Entry'!$I$11:$I1000,'Income Entry'!$L$11:$L1000,B16,'Income Entry'!$S$11:$S1000,Monthly!$K$10,'Income Entry'!$T$11:$T1000,Monthly!$S$10) -> 0 | F16: ='Setup Page'!Y11
A17: 1975 | B17: ='Setup Page'!C32 | C17: =SUMIFS('Income Entry'!$F$11:$F1000,'Income Entry'!$L$11:$L1000,B17,'Income Entry'!$S$11:$S1000,Monthly!$K$10,'Income Entry'!$T$11:$T1000,Monthly!$S$10) -> 0 | D17: =SUMIFS('Income Entry'!$H$11:$H1000,'Income Entry'!$L$11:$L1000,B17,'Income Entry'!$S$11:$S1000,Monthly!$K$10,'Income Entry'!$T$11:$T1000,Monthly!$S$10) -> 0 | E17: =SUMIFS('Income Entry'!$I$11:$I1000,'Income Entry'!$L$11:$L1000,B17,'Income Entry'!$S$11:$S1000,Monthly!$K$10,'Income Entry'!$T$11:$T1000,Monthly!$S$10) -> 0 | F17: ='Setup Page'!Y12
A18: 1976 | B18: ='Setup Page'!C33 | C18: =SUMIFS('Income Entry'!$F$11:$F1000,'Income Entry'!$L$11:$L1000,B18,'Income Entry'!$S$11:$S1000,Monthly!$K$10,'Income Entry'!$T$11:$T1000,Monthly!$S$10) -> 0 | D18: =SUMIFS('Income Entry'!$H$11:$H1000,'Income Entry'!$L$11:$L1000,B18,'Income Entry'!$S$11:$S1000,Monthly!$K$10,'Income Entry'!$T$11:$T1000,Monthly!$S$10) -> 0 | E18: =SUMIFS('Income Entry'!$I$11:$I1000,'Income Entry'!$L$11:$L1000,B18,'Income Entry'!$S$11:$S1000,Monthly!$K$10,'Income Entry'!$T$11:$T1000,Monthly!$S$10) -> 0 | F18: ='Setup Page'!AI10
A19: 1977 | B19: ='Setup Page'!C34 | C19: =SUMIFS('Income Entry'!$F$11:$F1000,'Income Entry'!$L$11:$L1000,B19,'Income Entry'!$S$11:$S1000,Monthly!$K$10,'Income Entry'!$T$11:$T1000,Monthly!$S$10) -> 0 | D19: =SUMIFS('Income Entry'!$H$11:$H1000,'Income Entry'!$L$11:$L1000,B19,'Income Entry'!$S$11:$S1000,Monthly!$K$10,'Income Entry'!$T$11:$T1000,Monthly!$S$10) -> 0 | E19: =SUMIFS('Income Entry'!$I$11:$I1000,'Income Entry'!$L$11:$L1000,B19,'Income Entry'!$S$11:$S1000,Monthly!$K$10,'Income Entry'!$T$11:$T1000,Monthly!$S$10) -> 0 | F19: ='Setup Page'!AI11
A20: 1978 | B20: ='Setup Page'!C35 | C20: =SUMIFS('Income Entry'!$F$11:$F1000,'Income Entry'!$L$11:$L1000,B20,'Income Entry'!$S$11:$S1000,Monthly!$K$10,'Income Entry'!$T$11:$T1000,Monthly!$S$10) -> 0 | D20: =SUMIFS('Income Entry'!$H$11:$H1000,'Income Entry'!$L$11:$L1000,B20,'Income Entry'!$S$11:$S1000,Monthly!$K$10,'Income Entry'!$T$11:$T1000,Monthly!$S$10) -> 0 | E20: =SUMIFS('Income Entry'!$I$11:$I1000,'Income Entry'!$L$11:$L1000,B20,'Income Entry'!$S$11:$S1000,Monthly!$K$10,'Income Entry'!$T$11:$T1000,Monthly!$S$10) -> 0 | F20: ='Setup Page'!AI12
A21: 1979 | B21: ='Setup Page'!C36 | C21: =SUMIFS('Income Entry'!$F$11:$F1000,'Income Entry'!$L$11:$L1000,B21,'Income Entry'!$S$11:$S1000,Monthly!$K$10,'Income Entry'!$T$11:$T1000,Monthly!$S$10) -> 0 | D21: =SUMIFS('Income Entry'!$H$11:$H1000,'Income Entry'!$L$11:$L1000,B21,'Income Entry'!$S$11:$S1000,Monthly!$K$10,'Income Entry'!$T$11:$T1000,Monthly!$S$10) -> 0 | E21: =SUMIFS('Income Entry'!$I$11:$I1000,'Income Entry'!$L$11:$L1000,B21,'Income Entry'!$S$11:$S1000,Monthly!$K$10,'Income Entry'!$T$11:$T1000,Monthly!$S$10) -> 0
A22: 1980 | B22: ='Setup Page'!C37 | C22: =SUMIFS('Income Entry'!$F$11:$F1000,'Income Entry'!$L$11:$L1000,B22,'Income Entry'!$S$11:$S1000,Monthly!$K$10,'Income Entry'!$T$11:$T1000,Monthly!$S$10) -> 0 | D22: =SUMIFS('Income Entry'!$H$11:$H1000,'Income Entry'!$L$11:$L1000,B22,'Income Entry'!$S$11:$S1000,Monthly!$K$10,'Income Entry'!$T$11:$T1000,Monthly!$S$10) -> 0 | E22: =SUMIFS('Income Entry'!$I$11:$I1000,'Income Entry'!$L$11:$L1000,B22,'Income Entry'!$S$11:$S1000,Monthly!$K$10,'Income Entry'!$T$11:$T1000,Monthly!$S$10) -> 0
A23: 1981 | B23: ='Setup Page'!C38 | C23: =SUMIFS('Income Entry'!$F$11:$F1000,'Income Entry'!$L$11:$L1000,B23,'Income Entry'!$S$11:$S1000,Monthly!$K$10,'Income Entry'!$T$11:$T1000,Monthly!$S$10) -> 0 | D23: =SUMIFS('Income Entry'!$H$11:$H1000,'Income Entry'!$L$11:$L1000,B23,'Income Entry'!$S$11:$S1000,Monthly!$K$10,'Income Entry'!$T$11:$T1000,Monthly!$S$10) -> 0 | E23: =SUMIFS('Income Entry'!$I$11:$I1000,'Income Entry'!$L$11:$L1000,B23,'Income Entry'!$S$11:$S1000,Monthly!$K$10,'Income Entry'!$T$11:$T1000,Monthly!$S$10) -> 0
A24: 1982 | B24: ='Setup Page'!C39 | C24: =SUMIFS('Income Entry'!$F$11:$F1000,'Income Entry'!$L$11:$L1000,B24,'Income Entry'!$S$11:$S1000,Monthly!$K$10,'Income Entry'!$T$11:$T1000,Monthly!$S$10) -> 0 | D24: =SUMIFS('Income Entry'!$H$11:$H1000,'Income Entry'!$L$11:$L1000,B24,'Income Entry'!$S$11:$S1000,Monthly!$K$10,'Income Entry'!$T$11:$T1000,Monthly!$S$10) -> 0 | E24: =SUMIFS('Income Entry'!$I$11:$I1000,'Income Entry'!$L$11:$L1000,B24,'Income Entry'!$S$11:$S1000,Monthly!$K$10,'Income Entry'!$T$11:$T1000,Monthly!$S$10) -> 0
A25: 1983 | B25: ='Setup Page'!C40 | C25: =SUMIFS('Income Entry'!$F$11:$F1000,'Income Entry'!$L$11:$L1000,B25,'Income Entry'!$S$11:$S1000,Monthly!$K$10,'Income Entry'!$T$11:$T1000,Monthly!$S$10) -> 0 | D25: =SUMIFS('Income Entry'!$H$11:$H1000,'Income Entry'!$L$11:$L1000,B25,'Income Entry'!$S$11:$S1000,Monthly!$K$10,'Income Entry'!$T$11:$T1000,Monthly!$S$10) -> 0 | E25: =SUMIFS('Income Entry'!$I$11:$I1000,'Income Entry'!$L$11:$L1000,B25,'Income Entry'!$S$11:$S1000,Monthly!$K$10,'Income Entry'!$T$11:$T1000,Monthly!$S$10) -> 0
A26: 1984 | B26: ='Setup Page'!C41 | C26: =SUMIFS('Income Entry'!$F$11:$F1000,'Income Entry'!$L$11:$L1000,B26,'Income Entry'!$S$11:$S1000,Monthly!$K$10,'Income Entry'!$T$11:$T1000,Monthly!$S$10) -> 0 | D26: =SUMIFS('Income Entry'!$H$11:$H1000,'Income Entry'!$L$11:$L1000,B26,'Income Entry'!$S$11:$S1000,Monthly!$K$10,'Income Entry'!$T$11:$T1000,Monthly!$S$10) -> 0 | E26: =SUMIFS('Income Entry'!$I$11:$I1000,'Income Entry'!$L$11:$L1000,B26,'Income Entry'!$S$11:$S1000,Monthly!$K$10,'Income Entry'!$T$11:$T1000,Monthly!$S$10) -> 0
A27: 1985 | B27: ='Setup Page'!C42 | C27: =SUMIFS('Income Entry'!$F$11:$F1000,'Income Entry'!$L$11:$L1000,B27,'Income Entry'!$S$11:$S1000,Monthly!$K$10,'Income Entry'!$T$11:$T1000,Monthly!$S$10) -> 0 | D27: =SUMIFS('Income Entry'!$H$11:$H1000,'Income Entry'!$L$11:$L1000,B27,'Income Entry'!$S$11:$S1000,Monthly!$K$10,'Income Entry'!$T$11:$T1000,Monthly!$S$10) -> 0 | E27: =SUMIFS('Income Entry'!$I$11:$I1000,'Income Entry'!$L$11:$L1000,B27,'Income Entry'!$S$11:$S1000,Monthly!$K$10,'Income Entry'!$T$11:$T1000,Monthly!$S$10) -> 0
A28: 1986 | B28: ='Setup Page'!C43 | C28: =SUMIFS('Income Entry'!$F$11:$F1000,'Income Entry'!$L$11:$L1000,B28,'Income Entry'!$S$11:$S1000,Monthly!$K$10,'Income Entry'!$T$11:$T1000,Monthly!$S$10) -> 0 | D28: =SUMIFS('Income Entry'!$H$11:$H1000,'Income Entry'!$L$11:$L1000,B28,'Income Entry'!$S$11:$S1000,Monthly!$K$10,'Income Entry'!$T$11:$T1000,Monthly!$S$10) -> 0 | E28: =SUMIFS('Income Entry'!$I$11:$I1000,'Income Entry'!$L$11:$L1000,B28,'Income Entry'!$S$11:$S1000,Monthly!$K$10,'Income Entry'!$T$11:$T1000,Monthly!$S$10) -> 0
A29: 1987 | B29: ='Setup Page'!C44 | C29: =SUMIFS('Income Entry'!$F$11:$F1000,'Income Entry'!$L$11:$L1000,B29,'Income Entry'!$S$11:$S1000,Monthly!$K$10,'Income Entry'!$T$11:$T1000,Monthly!$S$10) -> 0 | D29: =SUMIFS('Income Entry'!$H$11:$H1000,'Income Entry'!$L$11:$L1000,B29,'Income Entry'!$S$11:$S1000,Monthly!$K$10,'Income Entry'!$T$11:$T1000,Monthly!$S$10) -> 0 | E29: =SUMIFS('Income Entry'!$I$11:$I1000,'Income Entry'!$L$11:$L1000,B29,'Income Entry'!$S$11:$S1000,Monthly!$K$10,'Income Entry'!$T$11:$T1000,Monthly!$S$10) -> 0
A30: 1988 | B30: ='Setup Page'!C45 | C30: =SUMIFS('Income Entry'!$F$11:$F1000,'Income Entry'!$L$11:$L1000,B30,'Income Entry'!$S$11:$S1000,Monthly!$K$10,'Income Entry'!$T$11:$T1000,Monthly!$S$10) -> 0 | D30: =SUMIFS('Income Entry'!$H$11:$H1000,'Income Entry'!$L$11:$L1000,B30,'Income Entry'!$S$11:$S1000,Monthly!$K$10,'Income Entry'!$T$11:$T1000,Monthly!$S$10) -> 0 | E30: =SUMIFS('Income Entry'!$I$11:$I1000,'Income Entry'!$L$11:$L1000,B30,'Income Entry'!$S$11:$S1000,Monthly!$K$10,'Income Entry'!$T$11:$T1000,Monthly!$S$10) -> 0
A31: 1989 | B31: ='Setup Page'!C46 | C31: =SUMIFS('Income Entry'!$F$11:$F1000,'Income Entry'!$L$11:$L1000,B31,'Income Entry'!$S$11:$S1000,Monthly!$K$10,'Income Entry'!$T$11:$T1000,Monthly!$S$10) -> 0 | D31: =SUMIFS('Income Entry'!$H$11:$H1000,'Income Entry'!$L$11:$L1000,B31,'Income Entry'!$S$11:$S1000,Monthly!$K$10,'Income Entry'!$T$11:$T1000,Monthly!$S$10) -> 0 | E31: =SUMIFS('Income Entry'!$I$11:$I1000,'Income Entry'!$L$11:$L1000,B31,'Income Entry'!$S$11:$S1000,Monthly!$K$10,'Income Entry'!$T$11:$T1000,Monthly!$S$10) -> 0
A32: 1990 | B32: ='Setup Page'!C47 | C32: =SUMIFS('Income Entry'!$F$11:$F1000,'Income Entry'!$L$11:$L1000,B32,'Income Entry'!$S$11:$S1000,Monthly!$K$10,'Income Entry'!$T$11:$T1000,Monthly!$S$10) -> 0 | D32: =SUMIFS('Income Entry'!$H$11:$H1000,'Income Entry'!$L$11:$L1000,B32,'Income Entry'!$S$11:$S1000,Monthly!$K$10,'Income Entry'!$T$11:$T1000,Monthly!$S$10) -> 0 | E32: =SUMIFS('Income Entry'!$I$11:$I1000,'Income Entry'!$L$11:$L1000,B32,'Income Entry'!$S$11:$S1000,Monthly!$K$10,'Income Entry'!$T$11:$T1000,Monthly!$S$10) -> 0
A33: 1991 | B33: ='Setup Page'!C48 | C33: =SUMIFS('Income Entry'!$F$11:$F1000,'Income Entry'!$L$11:$L1000,B33,'Income Entry'!$S$11:$S1000,Monthly!$K$10,'Income Entry'!$T$11:$T1000,Monthly!$S$10) -> 0 | D33: =SUMIFS('Income Entry'!$H$11:$H1000,'Income Entry'!$L$11:$L1000,B33,'Income Entry'!$S$11:$S1000,Monthly!$K$10,'Income Entry'!$T$11:$T1000,Monthly!$S$10) -> 0 | E33: =SUMIFS('Income Entry'!$I$11:$I1000,'Income Entry'!$L$11:$L1000,B33,'Income Entry'!$S$11:$S1000,Monthly!$K$10,'Income Entry'!$T$11:$T1000,Monthly!$S$10) -> 0
A34: 1992 | B34: ='Setup Page'!C49 | C34: =SUMIFS('Income Entry'!$F$11:$F1000,'Income Entry'!$L$11:$L1000,B34,'Income Entry'!$S$11:$S1000,Monthly!$K$10,'Income Entry'!$T$11:$T1000,Monthly!$S$10) -> 0 | D34: =SUMIFS('Income Entry'!$H$11:$H1000,'Income Entry'!$L$11:$L1000,B34,'Income Entry'!$S$11:$S1000,Monthly!$K$10,'Income Entry'!$T$11:$T1000,Monthly!$S$10) -> 0 | E34: =SUMIFS('Income Entry'!$I$11:$I1000,'Income Entry'!$L$11:$L1000,B34,'Income Entry'!$S$11:$S1000,Monthly!$K$10,'Income Entry'!$T$11:$T1000,Monthly!$S$10) -> 0
A35: 1993 | B35: ='Setup Page'!C50 | C35: =SUMIFS('Income Entry'!$F$11:$F1000,'Income Entry'!$L$11:$L1000,B35,'Income Entry'!$S$11:$S1000,Monthly!$K$10,'Income Entry'!$T$11:$T1000,Monthly!$S$10) -> 0 | D35: =SUMIFS('Income Entry'!$H$11:$H1000,'Income Entry'!$L$11:$L1000,B35,'Income Entry'!$S$11:$S1000,Monthly!$K$10,'Income Entry'!$T$11:$T1000,Monthly!$S$10) -> 0 | E35: =SUMIFS('Income Entry'!$I$11:$I1000,'Income Entry'!$L$11:$L1000,B35,'Income Entry'!$S$11:$S1000,Monthly!$K$10,'Income Entry'!$T$11:$T1000,Monthly!$S$10) -> 0
A36: 1994 | B36: ='Setup Page'!C51 | C36: =SUMIFS('Income Entry'!$F$11:$F1000,'Income Entry'!$L$11:$L1000,B36,'Income Entry'!$S$11:$S1000,Monthly!$K$10,'Income Entry'!$T$11:$T1000,Monthly!$S$10) -> 0 | D36: =SUMIFS('Income Entry'!$H$11:$H1000,'Income Entry'!$L$11:$L1000,B36,'Income Entry'!$S$11:$S1000,Monthly!$K$10,'Income Entry'!$T$11:$T1000,Monthly!$S$10) -> 0 | E36: =SUMIFS('Income Entry'!$I$11:$I1000,'Income Entry'!$L$11:$L1000,B36,'Income Entry'!$S$11:$S1000,Monthly!$K$10,'Income Entry'!$T$11:$T1000,Monthly!$S$10) -> 0
A37: 1995 | B37: ='Setup Page'!C52 | C37: =SUMIFS('Income Entry'!$F$11:$F1000,'Income Entry'!$L$11:$L1000,B37,'Income Entry'!$S$11:$S1000,Monthly!$K$10,'Income Entry'!$T$11:$T1000,Monthly!$S$10) -> 0 | D37: =SUMIFS('Income Entry'!$H$11:$H1000,'Income Entry'!$L$11:$L1000,B37,'Income Entry'!$S$11:$S1000,Monthly!$K$10,'Income Entry'!$T$11:$T1000,Monthly!$S$10) -> 0 | E37: =SUMIFS('Income Entry'!$I$11:$I1000,'Income Entry'!$L$11:$L1000,B37,'Income Entry'!$S$11:$S1000,Monthly!$K$10,'Income Entry'!$T$11:$T1000,Monthly!$S$10) -> 0
A38: 1996 | B38: ='Setup Page'!C53 | C38: =SUMIFS('Income Entry'!$F$11:$F1000,'Income Entry'!$L$11:$L1000,B38,'Income Entry'!$S$11:$S1000,Monthly!$K$10,'Income Entry'!$T$11:$T1000,Monthly!$S$10) -> 0 | D38: =SUMIFS('Income Entry'!$H$11:$H1000,'Income Entry'!$L$11:$L1000,B38,'Income Entry'!$S$11:$S1000,Monthly!$K$10,'Income Entry'!$T$11:$T1000,Monthly!$S$10) -> 0 | E38: =SUMIFS('Income Entry'!$I$11:$I1000,'Income Entry'!$L$11:$L1000,B38,'Income Entry'!$S$11:$S1000,Monthly!$K$10,'Income Entry'!$T$11:$T1000,Monthly!$S$10) -> 0
A39: 1997 | B39: ='Setup Page'!C54 | C39: =SUMIFS('Income Entry'!$F$11:$F1000,'Income Entry'!$L$11:$L1000,B39,'Income Entry'!$S$11:$S1000,Monthly!$K$10,'Income Entry'!$T$11:$T1000,Monthly!$S$10) -> 0 | D39: =SUMIFS('Income Entry'!$H$11:$H1000,'Income Entry'!$L$11:$L1000,B39,'Income Entry'!$S$11:$S1000,Monthly!$K$10,'Income Entry'!$T$11:$T1000,Monthly!$S$10) -> 0 | E39: =SUMIFS('Income Entry'!$I$11:$I1000,'Income Entry'!$L$11:$L1000,B39,'Income Entry'!$S$11:$S1000,Monthly!$K$10,'Income Entry'!$T$11:$T1000,Monthly!$S$10) -> 0
A40: 1998 | B40: ='Setup Page'!C55 | C40: =SUMIFS('Income Entry'!$F$11:$F1000,'Income Entry'!$L$11:$L1000,B40,'Income Entry'!$S$11:$S1000,Monthly!$K$10,'Income Entry'!$T$11:$T1000,Monthly!$S$10) -> 0 | D40: =SUMIFS('Income Entry'!$H$11:$H1000,'Income Entry'!$L$11:$L1000,B40,'Income Entry'!$S$11:$S1000,Monthly!$K$10,'Income Entry'!$T$11:$T1000,Monthly!$S$10) -> 0 | E40: =SUMIFS('Income Entry'!$I$11:$I1000,'Income Entry'!$L$11:$L1000,B40,'Income Entry'!$S$11:$S1000,Monthly!$K$10,'Income Entry'!$T$11:$T1000,Monthly!$S$10) -> 0
A41: 1999 | B41: ='Setup Page'!C56 | C41: =SUMIFS('Income Entry'!$F$11:$F1000,'Income Entry'!$L$11:$L1000,B41,'Income Entry'!$S$11:$S1000,Monthly!$K$10,'Income Entry'!$T$11:$T1000,Monthly!$S$10) -> 0 | D41: =SUMIFS('Income Entry'!$H$11:$H1000,'Income Entry'!$L$11:$L1000,B41,'Income Entry'!$S$11:$S1000,Monthly!$K$10,'Income Entry'!$T$11:$T1000,Monthly!$S$10) -> 0 | E41: =SUMIFS('Income Entry'!$I$11:$I1000,'Income Entry'!$L$11:$L1000,B41,'Income Entry'!$S$11:$S1000,Monthly!$K$10,'Income Entry'!$T$11:$T1000,Monthly!$S$10) -> 0
A42: 2000 | B42: ='Setup Page'!C57 | C42: =SUMIFS('Income Entry'!$F$11:$F1000,'Income Entry'!$L$11:$L1000,B42,'Income Entry'!$S$11:$S1000,Monthly!$K$10,'Income Entry'!$T$11:$T1000,Monthly!$S$10) -> 0 | D42: =SUMIFS('Income Entry'!$H$11:$H1000,'Income Entry'!$L$11:$L1000,B42,'Income Entry'!$S$11:$S1000,Monthly!$K$10,'Income Entry'!$T$11:$T1000,Monthly!$S$10) -> 0 | E42: =SUMIFS('Income Entry'!$I$11:$I1000,'Income Entry'!$L$11:$L1000,B42,'Income Entry'!$S$11:$S1000,Monthly!$K$10,'Income Entry'!$T$11:$T1000,Monthly!$S$10) -> 0
A43: 2001 | B43: TOTALS | C43: =SUM(C2:C42) -> 0 | D43: =SUM(D2:D42) -> 0 | E43: =SUM(E2:E42) -> 0
A44: 2002
A45: 2003
A46: 2004
A47: 2005 | B47: EXPENSE CATEGORIES | C47: TOTAL AMOUNT | D47: NET | E47: TAX
A48: 2006 | B48: ='Setup Page'!P18 -> Virtual Address | C48: =SUMIFS('Expense Entry'!$F$11:$F1000,'Expense Entry'!$D$11:$D1000,B48,'Expense Entry'!$Q$11:$Q1000,Monthly!$K$10,'Expense Entry'!$R$11:$R1000,Monthly!$S$10) -> 0 | D48: =SUMIFS('Expense Entry'!$H$11:$H1000,'Expense Entry'!$D$11:$D1000,B48,'Expense Entry'!$Q$11:$Q1000,Monthly!$K$10,'Expense Entry'!$R$11:$R1000,Monthly!$S$10) -> 0 | E48: =SUMIFS('Expense Entry'!$I$11:$I1000,'Expense Entry'!$D$11:$D1000,B48,'Expense Entry'!$Q$11:$Q1000,Monthly!$K$10,'Expense Entry'!$R$11:$R1000,Monthly!$S$10) -> 0
A49: 2007 | B49: ='Setup Page'!P19 -> Legal Zoom | C49: =SUMIFS('Expense Entry'!$F$11:$F1000,'Expense Entry'!$D$11:$D1000,B49,'Expense Entry'!$Q$11:$Q1000,Monthly!$K$10,'Expense Entry'!$R$11:$R1000,Monthly!$S$10) -> 0 | D49: =SUMIFS('Expense Entry'!$H$11:$H1000,'Expense Entry'!$D$11:$D1000,B49,'Expense Entry'!$Q$11:$Q1000,Monthly!$K$10,'Expense Entry'!$R$11:$R1000,Monthly!$S$10) -> 0 | E49: =SUMIFS('Expense Entry'!$I$11:$I1000,'Expense Entry'!$D$11:$D1000,B49,'Expense Entry'!$Q$11:$Q1000,Monthly!$K$10,'Expense Entry'!$R$11:$R1000,Monthly!$S$10) -> 0
A50: 2008 | B50: ='Setup Page'!P20 -> Google GSuite | C50: =SUMIFS('Expense Entry'!$F$11:$F1000,'Expense Entry'!$D$11:$D1000,B50,'Expense Entry'!$Q$11:$Q1000,Monthly!$K$10,'Expense Entry'!$R$11:$R1000,Monthly!$S$10) -> 28.8 | D50: =SUMIFS('Expense Entry'!$H$11:$H1000,'Expense Entry'!$D$11:$D1000,B50,'Expense Entry'!$Q$11:$Q1000,Monthly!$K$10,'Expense Entry'!$R$11:$R1000,Monthly!$S$10) -> 26.181818 | E50: =SUMIFS('Expense Entry'!$I$11:$I1000,'Expense Entry'!$D$11:$D1000,B50,'Expense Entry'!$Q$11:$Q1000,Monthly!$K$10,'Expense Entry'!$R$11:$R1000,Monthly!$S$10) -> 2.6181818
A51: 2009 | B51: ='Setup Page'!P21 | C51: =SUMIFS('Expense Entry'!$F$11:$F1000,'Expense Entry'!$D$11:$D1000,B51,'Expense Entry'!$Q$11:$Q1000,Monthly!$K$10,'Expense Entry'!$R$11:$R1000,Monthly!$S$10) -> 0 | D51: =SUMIFS('Expense Entry'!$H$11:$H1000,'Expense Entry'!$D$11:$D1000,B51,'Expense Entry'!$Q$11:$Q1000,Monthly!$K$10,'Expense Entry'!$R$11:$R1000,Monthly!$S$10) -> 0 | E51: =SUMIFS('Expense Entry'!$I$11:$I1000,'Expense Entry'!$D$11:$D1000,B51,'Expense Entry'!$Q$11:$Q1000,Monthly!$K$10,'Expense Entry'!$R$11:$R1000,Monthly!$S$10) -> 0
A52: 2010 | B52: ='Setup Page'!P22 | C52: =SUMIFS('Expense Entry'!$F$11:$F1000,'Expense Entry'!$D$11:$D1000,B52,'Expense Entry'!$Q$11:$Q1000,Monthly!$K$10,'Expense Entry'!$R$11:$R1000,Monthly!$S$10) -> 0 | D52: =SUMIFS('Expense Entry'!$H$11:$H1000,'Expense Entry'!$D$11:$D1000,B52,'Expense Entry'!$Q$11:$Q1000,Monthly!$K$10,'Expense Entry'!$R$11:$R1000,Monthly!$S$10) -> 0 | E52: =SUMIFS('Expense Entry'!$I$11:$I1000,'Expense Entry'!$D$11:$D1000,B52,'Expense Entry'!$Q$11:$Q1000,Monthly!$K$10,'Expense Entry'!$R$11:$R1000,Monthly!$S$10) -> 0
A53: 2011 | B53: ='Setup Page'!P23 | C53: =SUMIFS('Expense Entry'!$F$11:$F1000,'Expense Entry'!$D$11:$D1000,B53,'Expense Entry'!$Q$11:$Q1000,Monthly!$K$10,'Expense Entry'!$R$11:$R1000,Monthly!$S$10) -> 0 | D53: =SUMIFS('Expense Entry'!$H$11:$H1000,'Expense Entry'!$D$11:$D1000,B53,'Expense Entry'!$Q$11:$Q1000,Monthly!$K$10,'Expense Entry'!$R$11:$R1000,Monthly!$S$10) -> 0 | E53: =SUMIFS('Expense Entry'!$I$11:$I1000,'Expense Entry'!$D$11:$D1000,B53,'Expense Entry'!$Q$11:$Q1000,Monthly!$K$10,'Expense Entry'!$R$11:$R1000,Monthly!$S$10) -> 0
A54: 2012 | B54: ='Setup Page'!P24 | C54: =SUMIFS('Expense Entry'!$F$11:$F1000,'Expense Entry'!$D$11:$D1000,B54,'Expense Entry'!$Q$11:$Q1000,Monthly!$K$10,'Expense Entry'!$R$11:$R1000,Monthly!$S$10) -> 0 | D54: =SUMIFS('Expense Entry'!$H$11:$H1000,'Expense Entry'!$D$11:$D1000,B54,'Expense Entry'!$Q$11:$Q1000,Monthly!$K$10,'Expense Entry'!$R$11:$R1000,Monthly!$S$10) -> 0 | E54: =SUMIFS('Expense Entry'!$I$11:$I1000,'Expense Entry'!$D$11:$D1000,B54,'Expense Entry'!$Q$11:$Q1000,Monthly!$K$10,'Expense Entry'!$R$11:$R1000,Monthly!$S$10) -> 0
A55: 2013 | B55: ='Setup Page'!P25 | C55: =SUMIFS('Expense Entry'!$F$11:$F1000,'Expense Entry'!$D$11:$D1000,B55,'Expense Entry'!$Q$11:$Q1000,Monthly!$K$10,'Expense Entry'!$R$11:$R1000,Monthly!$S$10) -> 0 | D55: =SUMIFS('Expense Entry'!$H$11:$H1000,'Expense Entry'!$D$11:$D1000,B55,'Expense Entry'!$Q$11:$Q1000,Monthly!$K$10,'Expense Entry'!$R$11:$R1000,Monthly!$S$10) -> 0 | E55: =SUMIFS('Expense Entry'!$I$11:$I1000,'Expense Entry'!$D$11:$D1000,B55,'Expense Entry'!$Q$11:$Q1000,Monthly!$K$10,'Expense Entry'!$R$11:$R1000,Monthly!$S$10) -> 0
A56: 2014 | B56: ='Setup Page'!P26 | C56: =SUMIFS('Expense Entry'!$F$11:$F1000,'Expense Entry'!$D$11:$D1000,B56,'Expense Entry'!$Q$11:$Q1000,Monthly!$K$10,'Expense Entry'!$R$11:$R1000,Monthly!$S$10) -> 0 | D56: =SUMIFS('Expense Entry'!$H$11:$H1000,'Expense Entry'!$D$11:$D1000,B56,'Expense Entry'!$Q$11:$Q1000,Monthly!$K$10,'Expense Entry'!$R$11:$R1000,Monthly!$S$10) -> 0 | E56: =SUMIFS('Expense Entry'!$I$11:$I1000,'Expense Entry'!$D$11:$D1000,B56,'Expense Entry'!$Q$11:$Q1000,Monthly!$K$10,'Expense Entry'!$R$11:$R1000,Monthly!$S$10) -> 0
A57: 2015 | B57: ='Setup Page'!P27 | C57: =SUMIFS('Expense Entry'!$F$11:$F1000,'Expense Entry'!$D$11:$D1000,B57,'Expense Entry'!$Q$11:$Q1000,Monthly!$K$10,'Expense Entry'!$R$11:$R1000,Monthly!$S$10) -> 0 | D57: =SUMIFS('Expense Entry'!$H$11:$H1000,'Expense Entry'!$D$11:$D1000,B57,'Expense Entry'!$Q$11:$Q1000,Monthly!$K$10,'Expense Entry'!$R$11:$R1000,Monthly!$S$10) -> 0 | E57: =SUMIFS('Expense Entry'!$I$11:$I1000,'Expense Entry'!$D$11:$D1000,B57,'Expense Entry'!$Q$11:$Q1000,Monthly!$K$10,'Expense Entry'!$R$11:$R1000,Monthly!$S$10) -> 0
A58: 2016 | B58: ='Setup Page'!P28 | C58: =SUMIFS('Expense Entry'!$F$11:$F1000,'Expense Entry'!$D$11:$D1000,B58,'Expense Entry'!$Q$11:$Q1000,Monthly!$K$10,'Expense Entry'!$R$11:$R1000,Monthly!$S$10) -> 0 | D58: =SUMIFS('Expense Entry'!$H$11:$H1000,'Expense Entry'!$D$11:$D1000,B58,'Expense Entry'!$Q$11:$Q1000,Monthly!$K$10,'Expense Entry'!$R$11:$R1000,Monthly!$S$10) -> 0 | E58: =SUMIFS('Expense Entry'!$I$11:$I1000,'Expense Entry'!$D$11:$D1000,B58,'Expense Entry'!$Q$11:$Q1000,Monthly!$K$10,'Expense Entry'!$R$11:$R1000,Monthly!$S$10) -> 0
A59: 2017 | B59: ='Setup Page'!P29 | C59: =SUMIFS('Expense Entry'!$F$11:$F1000,'Expense Entry'!$D$11:$D1000,B59,'Expense Entry'!$Q$11:$Q1000,Monthly!$K$10,'Expense Entry'!$R$11:$R1000,Monthly!$S$10) -> 0 | D59: =SUMIFS('Expense Entry'!$H$11:$H1000,'Expense Entry'!$D$11:$D1000,B59,'Expense Entry'!$Q$11:$Q1000,Monthly!$K$10,'Expense Entry'!$R$11:$R1000,Monthly!$S$10) -> 0 | E59: =SUMIFS('Expense Entry'!$I$11:$I1000,'Expense Entry'!$D$11:$D1000,B59,'Expense Entry'!$Q$11:$Q1000,Monthly!$K$10,'Expense Entry'!$R$11:$R1000,Monthly!$S$10) -> 0
A60: 2018 | B60: ='Setup Page'!P30 | C60: =SUMIFS('Expense Entry'!$F$11:$F1000,'Expense Entry'!$D$11:$D1000,B60,'Expense Entry'!$Q$11:$Q1000,Monthly!$K$10,'Expense Entry'!$R$11:$R1000,Monthly!$S$10) -> 0 | D60: =SUMIFS('Expense Entry'!$H$11:$H1000,'Expense Entry'!$D$11:$D1000,B60,'Expense Entry'!$Q$11:$Q1000,Monthly!$K$10,'Expense Entry'!$R$11:$R1000,Monthly!$S$10) -> 0 | E60: =SUMIFS('Expense Entry'!$I$11:$I1000,'Expense Entry'!$D$11:$D1000,B60,'Expense Entry'!$Q$11:$Q1000,Monthly!$K$10,'Expense Entry'!$R$11:$R1000,Monthly!$S$10) -> 0
A61: 2019 | B61: ='Setup Page'!P31 | C61: =SUMIFS('Expense Entry'!$F$11:$F1000,'Expense Entry'!$D$11:$D1000,B61,'Expense Entry'!$Q$11:$Q1000,Monthly!$K$10,'Expense Entry'!$R$11:$R1000,Monthly!$S$10) -> 0 | D61: =SUMIFS('Expense Entry'!$H$11:$H1000,'Expense Entry'!$D$11:$D1000,B61,'Expense Entry'!$Q$11:$Q1000,Monthly!$K$10,'Expense Entry'!$R$11:$R1000,Monthly!$S$10) -> 0 | E61: =SUMIFS('Expense Entry'!$I$11:$I1000,'Expense Entry'!$D$11:$D1000,B61,'Expense Entry'!$Q$11:$Q1000,Monthly!$K$10,'Expense Entry'!$R$11:$R1000,Monthly!$S$10) -> 0
A62: 2020 | B62: ='Setup Page'!P32 | C62: =SUMIFS('Expense Entry'!$F$11:$F1000,'Expense Entry'!$D$11:$D1000,B62,'Expense Entry'!$Q$11:$Q1000,Monthly!$K$10,'Expense Entry'!$R$11:$R1000,Monthly!$S$10) -> 0 | D62: =SUMIFS('Expense Entry'!$H$11:$H1000,'Expense Entry'!$D$11:$D1000,B62,'Expense Entry'!$Q$11:$Q1000,Monthly!$K$10,'Expense Entry'!$R$11:$R1000,Monthly!$S$10) -> 0 | E62: =SUMIFS('Expense Entry'!$I$11:$I1000,'Expense Entry'!$D$11:$D1000,B62,'Expense Entry'!$Q$11:$Q1000,Monthly!$K$10,'Expense Entry'!$R$11:$R1000,Monthly!$S$10) -> 0
A63: 2021 | B63: ='Setup Page'!P33 | C63: =SUMIFS('Expense Entry'!$F$11:$F1000,'Expense Entry'!$D$11:$D1000,B63,'Expense Entry'!$Q$11:$Q1000,Monthly!$K$10,'Expense Entry'!$R$11:$R1000,Monthly!$S$10) -> 0 | D63: =SUMIFS('Expense Entry'!$H$11:$H1000,'Expense Entry'!$D$11:$D1000,B63,'Expense Entry'!$Q$11:$Q1000,Monthly!$K$10,'Expense Entry'!$R$11:$R1000,Monthly!$S$10) -> 0 | E63: =SUMIFS('Expense Entry'!$I$11:$I1000,'Expense Entry'!$D$11:$D1000,B63,'Expense Entry'!$Q$11:$Q1000,Monthly!$K$10,'Expense Entry'!$R$11:$R1000,Monthly!$S$10) -> 0
A64: 2022 | B64: ='Setup Page'!P34 | C64: =SUMIFS('Expense Entry'!$F$11:$F1000,'Expense Entry'!$D$11:$D1000,B64,'Expense Entry'!$Q$11:$Q1000,Monthly!$K$10,'Expense Entry'!$R$11:$R1000,Monthly!$S$10) -> 0 | D64: =SUMIFS('Expense Entry'!$H$11:$H1000,'Expense Entry'!$D$11:$D1000,B64,'Expense Entry'!$Q$11:$Q1000,Monthly!$K$10,'Expense Entry'!$R$11:$R1000,Monthly!$S$10) -> 0 | E64: =SUMIFS('Expense Entry'!$I$11:$I1000,'Expense Entry'!$D$11:$D1000,B64,'Expense Entry'!$Q$11:$Q1000,Monthly!$K$10,'Expense Entry'!$R$11:$R1000,Monthly!$S$10) -> 0
A65: 2023 | B65: ='Setup Page'!P35 | C65: =SUMIFS('Expense Entry'!$F$11:$F1000,'Expense Entry'!$D$11:$D1000,B65,'Expense Entry'!$Q$11:$Q1000,Monthly!$K$10,'Expense Entry'!$R$11:$R1000,Monthly!$S$10) -> 0 | D65: =SUMIFS('Expense Entry'!$H$11:$H1000,'Expense Entry'!$D$11:$D1000,B65,'Expense Entry'!$Q$11:$Q1000,Monthly!$K$10,'Expense Entry'!$R$11:$R1000,Monthly!$S$10) -> 0 | E65: =SUMIFS('Expense Entry'!$I$11:$I1000,'Expense Entry'!$D$11:$D1000,B65,'Expense Entry'!$Q$11:$Q1000,Monthly!$K$10,'Expense Entry'!$R$11:$R1000,Monthly!$S$10) -> 0
A66: 2024 | B66: ='Setup Page'!P36 | C66: =SUMIFS('Expense Entry'!$F$11:$F1000,'Expense Entry'!$D$11:$D1000,B66,'Expense Entry'!$Q$11:$Q1000,Monthly!$K$10,'Expense Entry'!$R$11:$R1000,Monthly!$S$10) -> 0 | D66: =SUMIFS('Expense Entry'!$H$11:$H1000,'Expense Entry'!$D$11:$D1000,B66,'Expense Entry'!$Q$11:$Q1000,Monthly!$K$10,'Expense Entry'!$R$11:$R1000,Monthly!$S$10) -> 0 | E66: =SUMIFS('Expense Entry'!$I$11:$I1000,'Expense Entry'!$D$11:$D1000,B66,'Expense Entry'!$Q$11:$Q1000,Monthly!$K$10,'Expense Entry'!$R$11:$R1000,Monthly!$S$10) -> 0
A67: 2025 | B67: ='Setup Page'!P37 | C67: =SUMIFS('Expense Entry'!$F$11:$F1000,'Expense Entry'!$D$11:$D1000,B67,'Expense Entry'!$Q$11:$Q1000,Monthly!$K$10,'Expense Entry'!$R$11:$R1000,Monthly!$S$10) -> 0 | D67: =SUMIFS('Expense Entry'!$H$11:$H1000,'Expense Entry'!$D$11:$D1000,B67,'Expense Entry'!$Q$11:$Q1000,Monthly!$K$10,'Expense Entry'!$R$11:$R1000,Monthly!$S$10) -> 0 | E67: =SUMIFS('Expense Entry'!$I$11:$I1000,'Expense Entry'!$D$11:$D1000,B67,'Expense Entry'!$Q$11:$Q1000,Monthly!$K$10,'Expense Entry'!$R$11:$R1000,Monthly!$S$10) -> 0
A68: 2026 | B68: ='Setup Page'!P38 | C68: =SUMIFS('Expense Entry'!$F$11:$F1000,'Expense Entry'!$D$11:$D1000,B68,'Expense Entry'!$Q$11:$Q1000,Monthly!$K$10,'Expense Entry'!$R$11:$R1000,Monthly!$S$10) -> 0 | D68: =SUMIFS('Expense Entry'!$H$11:$H1000,'Expense Entry'!$D$11:$D1000,B68,'Expense Entry'!$Q$11:$Q1000,Monthly!$K$10,'Expense Entry'!$R$11:$R1000,Monthly!$S$10) -> 0 | E68: =SUMIFS('Expense Entry'!$I$11:$I1000,'Expense Entry'!$D$11:$D1000,B68,'Expense Entry'!$Q$11:$Q1000,Monthly!$K$10,'Expense Entry'!$R$11:$R1000,Monthly!$S$10) -> 0
A69: 2027 | B69: ='Setup Page'!P39 | C69: =SUMIFS('Expense Entry'!$F$11:$F1000,'Expense Entry'!$D$11:$D1000,B69,'Expense Entry'!$Q$11:$Q1000,Monthly!$K$10,'Expense Entry'!$R$11:$R1000,Monthly!$S$10) -> 0 | D69: =SUMIFS('Expense Entry'!$H$11:$H1000,'Expense Entry'!$D$11:$D1000,B69,'Expense Entry'!$Q$11:$Q1000,Monthly!$K$10,'Expense Entry'!$R$11:$R1000,Monthly!$S$10) -> 0 | E69: =SUMIFS('Expense Entry'!$I$11:$I1000,'Expense Entry'!$D$11:$D1000,B69,'Expense Entry'!$Q$11:$Q1000,Monthly!$K$10,'Expense Entry'!$R$11:$R1000,Monthly!$S$10) -> 0
A70: 2028 | B70: ='Setup Page'!P40 | C70: =SUMIFS('Expense Entry'!$F$11:$F1000,'Expense Entry'!$D$11:$D1000,B70,'Expense Entry'!$Q$11:$Q1000,Monthly!$K$10,'Expense Entry'!$R$11:$R1000,Monthly!$S$10) -> 0 | D70: =SUMIFS('Expense Entry'!$H$11:$H1000,'Expense Entry'!$D$11:$D1000,B70,'Expense Entry'!$Q$11:$Q1000,Monthly!$K$10,'Expense Entry'!$R$11:$R1000,Monthly!$S$10) -> 0 | E70: =SUMIFS('Expense Entry'!$I$11:$I1000,'Expense Entry'!$D$11:$D1000,B70,'Expense Entry'!$Q$11:$Q1000,Monthly!$K$10,'Expense Entry'!$R$11:$R1000,Monthly!$S$10) -> 0
A71: 2029 | B71: ='Setup Page'!P41 | C71: =SUMIFS('Expense Entry'!$F$11:$F1000,'Expense Entry'!$D$11:$D1000,B71,'Expense Entry'!$Q$11:$Q1000,Monthly!$K$10,'Expense Entry'!$R$11:$R1000,Monthly!$S$10) -> 0 | D71: =SUMIFS('Expense Entry'!$H$11:$H1000,'Expense Entry'!$D$11:$D1000,B71,'Expense Entry'!$Q$11:$Q1000,Monthly!$K$10,'Expense Entry'!$R$11:$R1000,Monthly!$S$10) -> 0 | E71: =SUMIFS('Expense Entry'!$I$11:$I1000,'Expense Entry'!$D$11:$D1000,B71,'Expense Entry'!$Q$11:$Q1000,Monthly!$K$10,'Expense Entry'!$R$11:$R1000,Monthly!$S$10) -> 0
A72: 2030 | B72: ='Setup Page'!P42 | C72: =SUMIFS('Expense Entry'!$F$11:$F1000,'Expense Entry'!$D$11:$D1000,B72,'Expense Entry'!$Q$11:$Q1000,Monthly!$K$10,'Expense Entry'!$R$11:$R1000,Monthly!$S$10) -> 0 | D72: =SUMIFS('Expense Entry'!$H$11:$H1000,'Expense Entry'!$D$11:$D1000,B72,'Expense Entry'!$Q$11:$Q1000,Monthly!$K$10,'Expense Entry'!$R$11:$R1000,Monthly!$S$10) -> 0 | E72: =SUMIFS('Expense Entry'!$I$11:$I1000,'Expense Entry'!$D$11:$D1000,B72,'Expense Entry'!$Q$11:$Q1000,Monthly!$K$10,'Expense Entry'!$R$11:$R1000,Monthly!$S$10) -> 0
A73: 2031 | B73: ='Setup Page'!P43 | C73: =SUMIFS('Expense Entry'!$F$11:$F1000,'Expense Entry'!$D$11:$D1000,B73,'Expense Entry'!$Q$11:$Q1000,Monthly!$K$10,'Expense Entry'!$R$11:$R1000,Monthly!$S$10) -> 0 | D73: =SUMIFS('Expense Entry'!$H$11:$H1000,'Expense Entry'!$D$11:$D1000,B73,'Expense Entry'!$Q$11:$Q1000,Monthly!$K$10,'Expense Entry'!$R$11:$R1000,Monthly!$S$10) -> 0 | E73: =SUMIFS('Expense Entry'!$I$11:$I1000,'Expense Entry'!$D$11:$D1000,B73,'Expense Entry'!$Q$11:$Q1000,Monthly!$K$10,'Expense Entry'!$R$11:$R1000,Monthly!$S$10) -> 0
A74: 2032 | B74: ='Setup Page'!P44 | C74: =SUMIFS('Expense Entry'!$F$11:$F1000,'Expense Entry'!$D$11:$D1000,B74,'Expense Entry'!$Q$11:$Q1000,Monthly!$K$10,'Expense Entry'!$R$11:$R1000,Monthly!$S$10) -> 0 | D74: =SUMIFS('Expense Entry'!$H$11:$H1000,'Expense Entry'!$D$11:$D1000,B74,'Expense Entry'!$Q$11:$Q1000,Monthly!$K$10,'Expense Entry'!$R$11:$R1000,Monthly!$S$10) -> 0 | E74: =SUMIFS('Expense Entry'!$I$11:$I1000,'Expense Entry'!$D$11:$D1000,B74,'Expense Entry'!$Q$11:$Q1000,Monthly!$K$10,'Expense Entry'!$R$11:$R1000,Monthly!$S$10) -> 0
A75: 2033 | B75: ='Setup Page'!P45 | C75: =SUMIFS('Expense Entry'!$F$11:$F1000,'Expense Entry'!$D$11:$D1000,B75,'Expense Entry'!$Q$11:$Q1000,Monthly!$K$10,'Expense Entry'!$R$11:$R1000,Monthly!$S$10) -> 0 | D75: =SUMIFS('Expense Entry'!$H$11:$H1000,'Expense Entry'!$D$11:$D1000,B75,'Expense Entry'!$Q$11:$Q1000,Monthly!$K$10,'Expense Entry'!$R$11:$R1000,Monthly!$S$10) -> 0 | E75: =SUMIFS('Expense Entry'!$I$11:$I1000,'Expense Entry'!$D$11:$D1000,B75,'Expense Entry'!$Q$11:$Q1000,Monthly!$K$10,'Expense Entry'!$R$11:$R1000,Monthly!$S$10) -> 0
A76: 2034 | B76: ='Setup Page'!P46 | C76: =SUMIFS('Expense Entry'!$F$11:$F1000,'Expense Entry'!$D$11:$D1000,B76,'Expense Entry'!$Q$11:$Q1000,Monthly!$K$10,'Expense Entry'!$R$11:$R1000,Monthly!$S$10) -> 0 | D76: =SUMIFS('Expense Entry'!$H$11:$H1000,'Expense Entry'!$D$11:$D1000,B76,'Expense Entry'!$Q$11:$Q1000,Monthly!$K$10,'Expense Entry'!$R$11:$R1000,Monthly!$S$10) -> 0 | E76: =SUMIFS('Expense Entry'!$I$11:$I1000,'Expense Entry'!$D$11:$D1000,B76,'Expense Entry'!$Q$11:$Q1000,Monthly!$K$10,'Expense Entry'!$R$11:$R1000,Monthly!$S$10) -> 0
A77: 2035 | B77: ='Setup Page'!P47 | C77: =SUMIFS('Expense Entry'!$F$11:$F1000,'Expense Entry'!$D$11:$D1000,B77,'Expense Entry'!$Q$11:$Q1000,Monthly!$K$10,'Expense Entry'!$R$11:$R1000,Monthly!$S$10) -> 0 | D77: =SUMIFS('Expense Entry'!$H$11:$H1000,'Expense Entry'!$D$11:$D1000,B77,'Expense Entry'!$Q$11:$Q1000,Monthly!$K$10,'Expense Entry'!$R$11:$R1000,Monthly!$S$10) -> 0 | E77: =SUMIFS('Expense Entry'!$I$11:$I1000,'Expense Entry'!$D$11:$D1000,B77,'Expense Entry'!$Q$11:$Q1000,Monthly!$K$10,'Expense Entry'!$R$11:$R1000,Monthly!$S$10) -> 0
A78: 2036 | B78: ='Setup Page'!P48 | C78: =SUMIFS('Expense Entry'!$F$11:$F1000,'Expense Entry'!$D$11:$D1000,B78,'Expense Entry'!$Q$11:$Q1000,Monthly!$K$10,'Expense Entry'!$R$11:$R1000,Monthly!$S$10) -> 0 | D78: =SUMIFS('Expense Entry'!$H$11:$H1000,'Expense Entry'!$D$11:$D1000,B78,'Expense Entry'!$Q$11:$Q1000,Monthly!$K$10,'Expense Entry'!$R$11:$R1000,Monthly!$S$10) -> 0 | E78: =SUMIFS('Expense Entry'!$I$11:$I1000,'Expense Entry'!$D$11:$D1000,B78,'Expense Entry'!$Q$11:$Q1000,Monthly!$K$10,'Expense Entry'!$R$11:$R1000,Monthly!$S$10) -> 0
A79: 2037 | B79: ='Setup Page'!P49 | C79: =SUMIFS('Expense Entry'!$F$11:$F1000,'Expense Entry'!$D$11:$D1000,B79,'Expense Entry'!$Q$11:$Q1000,Monthly!$K$10,'Expense Entry'!$R$11:$R1000,Monthly!$S$10) -> 0 | D79: =SUMIFS('Expense Entry'!$H$11:$H1000,'Expense Entry'!$D$11:$D1000,B79,'Expense Entry'!$Q$11:$Q1000,Monthly!$K$10,'Expense Entry'!$R$11:$R1000,Monthly!$S$10) -> 0 | E79: =SUMIFS('Expense Entry'!$I$11:$I1000,'Expense Entry'!$D$11:$D1000,B79,'Expense Entry'!$Q$11:$Q1000,Monthly!$K$10,'Expense Entry'!$R$11:$R1000,Monthly!$S$10) -> 0
A80: 2038 | B80: ='Setup Page'!P50 | C80: =SUMIFS('Expense Entry'!$F$11:$F1000,'Expense Entry'!$D$11:$D1000,B80,'Expense Entry'!$Q$11:$Q1000,Monthly!$K$10,'Expense Entry'!$R$11:$R1000,Monthly!$S$10) -> 0 | D80: =SUMIFS('Expense Entry'!$H$11:$H1000,'Expense Entry'!$D$11:$D1000,B80,'Expense Entry'!$Q$11:$Q1000,Monthly!$K$10,'Expense Entry'!$R$11:$R1000,Monthly!$S$10) -> 0 | E80: =SUMIFS('Expense Entry'!$I$11:$I1000,'Expense Entry'!$D$11:$D1000,B80,'Expense Entry'!$Q$11:$Q1000,Monthly!$K$10,'Expense Entry'!$R$11:$R1000,Monthly!$S$10) -> 0
A81: 2039 | B81: ='Setup Page'!P51 | C81: =SUMIFS('Expense Entry'!$F$11:$F1000,'Expense Entry'!$D$11:$D1000,B81,'Expense Entry'!$Q$11:$Q1000,Monthly!$K$10,'Expense Entry'!$R$11:$R1000,Monthly!$S$10) -> 0 | D81: =SUMIFS('Expense Entry'!$H$11:$H1000,'Expense Entry'!$D$11:$D1000,B81,'Expense Entry'!$Q$11:$Q1000,Monthly!$K$10,'Expense Entry'!$R$11:$R1000,Monthly!$S$10) -> 0 | E81: =SUMIFS('Expense Entry'!$I$11:$I1000,'Expense Entry'!$D$11:$D1000,B81,'Expense Entry'!$Q$11:$Q1000,Monthly!$K$10,'Expense Entry'!$R$11:$R1000,Monthly!$S$10) -> 0
A82: 2040 | B82: ='Setup Page'!P52 | C82: =SUMIFS('Expense Entry'!$F$11:$F1000,'Expense Entry'!$D$11:$D1000,B82,'Expense Entry'!$Q$11:$Q1000,Monthly!$K$10,'Expense Entry'!$R$11:$R1000,Monthly!$S$10) -> 0 | D82: =SUMIFS('Expense Entry'!$H$11:$H1000,'Expense Entry'!$D$11:$D1000,B82,'Expense Entry'!$Q$11:$Q1000,Monthly!$K$10,'Expense Entry'!$R$11:$R1000,Monthly!$S$10) -> 0 | E82: =SUMIFS('Expense Entry'!$I$11:$I1000,'Expense Entry'!$D$11:$D1000,B82,'Expense Entry'!$Q$11:$Q1000,Monthly!$K$10,'Expense Entry'!$R$11:$R1000,Monthly!$S$10) -> 0
A83: 2041 | B83: ='Setup Page'!P53 | C83: =SUMIFS('Expense Entry'!$F$11:$F1000,'Expense Entry'!$D$11:$D1000,B83,'Expense Entry'!$Q$11:$Q1000,Monthly!$K$10,'Expense Entry'!$R$11:$R1000,Monthly!$S$10) -> 0 | D83: =SUMIFS('Expense Entry'!$H$11:$H1000,'Expense Entry'!$D$11:$D1000,B83,'Expense Entry'!$Q$11:$Q1000,Monthly!$K$10,'Expense Entry'!$R$11:$R1000,Monthly!$S$10) -> 0 | E83: =SUMIFS('Expense Entry'!$I$11:$I1000,'Expense Entry'!$D$11:$D1000,B83,'Expense Entry'!$Q$11:$Q1000,Monthly!$K$10,'Expense Entry'!$R$11:$R1000,Monthly!$S$10) -> 0
A84: 2042 | B84: ='Setup Page'!P54 | C84: =SUMIFS('Expense Entry'!$F$11:$F1000,'Expense Entry'!$D$11:$D1000,B84,'Expense Entry'!$Q$11:$Q1000,Monthly!$K$10,'Expense Entry'!$R$11:$R1000,Monthly!$S$10) -> 0 | D84: =SUMIFS('Expense Entry'!$H$11:$H1000,'Expense Entry'!$D$11:$D1000,B84,'Expense Entry'!$Q$11:$Q1000,Monthly!$K$10,'Expense Entry'!$R$11:$R1000,Monthly!$S$10) -> 0 | E84: =SUMIFS('Expense Entry'!$I$11:$I1000,'Expense Entry'!$D$11:$D1000,B84,'Expense Entry'!$Q$11:$Q1000,Monthly!$K$10,'Expense Entry'!$R$11:$R1000,Monthly!$S$10) -> 0
A85: 2043 | B85: ='Setup Page'!P55 | C85: =SUMIFS('Expense Entry'!$F$11:$F1000,'Expense Entry'!$D$11:$D1000,B85,'Expense Entry'!$Q$11:$Q1000,Monthly!$K$10,'Expense Entry'!$R$11:$R1000,Monthly!$S$10) -> 0 | D85: =SUMIFS('Expense Entry'!$H$11:$H1000,'Expense Entry'!$D$11:$D1000,B85,'Expense Entry'!$Q$11:$Q1000,Monthly!$K$10,'Expense Entry'!$R$11:$R1000,Monthly!$S$10) -> 0 | E85: =SUMIFS('Expense Entry'!$I$11:$I1000,'Expense Entry'!$D$11:$D1000,B85,'Expense Entry'!$Q$11:$Q1000,Monthly!$K$10,'Expense Entry'!$R$11:$R1000,Monthly!$S$10) -> 0
A86: 2044 | B86: ='Setup Page'!P56 | C86: =SUMIFS('Expense Entry'!$F$11:$F1000,'Expense Entry'!$D$11:$D1000,B86,'Expense Entry'!$Q$11:$Q1000,Monthly!$K$10,'Expense Entry'!$R$11:$R1000,Monthly!$S$10) -> 0 | D86: =SUMIFS('Expense Entry'!$H$11:$H1000,'Expense Entry'!$D$11:$D1000,B86,'Expense Entry'!$Q$11:$Q1000,Monthly!$K$10,'Expense Entry'!$R$11:$R1000,Monthly!$S$10) -> 0 | E86: =SUMIFS('Expense Entry'!$I$11:$I1000,'Expense Entry'!$D$11:$D1000,B86,'Expense Entry'!$Q$11:$Q1000,Monthly!$K$10,'Expense Entry'!$R$11:$R1000,Monthly!$S$10) -> 0
A87: 2045 | B87: ='Setup Page'!P57 | C87: =SUMIFS('Expense Entry'!$F$11:$F1000,'Expense Entry'!$D$11:$D1000,B87,'Expense Entry'!$Q$11:$Q1000,Monthly!$K$10,'Expense Entry'!$R$11:$R1000,Monthly!$S$10) -> 0 | D87: =SUMIFS('Expense Entry'!$H$11:$H1000,'Expense Entry'!$D$11:$D1000,B87,'Expense Entry'!$Q$11:$Q1000,Monthly!$K$10,'Expense Entry'!$R$11:$R1000,Monthly!$S$10) -> 0 | E87: =SUMIFS('Expense Entry'!$I$11:$I1000,'Expense Entry'!$D$11:$D1000,B87,'Expense Entry'!$Q$11:$Q1000,Monthly!$K$10,'Expense Entry'!$R$11:$R1000,Monthly!$S$10) -> 0
A88: 2046 | B88: TOTALS | C88: =SUM(C48:C87) -> 28.8 | D88: =SUM(D48:D87) -> 26.181818 | E88: =SUM(E48:E87) -> 2.6181818
A89: 2047
A90: 2048
A91: 2049
A92: 2050
A93: 2051
A94: 2052
A95: 2053
A96: 2054
A97: 2055
A98: 2056
A99: 2057
A100: 2058
...

Sheet READ ME - Instructions
U2: Explore SerenatasEssentials:
B3: I N S T R U C T I O N S | U3: Discover valuable tools at our other shop for everyday use at SerenatasEssentials. Open the door to new opportunities and discover the ideal tools to elevate your personal endeavors.
B5: - B O O K K E E P I N G G U I D E -
U6: Don't miss out - visit SerenatasEssentials today!
B8: S E R E N A T A S J O U R N E Y | U8: L E T ' S S T A R T
C10: Welcome to your new bookkeeping spreadsheet! | U10: With a few important things...
C12: We are excited to have you here and confident that this template will simplify your financial record-keeping process. Our mission is to provide you with an easy-to-use tool to help you stay on top of your business's financial health and make informed decisions based on accurate data. | V12: This bookkeeping template is for informational purposes only and Serenatas Journey cannot provide any financial, tax, or legal advice. Before making any financial decisions, please do your own research and consult with a licensed financial advisor if necessary. Serenatas Journey will not be held responsible for any costs, losses, damages, or injuries that may result from the use of this spreadsheet.
C17: With this bookkeeping spreadsheet, you can efficiently track your income, expenses, and cash flow, ensuring that your finances are organized and up-to-date. We believe that by taking control of your bookkeeping, you can make better financial decisions and focus on growing your business.
V18: This bookkeeping template is copyrighted by Serenatas Journey and is for personal use only. Commercial or public use of any kind is strictly prohibited, including reselling, sharing, reproducing, or distributing the product, either in part or in full, with or without modifications.
C22: Thank you for choosing our bookkeeping template. We are dedicated to supporting you in managing your finances, and we're always here to answer any questions or concerns you may have. Let's work together to take your business to the next level.
V23: Serenatas Journey is not affiliated with Google Sheets in any way.
V25: Please note that this bookkeeping template can only be used on Google Sheets and is not compatible with Excel. A Google account is required to access the spreadsheet.
J28: Best regards, Anna and her Team | V28: Due to the nature of digital downloads, all sales for this bookkeeping template are final and no returns, exchanges, or cancellations will be accepted.
B32: M A K E Y O U R O W N E D I T A B L E C O P Y | U32: M O S T I M P O R T A N T I N S T R U C T I O N S
C34: To begin working towards your financial goals, it's important to have your own personal, editable copy of the bookkeeping template.
V35: 1. Refer to the Instructions tab for clarification on the bookkeeping template's workings.
C37: It's easy. | V37: 2. Only edit cells that are not color-coded.
C38: Go to the 'File' menu and click on 'Make a Copy'. | V38: 3. When entering transactions, ensure that mandatory fields are filled out, those are Date, Category, and Total amount.
V40: 4. Clear the data within rows and columns, but DO NOT delete them.
C46: IMPORTANT NOTE: PLEASE DO NOT REQUEST 'EDIT' ACCESS
B49: S E T U P P A G E
U52: C U R R E N C Y
U53: From the list of 11 options, choose the currency you would like to use throughout the entire template. If your desired currency is not listed, please contact us.
U56: M O N T H
U57: Select the starting month from the drop-down menu.
U59: Y E A R
U60: This template can be used for any year of your choosing. Simply use the drop-down menu to select the year for which you are starting your bookkeeping journey.
U63: P R O F I T G O A L
U64: Is a feature of the bookkeeping template that allows you to define a specific target profit for your business each month.
C67: C A T E G O R I E S
C68: Simply enter your income and expense categories, with the flexibility to create up to 20 categories in each section. This feature allows you to easily categorize your transactions and gain a better understanding of your business's financial performance. By customizing your categories, you can tailor the bookkeeping template to fit your unique business needs and goals.
B73: I N C O M E / E X P E N S E S E N T R Y
C88: In the Income & Expenses Entry tab of our bookkeeping Google Sheet template, you'll find three mandatory column entries: Date, Category or Product / Service, and Total Amount. These fields ensure that you have a clear record of your business's income & expenses, making it easier for you to track your financial performance. We've also included optional fields like ID, Tax, and fields for Client Tracking in the income Entry, which you can fill in for your convenience. Additionally, you can add a Description and Notes to provide more context for each income & expense transaction. Our goal is to provide you with a customizable and user-friendly tool to streamline your bookkeeping process and make it easy for you to stay on top of your business finances
C93: H I G H L I G H T C A T E G O R Y | U93: T A X R A T E
C94: With this feature, you can highlight a particular income or expense category, and all transactions within that category will be automatically highlighted in the sheet. This feature provides you with a quick and convenient way to search for and analyze specific categories of transactions, saving you time and effort in your bookkeeping process. | U94: Our bookkeeping Google Sheet template offers a convenient and flexible tax rate feature that allows you to set a default tax rate for your business transactions, while also providing the flexibility to modify the tax rate for specific transactions as needed. With this feature, you can set a common tax rate (such as 10%) in the upper right cell, and this rate will automatically apply to all transactions unless you specify a different tax rate in a particular transaction entry.
C99: N E T A M O U N T / T A X A M O U N T
C100: The Net and Tax Amount columns are designed to automatically calculate the net and tax amounts for each transaction based on the total amount and tax rate you've entered, or the default tax rate you have set. This feature saves you time and effort in your bookkeeping process. | U100: T O T A L S
U101: This section provides a fast and convenient way to view your financial data at a glance, including the total amount, net amount, and tax amount for all transactions combined.
B106: M O N T H L Y O V E R V I E W
W109: The Monthly Overview tab in our Bookkeeping Google Sheet template provides a comprehensive summary of your financial data for each month. Here, you can view the total income, total expenses, net income, and tax amount for each month, as well as the percentage of income and expenses for each category.
W115: M O N T H S E L E C T I O N
W116: With this feature, you can quickly navigate to a specific month to view your financial data
W119: F I N A N C E O V E R V I E W
W120: With the amount drop-down list, you can choose what financial data you want to view for each month, selecting to view the total amount, net amount, or tax amount for each month based on your specific needs and preferences.
C125: S U M M A R Y B O A R D
C126: The Summary Board on the left-hand side of our template provides a comprehensive overview of your financial data, displaying key figures including the total income, total expenses, income after tax, month's profit, and monthly profit goal for the selected month. This feature allows you to easily track your financial progress and stay on top of your financial goals, providing a clear and concise summary of your income, expenses, and profits for the month.
B131: A N N U A L O V E R V I E W
V134: The Annual Overview tab provides a comprehensive view of your financial data over the course of the year, including your income, expenses, and profit for each month, as well as your monthly profit goal and year-to-date profit. The tab also includes a section for tracking the tax collected and tax paid, giving you a complete picture of your financial performance
V139: F I N A N C E O V E R V I E W
V140: With the dropdown list feature, you can easily select which financial data you want to view for the entire year. Choose between total amount, net amount, or tax amount for both income and expenses categories, providing you with a comprehensive view of your finances
V145: V A T / S A L E S T A X
V146: The VAT/Tax collected and paid section is a manual entry where you can enter the tax collected and paid amounts from your sales transactions. This section allows you to have a clear record of your tax payments and can help you to prepare for tax season
V150: C A S H F L O W M O N T H B Y M O N T H
V151: The cash flow month by month section provides a detailed breakdown of your net income, total expenses, monthly profit, monthly profit goal, and goal progress for each month
B156: P R O F I T & L O S S C U S T O M O V E R V I E W
C159: In the "Profit & Loss Custom Overview" tab, you have the ability to define a specific date range ("From" - "To") to analyze your financial performance. This tab provides you with valuable insights such as net revenue, gross revenue, net income/loss, gross profit, total gross expenses, total net expenses, direct costs, and operating costs. Additionally, you'll find a comprehensive breakdown of all income and expense categories, showcasing the total, net, and tax amounts for each category within the selected period. This allows you to gain a clear understanding of your financial status and identify trends within your income and expenses.
C164: D A T E P E R I O D | U164: D E F I N E Y O U R E X P E N S E T Y P E
C165: The "Date Period Selection" section allows you to specify a specific time frame for analyzing your financial data. By setting the "From" and "To" dates, you can define the period you want to focus on and generate accurate insights. This feature enables you to easily compare different time intervals, track financial progress over specific durations, and make informed decisions based on the selected date range. | U165: The "Cost Type Assignment" feature allows you to categorize each expense category as either a Direct Cost or an Operating Cost. By utilizing the dropdown selection menu for each expense category, you can easily assign the appropriate cost type. This classification helps you differentiate between expenses directly associated with your products or services (Direct Costs) and those related to your business operations (Operating Costs). The Cost Type Assignment provides a clear breakdown of your expenses, enabling you to analyze their impact on profitability and make strategic financial decisions.
C173: E X P L A N A T I O N O F E A C H C A L C U L A T I O N
C174: Revenue: Net Revenue: The total amount of income generated from selling goods or services, excluding taxes. Gross Revenue: The total amount of income generated from selling goods or services, including taxes. Net Income/Loss: Calculated by adding the Operating Income and Other Income and subtracting any Other Expenses. It represents the final profit or loss for the specified period. Gross Profit: Calculated by subtracting the Cost of Goods Sold (Direct Costs) from the Revenue. It represents the profit generated before considering operating expenses. Direct Costs: Expenses directly associated with producing or acquiring goods, including raw materials, direct labor, or manufacturing costs. Operating Costs: Salaries and Wages: Total employee compensation expenses. Rent and Utilities: Costs related to office space, utilities, and facilities. Marketing and Advertising: Expenses incurred for promoting the business and attracting customers. Depreciation and Amortization: Allocation of the cost of assets over their useful life. Professional Fees: Expenses for legal, accounting, or consulting services. Other Operating Expenses: Miscellaneous expenses not categorized above. Total Gross Expenses: The total amount of expenses, including taxes. Total Net Expenses: The total amount of expenses, excluding taxes.
B194: F R E Q U E N T L Y A S K E D Q U E S T I O N S
C197: CAN I USE THIS TEMPLATE WITH EXCEL INSTEAD OF GOOGLE SHEETS?
C198: Unfortunately, our template is specifically designed for use in Google Sheets and may not function properly if exported to Excel. The formulas and formatting in the spreadsheet have been designed specifically for Google Sheets and may not translate properly when exported to Excel. For the best experience and results, we highly recommend using the template within Google Sheets only. Additionally, Google Sheets is more user-friendly and accessible across all devices, making it the preferred choice for our templates.
C203: CAN I HAVE MORE ROWS ON. . . . . ?
C204: Unfortunately, adding more rows to the template may affect the overall functionality and the formulas. However, we are always here to help and would be happy to make any necessary modifications for you to better meet your needs.
C208: CAN I USE THIS TEMPLATE THE NEXT YEAR ALSO?
C209: Yes, you can definitely use the template for the next year as well. It's always good to have an archive for reference, and creating a new copy for each year is an option. Alternatively, you can keep using the same template and updating the transactions, but this will erase the budget history of previous years. The choice is ultimately yours, but we're here to help you make the best decision for your financial tracking needs.
C213: CAN I CHANGE THE TEMPLATES COLORS?
C214: Yes, our template design allows you to customize the colors easily. To change the colors, you can go to the Format menu, select Theme, and then click on the Customize option. There, you will have the option to change the color palette to match your preferences.
B219: Serenata's Journey Team
B220: "Wishing you success in reaching your financial goals and a bright financial future."

Sheet Setup Page
V2: P I C K Y O U R C U R R E N C Y | AD2: P I C K Y O U R S T A R T M O N T H | AM2: P I C K T H E Y E A R
B3: S E T U P
W4: $ | AD4: July | AM4: 2023
B5: - D A S H B O A R D -
B8: P A Y M E N T M E T H O D S / A C C O U N T S
D10: 1 . | E10: Cash | N10: 4 . | O10: Zelle | X10: 7 . | AH10: 10 .
D11: 2 . | E11: Credit Card | N11: 5 . | X11: 8 . | AH11: 11 .
D12: 3 . | E12: Bank Account | N12: 6 . | X12: 9 . | AH12: 12 .
B15: S E T Y O U R C A T E G O R I E S | AC15: S E T Y O U R M O N T H L Y P R O F I T G O A L S
B17: P R O D U C T S / S E R V I C E S | O17: E X P E N S E | AC17: M O N T H | AK17: G O A L A M O U N T
C18: Investment | P18: Virtual Address | AC18: =DATE(AM4,MONTH(AD4&1),1) -> 45108 | AK18: =IF(AM18="","",$W$4) -> $ | AM18: 0 | AS18: =AC18 -> 45108 | AT18: =AM18 -> 0 | AU18: =month(AC18) -> 7 | AV18: =year(AC18) -> 2023 | AW18: =UPPER(TEXT('Setup Page'!AC18,"mmm yy")) -> JUL 23
C19: Fines | P19: Legal Zoom | AC19: =edate(AC18,1) -> 45139 | AK19: =IF(AM19="","",$W$4) -> $ | AM19: 0 | AS19: =AC19 -> 45139 | AT19: =AM19 -> 0 | AU19: =month(AC19) -> 8 | AV19: =year(AC19) -> 2023 | AW19: =UPPER(TEXT('Setup Page'!AC19,"mmm yy")) -> AUG 23
P20: Google GSuite | AC20: =edate(AC19,1) -> 45170 | AK20: =IF(AM20="","",$W$4) -> $ | AM20: 2400 | AS20: =AC20 -> 45170 | AT20: =AM20 -> 2400 | AU20: =month(AC20) -> 9 | AV20: =year(AC20) -> 2023 | AW20: =UPPER(TEXT('Setup Page'!AC20,"mmm yy")) -> SEP 23
AC21: =edate(AC20,1) -> 45200 | AK21: =IF(AM21="","",$W$4) -> $ | AM21: 2400 | AS21: =AC21 -> 45200 | AT21: =AM21 -> 2400 | AU21: =month(AC21) -> 10 | AV21: =year(AC21) -> 2023 | AW21: =UPPER(TEXT('Setup Page'!AC21,"mmm yy")) -> OCT 23
AC22: =edate(AC21,1) -> 45231 | AK22: =IF(AM22="","",$W$4) -> $ | AM22: 2400 | AS22: =AC22 -> 45231 | AT22: =AM22 -> 2400 | AU22: =month(AC22) -> 11 | AV22: =year(AC22) -> 2023 | AW22: =UPPER(TEXT('Setup Page'!AC22,"mmm yy")) -> NOV 23
AC23: =edate(AC22,1) -> 45261 | AK23: =IF(AM23="","",$W$4) -> $ | AM23: 6000 | AS23: =AC23 -> 45261 | AT23: =AM23 -> 6000 | AU23: =month(AC23) -> 12 | AV23: =year(AC23) -> 2023 | AW23: =UPPER(TEXT('Setup Page'!AC23,"mmm yy")) -> DEC 23
AC24: =edate(AC23,1) -> 45292 | AK24: =IF(AM24="","",$W$4) -> $ | AM24: 6000 | AS24: =AC24 -> 45292 | AT24: =AM24 -> 6000 | AU24: =month(AC24) -> 1 | AV24: =year(AC24) -> 2024 | AW24: =UPPER(TEXT('Setup Page'!AC24,"mmm yy")) -> JAN 24
AC25: =edate(AC24,1) -> 45323 | AK25: =IF(AM25="","",$W$4) -> $ | AM25: 6000 | AS25: =AC25 -> 45323 | AT25: =AM25 -> 6000 | AU25: =month(AC25) -> 2 | AV25: =year(AC25) -> 2024 | AW25: =UPPER(TEXT('Setup Page'!AC25,"mmm yy")) -> FEB 24
AC26: =edate(AC25,1) -> 45352 | AK26: =IF(AM26="","",$W$4) -> $ | AM26: 6000 | AS26: =AC26 -> 45352 | AT26: =AM26 -> 6000 | AU26: =month(AC26) -> 3 | AV26: =year(AC26) -> 2024 | AW26: =UPPER(TEXT('Setup Page'!AC26,"mmm yy")) -> MAR 24
AC27: =edate(AC26,1) -> 45383 | AK27: =IF(AM27="","",$W$4) -> $ | AM27: 6000 | AS27: =AC27 -> 45383 | AT27: =AM27 -> 6000 | AU27: =month(AC27) -> 4 | AV27: =year(AC27) -> 2024 | AW27: =UPPER(TEXT('Setup Page'!AC27,"mmm yy")) -> APR 24
AC28: =edate(AC27,1) -> 45413 | AK28: =IF(AM28="","",$W$4) -> $ | AM28: 6000 | AS28: =AC28 -> 45413 | AT28: =AM28 -> 6000 | AU28: =month(AC28) -> 5 | AV28: =year(AC28) -> 2024 | AW28: =UPPER(TEXT('Setup Page'!AC28,"mmm yy")) -> MAY 24
AC29: =edate(AC28,1) -> 45444 | AK29: =IF(AM29="","",$W$4) -> $ | AM29: 6000 | AS29: =AC29 -> 45444 | AT29: =AM29 -> 6000 | AU29: =month(AC29) -> 6 | AV29: =year(AC29) -> 2024 | AW29: =UPPER(TEXT('Setup Page'!AC29,"mmm yy")) -> JUN 24
AC31: A N N U A L P R O F I T G O A L
AE33: =W4 -> $ | AG33: =SUM(AM18:AQ29) -> 49200
AC36: I N C O M E E N T R Y | AK36: E X P E N S E E N T R Y
C58: EMPTY | P58: EMPTY

Sheet Income Entry
I2: H I G H L I G H T C L I E N T S N A M E / L A S T N A M E | L2: H I G H L I G H T P R O D U C T / S E R V I C E | P2: M O S T C O M M O N T A X R A T E ( % )
B3: I N C O M E
I4: F I R S T N A M E : | J4: Oluwafemi | L4: EMPTY | P4: 0
B5: - E N T R Y - | I5: L A S T N A M E :
E8: T O T A L I N C O M E | F8: =SUM(F11:F1002) -> 239652.06 | H8: =SUM(H11:H1002) -> 239652.06 | I8: =SUM(I11:I1002) -> 0
B9: I D | C9: D A T E | D9: F I R S T N A M E | E9: L A S T N A M E | F9: T O T A L A M O U N T | G9: T A X % | H9: N E T A M O U N T | I9: T A X A M O U N T | J9: P A I D W I T H | L9: P R O D U C T / S E R V I C E | M9: D E S C R I P T I O N | O9: A D D R E S S | P9: T E L . N U M B E R | Q9: E - M A I L
H10: =F10-I10 -> 0 | I10: =F10-(F10/(1+IF(G10="",$P$4,G10))) -> 0
B11: 100001 | C11: 45041 | D11: Oladapo | E11: Ajala | F11: 400 | H11: =F11-I11 -> 400 | I11: =F11-(F11/(1+IF(G11="",$P$4,G11))) -> 0 | J11: Zelle | L11: Investment | S11: =IF(C11="","",MONTH(C11)) -> 4 | T11: =IF(C11="","",YEAR(C11)) -> 2023
B12: =B11+1 -> 100002 | C12: 45033 | D12: Temitope | E12: Ajibola | F12: 200 | H12: =F12-I12 -> 200 | I12: =F12-(F12/(1+IF(G12="",$P$4,G12))) -> 0 | J12: Zelle | L12: Investment | S12: =IF(C12="","",MONTH(C12)) -> 4 | T12: =IF(C12="","",YEAR(C12)) -> 2023
B13: =B12+1 -> 100003 | C13: 45011 | D13: Abiodun | E13: Akindele | F13: 200 | H13: =F13-I13 -> 200 | I13: =F13-(F13/(1+IF(G13="",$P$4,G13))) -> 0 | J13: Zelle | L13: Investment | S13: =IF(C13="","",MONTH(C13)) -> 3 | T13: =IF(C13="","",YEAR(C13)) -> 2023
B14: =B13+1 -> 100004 | C14: 45005 | D14: Olurotimi | E14: Dosumu | F14: 200 | H14: =F14-I14 -> 200 | I14: =F14-(F14/(1+IF(G14="",$P$4,G14))) -> 0 | J14: Zelle | L14: Investment | S14: =IF(C14="","",MONTH(C14)) -> 3 | T14: =IF(C14="","",YEAR(C14)) -> 2023
B15: =B14+1 -> 100005 | C15: 44993 | D15: Oluwafemi | E15: Durojaiye | F15: 200 | H15: =F15-I15 -> 200 | I15: =F15-(F15/(1+IF(G15="",$P$4,G15))) -> 0 | J15: Zelle | L15: Investment | S15: =IF(C15="","",MONTH(C15)) -> 3 | T15: =IF(C15="","",YEAR(C15)) -> 2023
B16: =B15+1 -> 100006 | C16: 44993 | D16: Olatunji | E16: Ilori | F16: 200 | H16: =F16-I16 -> 200 | I16: =F16-(F16/(1+IF(G16="",$P$4,G16))) -> 0 | J16: Zelle | L16: Investment | S16: =IF(C16="","",MONTH(C16)) -> 3 | T16: =IF(C16="","",YEAR(C16)) -> 2023
B17: =B16+1 -> 100007 | C17: 44994 | D17: Oluremi | E17: Makinde | F17: 200 | H17: =F17-I17 -> 200 | I17: =F17-(F17/(1+IF(G17="",$P$4,G17))) -> 0 | J17: Zelle | L17: Investment | S17: =IF(C17="","",MONTH(C17)) -> 3 | T17: =IF(C17="","",YEAR(C17)) -> 2023
B18: =B17+1 -> 100008 | C18: 44993 | D18: Jamiu | E18: Momodu | F18: 200 | H18: =F18-I18 -> 200 | I18: =F18-(F18/(1+IF(G18="",$P$4,G18))) -> 0 | J18: Zelle | L18: Investment | S18: =IF(C18="","",MONTH(C18)) -> 3 | T18: =IF(C18="","",YEAR(C18)) -> 2023
B19: =B18+1 -> 100009 | C19: 44996 | D19: Opeyemi | E19: Olomola | F19: 200 | H19: =F19-I19 -> 200 | I19: =F19-(F19/(1+IF(G19="",$P$4,G19))) -> 0 | J19: Zelle | L19: Investment | S19: =IF(C19="","",MONTH(C19)) -> 3 | T19: =IF(C19="","",YEAR(C19)) -> 2023
B20: =B19+1 -> 100010 | C20: 45013 | D20: Temitope | E20: Olutola | F20: 200 | H20: =F20-I20 -> 200 | I20: =F20-(F20/(1+IF(G20="",$P$4,G20))) -> 0 | J20: Zelle | L20: Investment | S20: =IF(C20="","",MONTH(C20)) -> 3 | T20: =IF(C20="","",YEAR(C20)) -> 2023
B21: =B20+1 -> 100011 | C21: 45010 | D21: Olumuyiwa | E21: Shoneye | F21: 200 | H21: =F21-I21 -> 200 | I21: =F21-(F21/(1+IF(G21="",$P$4,G21))) -> 0 | J21: Zelle | L21: Investment | S21: =IF(C21="","",MONTH(C21)) -> 3 | T21: =IF(C21="","",YEAR(C21)) -> 2023
B22: =B21+1 -> 100012 | C22: 45038 | D22: Dimeji | E22: Sule | F22: 400 | H22: =F22-I22 -> 400 | I22: =F22-(F22/(1+IF(G22="",$P$4,G22))) -> 0 | J22: Zelle | L22: Investment | S22: =IF(C22="","",MONTH(C22)) -> 4 | T22: =IF(C22="","",YEAR(C22)) -> 2023
B23: =B22+1 -> 100013 | C23: 44995 | D23: Temitope | E23: Ajibola | F23: 200 | H23: =F23-I23 -> 200 | I23: =F23-(F23/(1+IF(G23="",$P$4,G23))) -> 0 | J23: Zelle | L23: Investment | S23: =IF(C23="","",MONTH(C23)) -> 3 | T23: =IF(C23="","",YEAR(C23)) -> 2023
... B69: =B68+1 -> 100059 | C69: 45147 | D69: Dimeji | E69: Sule | F69: 500 | H69: =F69-I69 -> 500 | I69: =F69-(F69/(1+IF(G69="",$P$4,G69))) -> 0 | J69: Zelle | L69: Investment | S69: =IF(C69="","",MONTH(C69)) -> 8 | T69: =IF(C69="","",YEAR(C69)) -> 2023
B70: =B69+1 -> 100060 | C70: 45153 | D70: Oluremi | E70: Makinde | F70: 500 | H70: 500 | I70: =F70-(F70/(1+IF(G70="",$P$4,G70))) -> 0 | J70: Zelle | L70: Investment | S70: =IF(C70="","",MONTH(C70)) -> 8 | T70: =IF(C70="","",YEAR(C70)) -> 2023
B71: =B70+1 -> 100061 | C71: 45154 | D71: Oluwafemi | E71: Durojaiye | F71: 500 | H71: =F71-I71 -> 500 | I71: =F71-(F71/(1+IF(G71="",$P$4,G71))) -> 0 | J71: Zelle | L71: Investment | S71: =IF(C71="","",MONTH(C71)) -> 8 | T71: =IF(C71="","",YEAR(C71)) -> 2023
B72: =B71+1 -> 100062 | C72: 45154 | D72: Dimeji | E72: Sule | F72: 500 | H72: =F72-I72 -> 500 | I72: =F72-(F72/(1+IF(G72="",$P$4,G72))) -> 0 | J72: Zelle | L72: Investment | S72: =IF(C72="","",MONTH(C72)) -> 8 | T72: =IF(C72="","",YEAR(C72)) -> 2023
B73: =B72+1 -> 100063 | C73: 45155 | D73: Oladapo | E73: Ajala | F73: 500 | H73: =F73-I73 -> 500 | I73: =F73-(F73/(1+IF(G73="",$P$4,G73))) -> 0 | J73: Zelle | L73: Investment | S73: =IF(C73="","",MONTH(C73)) -> 8 | T73: =IF(C73="","",YEAR(C73)) -> 2023
B74: =B73+1 -> 100064 | C74: 45155 | D74: Temitope | E74: Olutola | F74: 500 | H74: =F74-I74 -> 500 | I74: =F74-(F74/(1+IF(G74="",$P$4,G74))) -> 0 | J74: Zelle | L74: Investment | S74: =IF(C74="","",MONTH(C74)) -> 8 | T74: =IF(C74="","",YEAR(C74)) -> 2023
B75: =B74+1 -> 100065 | C75: 45159 | D75: Abiodun | E75: Akindele | F75: 500 | H75: =F75-I75 -> 500 | I75: =F75-(F75/(1+IF(G75="",$P$4,G75))) -> 0 | J75: Zelle | L75: Investment | S75: =IF(C75="","",MONTH(C75)) -> 8 | T75: =IF(C75="","",YEAR(C75)) -> 2023
B76: =B75+1 -> 100066 | C76: 45160 | D76: Olumuyiwa | E76: Shoneye | F76: 550 | H76: =F76-I76 -> 550 | I76: =F76-(F76/(1+IF(G76="",$P$4,G76))) -> 0 | J76: Zelle | L76: Investment | S76: =IF(C76="","",MONTH(C76)) -> 8 | T76: =IF(C76="","",YEAR(C76)) -> 2023
B77: =B76+1 -> 100067 | C77: 45163 | D77: Temitope | E77: Ajibola | F77: 500 | H77: =F77-I77 -> 500 | I77: =F77-(F77/(1+IF(G77="",$P$4,G77))) -> 0 | J77: Zelle | L77: Investment | S77: =IF(C77="","",MONTH(C77)) -> 8 | T77: =IF(C77="","",YEAR(C77)) -> 2023
B78: =B77+1 -> 100068 | C78: 45167 | D78: Olurotimi | E78: Dosumu | F78: 500 | H78: =F78-I78 -> 500 | I78: =F78-(F78/(1+IF(G78="",$P$4,G78))) -> 0 | J78: Zelle | L78: Investment | S78: =IF(C78="","",MONTH(C78)) -> 8 | T78: =IF(C78="","",YEAR(C78)) -> 2023
B79: =B78+1 -> 100069 | C79: 45167 | D79: Olatunji | E79: Ilori | F79: 500 | H79: =F79-I79 -> 500 | I79: =F79-(F79/(1+IF(G79="",$P$4,G79))) -> 0 | J79: Zelle | L79: Investment | S79: =IF(C79="","",MONTH(C79)) -> 8 | T79: =IF(C79="","",YEAR(C79)) -> 2023
B80: =B79+1 -> 100070 | C80: 45170 | D80: Opeyemi | E80: Olomola | F80: 500 | H80: =F80-I80 -> 500 | I80: =F80-(F80/(1+IF(G80="",$P$4,G80))) -> 0 | J80: Zelle | L80: Investment | S80: =IF(C80="","",MONTH(C80)) -> 9 | T80: =IF(C80="","",YEAR(C80)) -> 2023
B81: =B80+1 -> 100071 | C81: 45174 | D81: Jamiu | E81: Momodu | F81: 500 | H81: =F81-I81 -> 500 | I81: =F81-(F81/(1+IF(G81="",$P$4,G81))) -> 0 | J81: Zelle | L81: Investment | S81: =IF(C81="","",MONTH(C81)) -> 9 | T81: =IF(C81="","",YEAR(C81)) -> 2023
B82: =B81+1 -> 100072 | C82: 45184 | D82: Temitope | E82: Ajibola | F82: 500 | H82: =F82-I82 -> 500 | I82: =F82-(F82/(1+IF(G82="",$P$4,G82))) -> 0 | J82: Zelle | L82: Investment | S82: =IF(C82="","",MONTH(C82)) -> 9 | T82: =IF(C82="","",YEAR(C82)) -> 2023
... B138: =B137+1 -> 100128 | C138: 45322 | D138: Olatunji | E138: Ilori | F138: 500 | H138: =F138-I138 -> 500 | I138: =F138-(F138/(1+IF(G138="",$P$4,G138))) -> 0 | J138: Zelle | L138: Investment | S138: =IF(C138="","",MONTH(C138)) -> 1 | T138: =IF(C138="","",YEAR(C138)) -> 2024
B139: =B138+1 -> 100129 | C139: 45322 | D139: Axios | E139: Interest | F139: 192.05 | H139: =F139-I139 -> 192.05 | I139: =F139-(F139/(1+IF(G139="",$P$4,G139))) -> 0 | J139: Bank Account | S139: =IF(C139="","",MONTH(C139)) -> 1 | T139: =IF(C139="","",YEAR(C139)) -> 2024
B140: =B139+1 -> 100130 | C140: 45327 | D140: Opeyemi | E140: Olomola | F140: 1000 | H140: =F140-I140 -> 1000 | I140: =F140-(F140/(1+IF(G140="",$P$4,G140))) -> 0 | J140: Zelle | L140: Investment | S140: =IF(C140="","",MONTH(C140)) -> 2 | T140: =IF(C140="","",YEAR(C140)) -> 2024
B141: =B140+1 -> 100131 | C141: 45329 | D141: Oluwafemi | E141: Durojaiye | F141: 600 | H141: =F141-I141 -> 600 | I141: =F141-(F141/(1+IF(G141="",$P$4,G141))) -> 0 | J141: Zelle | L141: Investment | S141: =IF(C141="","",MONTH(C141)) -> 2 | T141: =IF(C141="","",YEAR(C141)) -> 2024
B142: =B141+1 -> 100132 | C142: 45334 | D142: Temitope | E142: Olutola | F142: 1500 | H142: =F142-I142 -> 1500 | I142: =F142-(F142/(1+IF(G142="",$P$4,G142))) -> 0 | J142: Zelle | L142: Investment | S142: =IF(C142="","",MONTH(C142)) -> 2 | T142: =IF(C142="","",YEAR(C142)) -> 2024
B143: =B142+1 -> 100133 | C143: 45337 | D143: Dimeji | E143: Sule | F143: 500 | H143: =F143-I143 -> 500 | I143: =F143-(F143/(1+IF(G143="",$P$4,G143))) -> 0 | J143: Zelle | L143: Investment | S143: =IF(C143="","",MONTH(C143)) -> 2 | T143: =IF(C143="","",YEAR(C143)) -> 2024
B144: =B143+1 -> 100134 | C144: 45338 | D144: Jamiu | E144: Momodu | F144: 500 | H144: =F144-I144 -> 500 | I144: =F144-(F144/(1+IF(G144="",$P$4,G144))) -> 0 | J144: Zelle | L144: Investment | S144: =IF(C144="","",MONTH(C144)) -> 2 | T144: =IF(C144="","",YEAR(C144)) -> 2024
B145: =B144+1 -> 100135 | C145: 45342 | D145: Temitope | E145: Ajibola | F145: 1000 | H145: =F145-I145 -> 1000 | I145: =F145-(F145/(1+IF(G145="",$P$4,G145))) -> 0 | J145: Zelle | L145: Investment | S145: =IF(C145="","",MONTH(C145)) -> 2 | T145: =IF(C145="","",YEAR(C145)) -> 2024
B146: =B145+1 -> 100136 | C146: 45342 | D146: Abiodun | E146: Akindele | F146: 500 | H146: =F146-I146 -> 500 | I146: =F146-(F146/(1+IF(G146="",$P$4,G146))) -> 0 | J146: Zelle | L146: Investment | S146: =IF(C146="","",MONTH(C146)) -> 2 | T146: =IF(C146="","",YEAR(C146)) -> 2024
B147: =B146+1 -> 100137 | C147: 45344 | D147: Oladapo | E147: Ajala | F147: 500 | H147: =F147-I147 -> 500 | I147: =F147-(F147/(1+IF(G147="",$P$4,G147))) -> 0 | J147: Zelle | L147: Investment | S147: =IF(C147="","",MONTH(C147)) -> 2 | T147: =IF(C147="","",YEAR(C147)) -> 2024
B148: =B147+1 -> 100138 | C148: 45348 | D148: Olurotimi | E148: Dosumu | F148: 2500 | H148: =F148-I148 -> 2500 | I148: =F148-(F148/(1+IF(G148="",$P$4,G148))) -> 0 | J148: Zelle | L148: Investment | S148: =IF(C148="","",MONTH(C148)) -> 2 | T148: =IF(C148="","",YEAR(C148)) -> 2024
B149: =B148+1 -> 100139 | C149: 45348 | D149: Oluwafemi | E149: Durojaiye | F149: 1000 | H149: =F149-I149 -> 1000 | I149: =F149-(F149/(1+IF(G149="",$P$4,G149))) -> 0 | J149: Zelle | L149: Investment | S149: =IF(C149="","",MONTH(C149)) -> 2 | T149: =IF(C149="","",YEAR(C149)) -> 2024
B150: =B149+1 -> 100140 | C150: 45348 | D150: Olatunji | E150: Ilori | F150: 500 | H150: =F150-I150 -> 500 | I150: =F150-(F150/(1+IF(G150="",$P$4,G150))) -> 0 | J150: Zelle | L150: Investment | S150: =IF(C150="","",MONTH(C150)) -> 2 | T150: =IF(C150="","",YEAR(C150)) -> 2024
B151: =B150+1 -> 100141 | C151: 45349 | D151: Olumuyiwa | E151: Shoneye | F151: 500 | H151: =F151-I151 -> 500 | I151: =F151-(F151/(1+IF(G151="",$P$4,G151))) -> 0 | J151: Zelle | L151: Investment | S151: =IF(C151="","",MONTH(C151)) -> 2 | T151: =IF(C151="","",YEAR(C151)) -> 2024
B152: =B151+1 -> 100142 | C152: 45351 | D152: Oluremi | E152: Makinde | F152: 1500 | H152: =F152-I152 -> 1500 | I152: =F152-(F152/(1+IF(G152="",$P$4,G152))) -> 0 | J152: Zelle | L152: Investment | S152: =IF(C152="","",MONTH(C152)) -> 2 | T152: =IF(C152="","",YEAR(C152)) -> 2024
B153: =B152+1 -> 100143 | C153: 45351 | D153: Axios | E153: Interest | F153: 225.41 | H153: =F153-I153 -> 225.41 | I153: =F153-(F153/(1+IF(G153="",$P$4,G153))) -> 0 | J153: Bank Account | S153: =IF(C153="","",MONTH(C153)) -> 2 | T153: =IF(C153="","",YEAR(C153)) -> 2024
B154: =B153+1 -> 100144 | C154: 45362 | D154: Temitope | E154: Olutola | F154: 1500 | H154: =F154-I154 -> 1500 | I154: =F154-(F154/(1+IF(G154="",$P$4,G154))) -> 0 | J154: Zelle | L154: Investment | S154: =IF(C154="","",MONTH(C154)) -> 3 | T154: =IF(C154="","",YEAR(C154)) -> 2024
B155: =B154+1 -> 100145 | C155: 45366 | D155: Jamiu | E155: Momodu | F155: 3000 | H155: =F155-I155 -> 3000 | I155: =F155-(F155/(1+IF(G155="",$P$4,G155))) -> 0 | J155: Zelle | L155: Investment | S155: =IF(C155="","",MONTH(C155)) -> 3 | T155: =IF(C155="","",YEAR(C155)) -> 2024
B156: =B155+1 -> 100146 | C156: 45366 | D156: Dimeji | E156: Sule | F156: 500 | H156: =F156-I156 -> 500 | I156: =F156-(F156/(1+IF(G156="",$P$4,G156))) -> 0 | J156: Zelle | L156: Investment | S156: =IF(C156="","",MONTH(C156)) -> 3 | T156: =IF(C156="","",YEAR(C156)) -> 2024
B157: =B156+1 -> 100147 | C157: 45369 | D157: Temitope | E157: Ajibola | F157: 2000 | H157: =F157-I157 -> 2000 | I157: =F157-(F157/(1+IF(G157="",$P$4,G157))) -> 0 | J157: Zelle | L157: Investment | S157: =IF(C157="","",MONTH(C157)) -> 3 | T157: =IF(C157="","",YEAR(C157)) -> 2024
B158: =B157+1 -> 100148 | C158: 45369 | D158: Temitope | E158: Olutola | F158: 1000 | H158: =F158-I158 -> 1000 | I158: =F158-(F158/(1+IF(G158="",$P$4,G158))) -> 0 | J158: Zelle | L158: Investment | S158: =IF(C158="","",MONTH(C158)) -> 3 | T158: =IF(C158="","",YEAR(C158)) -> 2024
B159: =B158+1 -> 100149 | C159: 45369 | D159: Temitope | E159: Ajibola | F159: 500 | H159: =F159-I159 -> 500 | I159: =F159-(F159/(1+IF(G159="",$P$4,G159))) -> 0 | J159: Zelle | L159: Investment | S159: =IF(C159="","",MONTH(C159)) -> 3 | T159: =IF(C159="","",YEAR(C159)) -> 2024
B160: =B159+1 -> 100150 | C160: 45369 | D160: Abiodun | E160: Akindele | F160: 500 | H160: =F160-I160 -> 500 | I160: =F160-(F160/(1+IF(G160="",$P$4,G160))) -> 0 | J160: Zelle | L160: Investment | S160: =IF(C160="","",MONTH(C160)) -> 3 | T160: =IF(C160="","",YEAR(C160)) -> 2024
B161: =B160+1 -> 100151 | C161: 45370 | D161: Oluremi | E161: Makinde | F161: 2000 | H161: =F161-I161 -> 2000 | I161: =F161-(F161/(1+IF(G161="",$P$4,G161))) -> 0 | J161: Zelle | L161: Investment | S161: =IF(C161="","",MONTH(C161)) -> 3 | T161: =IF(C161="","",YEAR(C161)) -> 2024
B162: =B161+1 -> 100152 | C162: 45373 | D162: Oluremi | E162: Makinde | F162: 1000 | H162: =F162-I162 -> 1000 | I162: =F162-(F162/(1+IF(G162="",$P$4,G162))) -> 0 | J162: Zelle | L162: Investment | S162: =IF(C162="","",MONTH(C162)) -> 3 | T162: =IF(C162="","",YEAR(C162)) -> 2024
B163: =B162+1 -> 100153 | C163: 45378 | D163: Olatunji | E163: Ilori | F163: 3000 | H163: =F163-I163 -> 3000 | I163: =F163-(F163/(1+IF(G163="",$P$4,G163))) -> 0 | J163: Zelle | L163: Investment | S163: =IF(C163="","",MONTH(C163)) -> 3 | T163: =IF(C163="","",YEAR(C163)) -> 2024
B164: =B163+1 -> 100154 | C164: 45378 | D164: Oluwafemi | E164: Durojaiye | F164: 500 | H164: =F164-I164 -> 500 | I164: =F164-(F164/(1+IF(G164="",$P$4,G164))) -> 0 | J164: Zelle | L164: Investment | S164: =IF(C164="","",MONTH(C164)) -> 3 | T164: =IF(C164="","",YEAR(C164)) -> 2024
B165: =B164+1 -> 100155 | C165: 45379 | D165: Olatunji | E165: Ilori | F165: 2000 | H165: =F165-I165 -> 2000 | I165: =F165-(F165/(1+IF(G165="",$P$4,G165))) -> 0 | J165: Zelle | L165: Investment | S165: =IF(C165="","",MONTH(C165)) -> 3 | T165: =IF(C165="","",YEAR(C165)) -> 2024
... B169: =B168+1 -> 100159 | C169: 45381 | D169: Axios | E169: Interest | F169: 276.84 | H169: =F169-I169 -> 276.84 | I169: =F169-(F169/(1+IF(G169="",$P$4,G169))) -> 0 | J169: Bank Account | L169: Investment | S169: =IF(C169="","",MONTH(C169)) -> 3 | T169: =IF(C169="","",YEAR(C169)) -> 2024
B170: =B169+1 -> 100160 | C170: 45383 | D170: Olatunji | E170: Ilori | F170: 500 | H170: =F170-I170 -> 500 | I170: =F170-(F170/(1+IF(G170="",$P$4,G170))) -> 0 | J170: Zelle | S170: =IF(C170="","",MONTH(C170)) -> 4 | T170: =IF(C170="","",YEAR(C170)) -> 2024
B171: =B170+1 -> 100161 | C171: 45383 | D171: Opeyemi | E171: Olomola | F171: 3000 | H171: =F171-I171 -> 3000 | I171: =F171-(F171/(1+IF(G171="",$P$4,G171))) -> 0 | J171: Zelle | S171: =IF(C171="","",MONTH(C171)) -> 4 | T171: =IF(C171="","",YEAR(C171)) -> 2024
B172: =B171+1 -> 100162 | C172: 45394 | D172: Oladapo | E172: Ajala | F172: 2500 | H172: =F172-I172 -> 2500 | I172: =F172-(F172/(1+IF(G172="",$P$4,G172))) -> 0 | J172: Zelle | S172: =IF(C172="","",MONTH(C172)) -> 4 | T172: =IF(C172="","",YEAR(C172)) -> 2024
B173: =B172+1 -> 100163 | C173: 45397 | D173: Abiodun | E173: Akindele | F173: 1000 | H173: =F173-I173 -> 1000 | I173: =F173-(F173/(1+IF(G173="",$P$4,G173))) -> 0 | J173: Zelle | S173: =IF(C173="","",MONTH(C173)) -> 4 | T173: =IF(C173="","",YEAR(C173)) -> 2024
B174: =B173+1 -> 100164 | C174: 45397 | D174: Temitope | E174: Olutola | F174: 500 | H174: =F174-I174 -> 500 | I174: =F174-(F174/(1+IF(G174="",$P$4,G174))) -> 0 | J174: Zelle | S174: =IF(C174="","",MONTH(C174)) -> 4 | T174: =IF(C174="","",YEAR(C174)) -> 2024
B175: =B174+1 -> 100165 | C175: 45397 | D175: Jamiu | E175: Momodu | F175: 500 | H175: =F175-I175 -> 500 | I175: =F175-(F175/(1+IF(G175="",$P$4,G175))) -> 0 | J175: Zelle | S175: =IF(C175="","",MONTH(C175)) -> 4 | T175: =IF(C175="","",YEAR(C175)) -> 2024
B176: =B175+1 -> 100166 | C176: 45397 | D176: Dimeji | E176: Sule | F176: 500 | H176: =F176-I176 -> 500 | I176: =F176-(F176/(1+IF(G176="",$P$4,G176))) -> 0 | J176: Zelle | S176: =IF(C176="","",MONTH(C176)) -> 4 | T176: =IF(C176="","",YEAR(C176)) -> 2024
B177: =B176+1 -> 100167 | C177: 45399 | D177: Temitope | E177: Ajibola | F177: 500 | H177: =F177-I177 -> 500 | I177: =F177-(F177/(1+IF(G177="",$P$4,G177))) -> 0 | J177: Zelle | S177: =IF(C177="","",MONTH(C177)) -> 4 | T177: =IF(C177="","",YEAR(C177)) -> 2024
B178: =B177+1 -> 100168 | C178: 45404 | D178: Oluwafemi | E178: Durojaiye | F178: 1500 | H178: =F178-I178 -> 1500 | I178: =F178-(F178/(1+IF(G178="",$P$4,G178))) -> 0 | J178: Zelle | S178: =IF(C178="","",MONTH(C178)) -> 4 | T178: =IF(C178="","",YEAR(C178)) -> 2024
B179: =B178+1 -> 100169 | C179: 45408 | D179: Olumuyiwa | E179: Shoneye | F179: 500 | H179: =F179-I179 -> 500 | I179: =F179-(F179/(1+IF(G179="",$P$4,G179))) -> 0 | J179: Zelle | S179: =IF(C179="","",MONTH(C179)) -> 4 | T179: =IF(C179="","",YEAR(C179)) -> 2024
B180: =B179+1 -> 100170 | C180: 45411 | D180: Abiodun | E180: Akindele | F180: 500 | H180: =F180-I180 -> 500 | I180: =F180-(F180/(1+IF(G180="",$P$4,G180))) -> 0 | J180: Zelle | S180: =IF(C180="","",MONTH(C180)) -> 4 | T180: =IF(C180="","",YEAR(C180)) -> 2024
B181: =B180+1 -> 100171 | C181: 45411 | D181: Oluremi | E181: Makinde | F181: 500 | H181: =F181-I181 -> 500 | I181: =F181-(F181/(1+IF(G181="",$P$4,G181))) -> 0 | J181: Zelle | S181: =IF(C181="","",MONTH(C181)) -> 4 | T181: =IF(C181="","",YEAR(C181)) -> 2024
... B196: =B195+1 -> 100186 | C196: 45455 | D196: Opeyemi | E196: Olomola | F196: 1500 | H196: =F196-I196 -> 1500 | I196: =F196-(F196/(1+IF(G196="",$P$4,G196))) -> 0 | J196: Zelle | S196: =IF(C196="","",MONTH(C196)) -> 6 | T196: =IF(C196="","",YEAR(C196)) -> 2024
B197: =B196+1 -> 100187 | C197: 45457 | D197: Jamiu | E197: Momodu | F197: 700 | H197: =F197-I197 -> 700 | I197: =F197-(F197/(1+IF(G197="",$P$4,G197))) -> 0 | J197: Zelle | S197: =IF(#REF!="","",MONTH(#REF!)) -> #REF! | T197: =IF(#REF!="","",YEAR(#REF!)) -> #REF!
B198: =B197+1 -> 100188 | C198: 45460 | D198: Temitope | E198: Ajibola | F198: 600 | H198: =F198-I198 -> 600 | I198: =F198-(F198/(1+IF(G198="",$P$4,G198))) -> 0 | J198: Zelle | S198: =IF(C197="","",MONTH(C197)) -> 6 | T198: =IF(C197="","",YEAR(C197)) -> 2024
B199: =B198+1 -> 100189 | C199: 45460 | D199: Dimeji | E199: Sule | F199: 500 | H199: =F199-I199 -> 500 | I199: =F199-(F199/(1+IF(G199="",$P$4,G199))) -> 0 | J199: Zelle | S199: =IF(C199="","",MONTH(C199)) -> 6 | T199: =IF(C199="","",YEAR(C199)) -> 2024
B200: =B199+1 -> 100190 | C200: 45469 | D200: Temitope | E200: Olutola | F200: 800 | H200: =F200-I200 -> 800 | I200: =F200-(F200/(1+IF(G200="",$P$4,G200))) -> 0 | J200: Zelle | S200: =IF(C200="","",MONTH(C200)) -> 6 | T200: =IF(C200="","",YEAR(C200)) -> 2024
B201: =B200+1 -> 100191 | C201: 45470 | D201: Abiodun | E201: Akindele | F201: 500 | H201: =F201-I201 -> 500 | I201: =F201-(F201/(1+IF(G201="",$P$4,G201))) -> 0 | J201: Zelle | S201: =IF(C201="","",MONTH(C201)) -> 6 | T201: =IF(C201="","",YEAR(C201)) -> 2024
B202: =B201+1 -> 100192 | C202: 45470 | D202: Olumuyiwa | E202: Shoneye | F202: 500 | H202: =F202-I202 -> 500 | I202: =F202-(F202/(1+IF(G202="",$P$4,G202))) -> 0 | J202: Zelle | S202: =IF(C202="","",MONTH(C202)) -> 6 | T202: =IF(C202="","",YEAR(C202)) -> 2024
B203: =B202+1 -> 100193 | C203: 45471 | D203: Oladapo | E203: Ajala | F203: 1500 | H203: =F203-I203 -> 1500 | I203: =F203-(F203/(1+IF(G203="",$P$4,G203))) -> 0 | J203: Zelle | S203: =IF(C203="","",MONTH(C203)) -> 6 | T203: =IF(C203="","",YEAR(C203)) -> 2024
B204: =B203+1 -> 100194 | C204: 45474 | D204: Olatunji | E204: Ilori | F204: 500 | H204: =F204-I204 -> 500 | I204: =F204-(F204/(1+IF(G204="",$P$4,G204))) -> 0 | J204: Zelle | S204: =IF(C204="","",MONTH(C204)) -> 7 | T204: =IF(C204="","",YEAR(C204)) -> 2024
B205: =B204+1 -> 100195 | C205: 45474 | D205: Oluwafemi | E205: Durojaiye | F205: 500 | H205: =F205-I205 -> 500 | I205: =F205-(F205/(1+IF(G205="",$P$4,G205))) -> 0 | J205: Zelle | S205: =IF(C205="","",MONTH(C205)) -> 7 | T205: =IF(C205="","",YEAR(C205)) -> 2024
B206: =B205+1 -> 100196 | C206: 45488 | D206: Jamiu | E206: Momodu | F206: 800 | H206: =F206-I206 -> 800 | I206: =F206-(F206/(1+IF(G206="",$P$4,G206))) -> 0 | J206: Zelle | S206: =IF(C206="","",MONTH(C206)) -> 7 | T206: =IF(C206="","",YEAR(C206)) -> 2024
B207: =B206+1 -> 100197 | C207: 45488 | D207: Temitope | E207: Ajibola | F207: 500 | H207: =F207-I207 -> 500 | I207: =F207-(F207/(1+IF(G207="",$P$4,G207))) -> 0 | J207: Zelle | S207: =IF(C207="","",MONTH(C207)) -> 7 | T207: =IF(C207="","",YEAR(C207)) -> 2024
B208: =B207+1 -> 100198 | C208: 45490 | D208: Dimeji | E208: Sule | F208: 500 | H208: =F208-I208 -> 500 | I208: =F208-(F208/(1+IF(G208="",$P$4,G208))) -> 0 | J208: Zelle | S208: =IF(C208="","",MONTH(C208)) -> 7 | T208: =IF(C208="","",YEAR(C208)) -> 2024
B209: =B208+1 -> 100199 | C209: 45492 | D209: Opeyemi | E209: Olomola | F209: 1000 | H209: =F209-I209 -> 1000 | I209: =F209-(F209/(1+IF(G209="",$P$4,G209))) -> 0 | J209: Zelle | S209: =IF(C209="","",MONTH(C209)) -> 7 | T209: =IF(C209="","",YEAR(C209)) -> 2024
B210: =B209+1 -> 100200 | C210: 45495 | D210: Abiodun | E210: Akindele | F210: 500 | H210: =F210-I210 -> 500 | I210: =F210-(F210/(1+IF(G210="",$P$4,G210))) -> 0 | J210: Zelle | S210: =IF(C210="","",MONTH(C210)) -> 7 | T210: =IF(C210="","",YEAR(C210)) -> 2024
... B227: =B226+1 -> 100217 | C227: 45530 | D227: Temitope | E227: Olutola | F227: 400 | H227: =F227-I227 -> 400 | I227: =F227-(F227/(1+IF(G227="",$P$4,G227))) -> 0 | J227: Zelle | S227: =IF(C227="","",MONTH(C227)) -> 8 | T227: =IF(C227="","",YEAR(C227)) -> 2024
B228: =B227+1 -> 100218 | C228: 45530 | D228: Jamiu | E228: Momodu | F228: 20 | H228: =F228-I228 -> 20 | I228: =F228-(F228/(1+IF(G228="",$P$4,G228))) -> 0 | J228: Zelle | L228: Fines | S228: =IF(C228="","",MONTH(C228)) -> 8 | T228: =IF(C228="","",YEAR(C228)) -> 2024
B229: =B228+1 -> 100219 | C229: 45534 | D229: Olatunji | E229: Ilori | F229: 500 | H229: =F229-I229 -> 500 | I229: =F229-(F229/(1+IF(G229="",$P$4,G229))) -> 0 | J229: Zelle | S229: =IF(C229="","",MONTH(C229)) -> 8 | T229: =IF(C229="","",YEAR(C229)) -> 2024
B230: =B229+1 -> 100220 | C230: 45548 | D230: Temitope | E230: Ajibola | F230: 1000 | H230: =F230-I230 -> 1000 | I230: =F230-(F230/(1+IF(G230="",$P$4,G230))) -> 0 | J230: Zelle | S230: =IF(C230="","",MONTH(C230)) -> 9 | T230: =IF(C230="","",YEAR(C230)) -> 2024
B231: =B230+1 -> 100221 | C231: 45548 | D231: Oluremi | E231: Makinde | F231: 500 | H231: =F231-I231 -> 500 | I231: =F231-(F231/(1+IF(G231="",$P$4,G231))) -> 0 | J231: Zelle | S231: =IF(C231="","",MONTH(C231)) -> 9 | T231: =IF(C231="","",YEAR(C231)) -> 2024
B232: =B231+1 -> 100222 | C232: 45551 | D232: Jamiu | E232: Momodu | F232: 800 | H232: =F232-I232 -> 800 | I232: =F232-(F232/(1+IF(G232="",$P$4,G232))) -> 0 | J232: Zelle | S232: =IF(C232="","",MONTH(C232)) -> 9 | T232: =IF(C232="","",YEAR(C232)) -> 2024
B233: =B232+1 -> 100223 | C233: 45551 | D233: Dimeji | E233: Sule | F233: 500 | H233: =F233-I233 -> 500 | I233: =F233-(F233/(1+IF(G233="",$P$4,G233))) -> 0 | J233: Zelle | S233: =IF(C233="","",MONTH(C233)) -> 9 | T233: =IF(C233="","",YEAR(C233)) -> 2024
B234: =B233+1 -> 100224 | C234: 45552 | D234: Dimeji | E234: Sule | F234: 2000 | H234: =F234-I234 -> 2000 | I234: =F234-(F234/(1+IF(G234="",$P$4,G234))) -> 0 | J234: Zelle | S234: =IF(C234="","",MONTH(C234)) -> 9 | T234: =IF(C234="","",YEAR(C234)) -> 2024
B235: =B234+1 -> 100225 | C235: 45552 | D235: Oluwafemi | E235: Durojaiye | F235: 1500 | H235: =F235-I235 -> 1500 | I235: =F235-(F235/(1+IF(G235="",$P$4,G235))) -> 0 | J235: Zelle | S235: =IF(C235="","",MONTH(C235)) -> 9 | T235: =IF(C235="","",YEAR(C235)) -> 2024
B236: =B235+1 -> 100226 | C236: 45552 | D236: Temitope | E236: Olutola | F236: 800 | H236: =F236-I236 -> 800 | I236: =F236-(F236/(1+IF(G236="",$P$4,G236))) -> 0 | J236: Zelle | S236: =IF(C236="","",MONTH(C236)) -> 9 | T236: =IF(C236="","",YEAR(C236)) -> 2024
...

Sheet Members
L1: SHARE PRICE CALCULATOR
EK2: Forecast
C3: 45017 | F3: 45047 | K3: 45078 | P3: 45108 | U3: 45139 | Z3: 45170 | AE3: 45200 | AJ3: 45231 | AO3: 45261 | AT3: 45292 | AY3: 45323 | BD3: 45352 | BI3: 45383 | BN3: 45413 | BS3: 45444 | BX3: 45474 | CC3: 45505 | CH3: 45536 | CM3: 45566 | CR3: 45597 | CW3: 45627 | DB3: 45658 | DG3: 45689 | DL3: 45717 | DQ3: 45748 | DV3: 45778 | EA3: 45809 | EF3: 45839 | EK3: 45870
B4: TerraCotta Share Price | C4: =C7/D9 -> 0.04 | F4: =F7/D9 -> 0.051315833 | K4: =K7/H9 -> 0.076028528 | P4: =P7/M9 -> 0.070970446 | U4: =U7/R9 -> 0.077428552 | Z4: =Z7/W9 -> 0.072332214 | AE4: =AE7/AB9 -> 0.079634193 | AJ4: =AJ7/AG9 -> 0.076319046 | AO4: =AO7/AL9 -> 0.070202145 | AT4: =AT7/AQ9 -> 0.080405622 | AY4: =AY7/AV9 -> 0.080067283 | BD4: =BD7/BA9 -> 0.088320591 | BI4: =BI7/BF9 -> 0.082628744 | BN4: =BN7/BK9 -> 0.079686492 | BS4: =BS7/BP9 -> 0.078849366 | BX4: =BX7/BU9 -> 0.079669817 | CC4: =CC7/BZ9 -> 0.073401159 | CH4: =CH7/CE9 -> 0.077482679 | CM4: =CM7/CJ9 -> 0.094147037 | CR4: =CR7/CO9 -> 0.079340885 | CW4: =CW7/CT9 -> 0.07571222 | DB4: =DB7/CY9 -> 0.071094219 | DG4: =DG7/DD9 -> 0.070311994 | DL4: =DL7/DI9 -> 0.069754763 | DQ4: =DQ7/CY9 -> 0.08536629 | DV4: =DV7/DD9 -> 0.083294964 | EA4: =EA7/DI9 -> 0.081375326 | EC4: BOA Balance | ED4: 7140.64 | EF4: =EF7/DN9 -> 0.077697034 | EH4: BOA Balance | EI4: 25589.16 | EK4: =EK7/DS9 -> 0.076065652
B5: Total Inflows | C5: =C9 -> 4800 | F5: =F9 -> 2200 | K5: =K9 -> 6225 | P5: =P9 -> 5000 | U5: =U9 -> 7050 | Z5: =Z9 -> 5000 | AE5: =AE9 -> 8500 | AJ5: =AJ9 -> 6600 | AO5: =AO9 -> 5192.76 | AT5: =AT9 -> 12692.05 | AY5: =AY9 -> 12325.41 | BD5: =BD9 -> 20776.84 | BI5: =BI9 -> 13244.6 | BN5: =BN9 -> 8800 | BS5: =BS9 -> 7737.18 | BX5: =BX9 -> 8472.49 | CC5: =CC9 -> 7280 | CH5: =CH9 -> 16297.89 | CM5: =CM9 -> 182651.57 | CR5: =CR9 -> -19541.57 | CW5: =CW9 -> 4873.05 | DB5: =DB9 -> 7600 | DG5: =DG9 -> 9352.64 | DL5: =DL9 -> 12690.84 | DQ5: =DQ9 -> 27075.63 | DV5: =DV9 -> 7450 | EA5: =EA9 -> 10460.36 | EC5: Axios Balance | ED5: 61411.26 | EF5: =EF9 -> 6194.85 | EH5: Axios Balance | EI5: 61606.11 | EK5: =EK9 -> 6500
B6: Total Outflows | C6: 0 | F6: 842.1 | K6: 0 | P6: 12.96 | U6: 14.4 | Z6: 20.4 | AE6: 28.8 | AJ6: 29.8 | AO6: 2682.49 | AT6: 28.8 | AY6: 128.8 | BD6: 28.8 | BI6: 29.8 | BN6: 28.8 | BS6: 232.8 | BX6: 28.8 | CC6: 10083.79 | CH6: 1513.63 | CM6: 137228.11 | CR6: 3516.99 | CW6: 3568.83 | DB6: 10643.36 | DG6: 3571.29 | DL6: 6319.94 | DQ6: 6488.78 | DV6: 3226.91 | EA6: 6077.23 | EC6: Wells Fargo Bal | ED6: 11551.75 | EF6: 3428.01 | EH6: Wells Fargo Bal | EI6: 464.75 | EK6: 3428.01
B7: TerraCotta Valuation | C7: 4800 | F7: =C7+(F5-F6) -> 6157.9 | K7: =F7+(K5-K6) -> 12382.9 | P7: =K7+(P5-P6) -> 17369.94 | U7: =P7+(U5-U6) -> 24405.54 | Z7: =U7+(Z5-Z6) -> 29385.14 | AE7: =Z7+(AE5-AE6) -> 37856.34 | AJ7: =AE7+(AJ5-AJ6) -> 44426.54 | AO7: =AJ7+(AO5-AO6) -> 46936.81 | AT7: =AO7+(AT5-AT6) -> 59600.06 | AY7: =AT7+(AY5-AY6) -> 71796.67 | BD7: =AY7+(BD5-BD6) -> 92544.71 | BI7: =BD7+(BI5-BI6) -> 105759.51 | BN7: =BI7+(BN5-BN6) -> 114530.71 | BS7: =BN7+(BS5-BS6) -> 122035.09 | BX7: =BS7+(BX5-BX6) -> 130478.78 | CC7: =BX7+(CC5-CC6) -> 127674.99 | CH7: =CC7+(CH5-CH6) -> 142459.25 | CM7: =CH7+(CM5-CM6) -> 187882.71 | CR7: =CM7+(CR5-CR6) -> 164824.15 | CW7: =CR7+(CW5-CW6) -> 166128.37 | DB7: =CW7+(DB5-DB6) -> 163085.01 | DG7: =DB7+(DG5-DG6) -> 168866.36 | DL7: =DG7+(DL5-DL6) -> 175237.26 | DQ7: =DL7+(DQ5-DQ6) -> 195824.11 | DV7: =DQ7+(DV5-DV6) -> 200047.2 | EA7: =DV7+(EA5-EA6) -> 204430.33 | EC7: Total Balance | ED7: =SUM(ED4:ED6) -> 80103.65 | EF7: =EA7+(EF5-EF6) -> 207197.17 | EH7: Total Balance | EI7: =SUM(EI4:EI6) -> 87660.02 | EK7: =EF7+(EK5-EK6) -> 210269.16
B9: Total | C9: =SUM(C12:C23) -> 4800 | D9: =SUM(D12:D23) -> 120000 | F9: =SUM(F12:F23) -> 2200 | G9: =SUM(G12:G23) -> 42871.758 | H9: =SUM(H12:H23) -> 162871.76 | K9: =SUM(K12:K23) -> 6225 | L9: =SUM(L12:L23) -> 81877.161 | M9: =SUM(M12:M23) -> 244748.92 | P9: =SUM(P12:P23) -> 5000 | Q9: =SUM(Q12:Q23) -> 70451.861 | R9: =SUM(R12:R23) -> 315200.78 | U9: =SUM(U12:U23) -> 7050 | V9: =SUM(V12:V23) -> 91051.683 | W9: =SUM(W12:W23) -> 406252.46 | Z9: =SUM(Z12:Z23) -> 5000 | AA9: =SUM(AA12:AA23) -> 69125.494 | AB9: =SUM(AB12:AB23) -> 475377.96 | AE9: =SUM(AE12:AE23) -> 8500 | AF9: =SUM(AF12:AF23) -> 106738.07 | AG9: =SUM(AG12:AG23) -> 582116.03 | AJ9: =SUM(AJ12:AJ23) -> 6600 | AK9: =SUM(AK12:AK23) -> 86479.068 | AL9: =SUM(AL12:AL23) -> 668595.09 | AO9: =SUM(AO12:AO26) -> 5192.76 | AP9: =SUM(AP12:AP26) -> 72647.352 | AQ9: =SUM(AQ12:AQ26) -> 741242.45 | AT9: =SUM(AT12:AT26) -> 12692.05 | AU9: =SUM(AU12:AU26) -> 155461.77 | AV9: =SUM(AV12:AV26) -> 896704.21 | AY9: =SUM(AY12:AY26) -> 12325.41 | AZ9: =SUM(AZ12:AZ26) -> 151122.9 | BA9: =SUM(BA12:BA26) -> 1047827.1 | BD9: =SUM(BD12:BD26) -> 20776.84 | BE9: =SUM(BE12:BE26) -> 232108.95 | BF9: =SUM(BF12:BF26) -> 1279936.1 | BI9: =SUM(BI12:BI26) -> 13244.6 | BJ9: =SUM(BJ12:BJ26) -> 157330.24 | BK9: =SUM(BK12:BK26) -> 1437266.3 | BN9: =SUM(BN12:BN26) -> 8800 | BO9: =SUM(BO12:BO26) -> 110432.77 | BP9: =SUM(BP12:BP26) -> 1547699.1 | BS9: =SUM(BS12:BS26) -> 7737.18 | BT9: =SUM(BT12:BT26) -> 90045.113 | BU9: =SUM(BU12:BU26) -> 1637744.2 | BX9: =SUM(BX12:BX26) -> 8472.49 | BY9: =SUM(BY12:BY26) -> 101669.62 | BZ9: =SUM(BZ12:BZ26) -> 1739413.8 | CC9: =SUM(CC12:CC26) -> 7280 | CD9: =SUM(CD12:CD26) -> 99180.995 | CE9: =SUM(CE12:CE26) -> 1838594.8 | CH9: =SUM(CH12:CH26) -> 16297.89 | CI9: =SUM(CI12:CI26) -> 157035.83 | CJ9: =SUM(CJ12:CJ24) -> 1995630.6 | CM9: =SUM(CM12:CM29) -> 182651.57 | CN9: =SUM(CN12:CN26) -> 81786.961 | CO9: =SUM(CO12:CO26) -> 2077417.6 | CR9: =SUM(CR12:CR26) +(sum(CR28:CR29) - sum(CM28:CM29)) -> -19541.57 | CS9: =SUM(CS12:CS26) -> 116790.57 | CT9: =SUM(CT12:CT26) -> 2194208.2 | CW9: =SUM(CW12:CW26) +(sum(CW28:CW29) - sum(CR28:CR29)) -> 4873.05 | CX9: =SUM(CX12:CX26) -> 99719.702 | CY9: =SUM(CY12:CY26) -> 2293927.9 | DB9: =SUM(DB12:DB26) +(sum(DB28:DB29) - sum(CW28:CW29)) -> 7600 | DC9: =SUM(DC12:DC26) -> 107744.34 | DD9: =SUM(DD12:DD26) -> 2401672.2 | DG9: =SUM(DG12:DG26) +(sum(DG28:DG29) - sum(DB28:DB29)) -> 9352.64 | DH9: =SUM(DH12:DH26) -> 110518.41 | DI9: =SUM(DI12:DI26) -> 2512190.6 | DL9: =SUM(DL12:DL27) +(sum(DL28:DL29) - sum(DG28:DG29)) -> 12690.84 | DM9: =SUM(DM12:DM26) -> 154541.42 | DN9: =SUM(DN12:DN26) -> 2666732 | DQ9: =SUM(DQ12:DQ27) +(sum(DQ28:DQ29) - sum(DL28:DL29)) -> 27075.63 | DR9: =SUM(DR12:DR26) -> 97579.501 | DS9: =SUM(DS12:DS26) -> 2764311.5 | DV9: =SUM(DV12:DV26) -> 7450 | DW9: =SUM(DW12:DW26) -> 90401.623 | DX9: =SUM(DX12:DX26) -> 2854713.2 | EA9: =SUM(EA12:EA26) -> 10460.36 | EB9: =SUM(EB12:EB26) -> 126942.66 | EC9: =SUM(EC12:EC26) -> 2981655.8 | EF9: =SUM(EF12:EF26) -> 6194.85 | EG9: =SUM(EG12:EG26) -> 77223.025 | EH9: =SUM(EH12:EH26) -> 3058878.8 | EK9: =SUM(EK12:EK26) -> 6500 | EL9: =SUM(EL12:EL26) -> 86109.825 | EM9: =SUM(EM12:EM26) -> 2850421.4
EO10: 2023 Total | EP10: 2024 Total | EQ10: 2024 Year end | ER10: 2025 Total | ES10: Overall Total
A11: ID | B11: MEMBER | C11: CONTR | D11: Shares | F11: CONTR | G11: Shares | H11: Total Shares | I11: % Shares | K11: CONTR | L11: Shares | M11: Total Shares | N11: % Shares | P11: CONTR | Q11: Shares | R11: Total Shares | S11: % Shares | U11: CONTR | V11: Shares | W11: Total Shares | X11: % Shares | Z11: CONTR | AA11: Shares | AB11: Total Shares | AC11: % shares | AE11: CONTR | AF11: Shares | AG11: Total Shares | AH11: % shares | AJ11: CONTR | AK11: Shares | AL11: Total Shares | AM11: % shares | AO11: CONTR | AP11: Shares | AQ11: Total Shares | AR11: % shares | AT11: CONTR | AU11: Shares | AV11: Total Shares | AW11: % shares | AY11: CONTR | AZ11: Shares | BA11: Total Shares | BB11: % shares | BD11: CONTR | BE11: Shares | BF11: Total Shares | BG11: % shares | BI11: CONTR | BJ11: Shares | BK11: Total Shares | BL11: % shares | BN11: CONTR | BO11: Shares | BP11: Total Shares | BQ11: % shares | BS11: CONTR | BT11: Shares | BU11: Total Shares | BV11: % shares | BX11: CONTR | BY11: Shares | BZ11: Total Shares | CA11: % shares | CC11: CONTR | CD11: Shares | CE11: Total Shares | CF11: % shares | CH11: CONTR | CI11: Shares | CJ11: Total Shares | CK11: % shares | CM11: CONTR | CN11: Shares | CO11: Total Shares | CP11: % shares | CR11: CONTR | CS11: Shares | CT11: Total Shares | CU11: % shares | CW11: CONTR | CX11: Shares | CY11: Total Shares | CZ11: % shares | DB11: CONTR | DC11: Shares | DD11: Total Shares | DE11: % shares | DG11: CONTR | DH11: Shares | DI11: Total Shares | DJ11: % shares | DL11: CONTR | DM11: Shares | DN11: Total Shares | DO11: % shares | DQ11: CONTR | DR11: Shares | DS11: Total Shares | DT11: % shares | DV11: CONTR | DW11: Shares | DX11: Total Shares | DY11: % shares | EA11: CONTR | EB11: Shares | EC11: Total Shares | ED11: % shares | EF11: CONTR | EG11: Shares | EH11: Total Shares | EI11: % shares | EK11: CONTR | EL11: Shares | EM11: Total Shares | EN11: % shares
A12: 1722 | B12: Ajala Oladapo | C12: 400 | D12: 10000 | F12: 200 | G12: =F12/F$4 -> 3897.4326 | H12: =D12+G12 -> 13897.433 | I12: =H12/$H$9 -> 0.085327455 | K12: 500 | L12: =K12/K$4 -> 6576.4788 | M12: =H12+L12 -> 20473.911 | N12: =M12/$M$9 -> 0.083652714 | P12: 500 | Q12: =P12/P$4 -> 7045.1861 | R12: =M12+Q12 -> 27519.097 | S12: =R12/$R$9 -> 0.087306565 | U12: 500 | V12: =U12/U$4 -> 6457.5662 | W12: =R12+V12 -> 33976.664 | X12: =W12/$W$9 -> 0.083634357 | Z12: 500 | AA12: =Z12/Z$4 -> 6912.5494 | AB12: =W12+AA12 -> 40889.213 | AC12: =AB12/$AB$9 -> 0.086014112 | AE12: 500 | AF12: =AE12/AE$4 -> 6278.7099 | AG12: =AB12+AF12 -> 47167.923 | AH12: =AG12/$AG$9 -> 0.081028388 | AJ12: 500 | AK12: =AJ12/AJ$4 -> 6551.4445 | AL12: =AG12+AK12 -> 53719.368 | AM12: =AL12/$AL$9 -> 0.080346637 | AO12: 500 | AP12: =AO12/AO$4 -> 7122.2895 | AQ12: =AL12+AP12 -> 60841.657 | AR12: =AQ12/$AQ$9 -> 0.082080643 | AT12: 500 | AU12: =AT12/AT$4 -> 6218.4706 | AV12: =AQ12+AU12 -> 67060.128 | AW12: =AV12/$AV$9 -> 0.074785115 | AY12: 500 | AZ12: =AY12/AY$4 -> 6244.7479 | BA12: =AV12+AZ12 -> 73304.876 | BB12: =BA12/$BA$9 -> 0.069958941 | BD12: 500 | BE12: =BD12/BD$4 -> 5661.194 | BF12: =BA12+BE12 -> 78966.07 | BG12: =BF12/$BF$9 -> 0.061695323 | BI12: 2500 | BJ12: =BI12/BI$4 -> 30255.815 | BK12: =BF12+BJ12 -> 109221.88 | BL12: =BK12/$BK$9 -> 0.075992796 | BN12: 2000 | BO12: =BN12/BN$4 -> 25098.357 | BP12: =BK12+BO12 -> 134320.24 | BQ12: =BP12/$BP$9 -> 0.086787053 | BS12: 1500 | BT12: =BS12/BS$4 -> 19023.615 | BU12: =BP12+BT12 -> 153343.86 | BV12: =BU12/$BU$9 -> 0.093631141 | BX12: 1000 | BY12: =BX12/BX$4 -> 12551.805 | BZ12: =BU12+BY12 -> 165895.66 | CA12: =BZ12/$BZ$9 -> 0.095374465 | CC12: 0 | CD12: =CC12/CC$4 -> 0 | CE12: =BZ12+CD12 -> 165895.66 | CF12: =CE12/$CE$9 -> 0.090229593 | CH12: 500 | CI12: =CH12/CH$4 -> 6453.0552 | CJ12: =CE12+CI12 -> 172348.72 | CK12: =CJ12/$CJ$9 -> 0.086363035 | CM12: 500 | CN12: =CM12/CM$4 -> 5310.8416 | CO12: =CJ12+CN12 -> 177659.56 | CP12: =CO12/$CO$9 -> 0.085519425 | CR12: 500 | CS12: =CR12/CR$4 -> 6301.9211 | CT12: =CO12+CS12 -> 183961.48 | CU12: =CT12/$CT$9 -> 0.083839575 | CW12: 500 | CX12: =CW12/CW$4 -> 6603.9538 | CY12: =CT12+CX12 -> 190565.43 | CZ12: =CY12/$CY$9 -> 0.083073856 | DB12: 500 | DC12: =DB12/DB$4 -> 7032.9206 | DD12: =CY12+DC12 -> 197598.35 | DE12: =DD12/$DD$9 -> 0.082275322 | DG12: 500 | DH12: =DG12/DG$4 -> 7111.1623 | DI12: =DD12+DH12 -> 204709.52 | DJ12: =DI12/$DI$9 -> 0.081486458 | DL12: 500 | DM12: =DL12/DL$4 -> 7167.9693 | DN12: =DI12+DM12 -> 211877.49 | DO12: =DN12/$DN$9 -> 0.079452109 | DQ12: 500 | DR12: =DQ12/DQ$4 -> 5857.1129 | DS12: =DN12+DR12 -> 217734.6 | DT12: =DS12/$DS$9 -> 0.078766302 | DV12: 0 | DW12: =DV12/DV$4 -> 0 | DX12: =DS12+DW12 -> 217734.6 | DY12: =DX12/$DX$9 -> 0.076271971 | EA12: 1000 | EB12: =EA12/EA$4 -> 12288.737 | EC12: =DX12+EB12 -> 230023.34 | ED12: =EC12/$EC$9 -> 0.077146173 | EF12: 500 | EG12: =EF12/EF$4 -> 6435.2521 | EH12: =EC12+EG12 -> 236458.59 | EI12: =EH12/$EH$9 -> 0.077302371 | EK12: 500 | EL12: =EK12/EK$4 -> 6573.2691 | EM12: =DS12+EL12 -> 224307.87 | EN12: =EM12/$EM$9 -> 0.078692881 | EO12: =C12+F12+K12+P12+U12+Z12+AE12+AJ12+AO12 -> 4100 | EP12: =AT12+AY12+BD12+BI12+BN12+BS12+BX12+CC12+CH12+CM12+CR12+CW12 -> 10500 | EQ12: =EO12+EP12 -> 14600 | ER12: =DB12+DG12+DL12+DQ12+DV12+EA12+EF12 -> 3500 | ES12: =EQ12+ER12 -> 18100
A13: =RANDBETWEEN(17,44) +A12 -> 1766 | B13: Ajibola Temitope | C13: 400 | D13: 10000 | F13: 200 | G13: =F13/F$4 -> 3897.4326 | H13: =D13+G13 -> 13897.433 | I13: =H13/$H$9 -> 0.085327455 | K13: 500 | L13: =K13/K$4 -> 6576.4788 | M13: =H13+L13 -> 20473.911 | N13: =M13/$M$9 -> 0.083652714 | P13: 500 | Q13: =P13/P$4 -> 7045.1861 | R13: =M13+Q13 -> 27519.097 | S13: =R13/$R$9 -> 0.087306565 | U13: 500 | V13: =U13/U$4 -> 6457.5662 | W13: =R13+V13 -> 33976.664 | X13: =W13/$W$9 -> 0.083634357 | Z13: 500 | AA13: =Z13/Z$4 -> 6912.5494 | AB13: =W13+AA13 -> 40889.213 | AC13: =AB13/$AB$9 -> 0.086014112 | AE13: 500 | AF13: =AE13/AE$4 -> 6278.7099 | AG13: =AB13+AF13 -> 47167.923 | AH13: =AG13/$AG$9 -> 0.081028388 | AJ13: 500 | AK13: =AJ13/AJ$4 -> 6551.4445 | AL13: =AG13+AK13 -> 53719.368 | AM13: =AL13/$AL$9 -> 0.080346637 | AO13: 1000 | AP13: =AO13/AO$4 -> 14244.579 | AQ13: =AL13+AP13 -> 67963.946 | AR13: =AQ13/$AQ$9 -> 0.091689226 | AT13: 1000 | AU13: =AT13/AT$4 -> 12436.941 | AV13: =AQ13+AU13 -> 80400.888 | AW13: =AV13/$AV$9 -> 0.089662663 | AY13: 1000 | AZ13: =AY13/AY$4 -> 12489.496 | BA13: =AV13+AZ13 -> 92890.384 | BB13: =BA13/$BA$9 -> 0.088650487 | BD13: 2500 | BE13: =BD13/BD$4 -> 28305.97 | BF13: =BA13+BE13 -> 121196.35 | BG13: =BF13/$BF$9 -> 0.094689381 | BI13: 500 | BJ13: =BI13/BI$4 -> 6051.163 | BK13: =BF13+BJ13 -> 127247.52 | BL13: =BK13/$BK$9 -> 0.088534405 | BN13: 500 | BO13: =BN13/BN$4 -> 6274.5892 | BP13: =BK13+BO13 -> 133522.11 | BQ13: =BP13/$BP$9 -> 0.086271361 | BS13: 600 | BT13: =BS13/BS$4 -> 7609.4461 | BU13: =BP13+BT13 -> 141131.55 | BV13: =BU13/$BU$9 -> 0.086174357 | BX13: 500 | BY13: =BX13/BX$4 -> 6275.9024 | BZ13: =BU13+BY13 -> 147407.45 | CA13: =BZ13/$BZ$9 -> 0.084745478 | CC13: 500 | CD13: =CC13/CC$4 -> 6811.8815 | CE13: =BZ13+CD13 -> 154219.34 | CF13: =CE13/$CE$9 -> 0.083878914 | CH13: 1000 | CI13: =CH13/CH$4 -> 12906.11 | CJ13: =CE13+CI13 -> 167125.45 | CK13: =CJ13/$CJ$9 -> 0.083745681 | CM13: 500 | CN13: =CM13/CM$4 -> 5310.8416 | CO13: =CJ13+CN13 -> 172436.29 | CP13: =CO13/$CO$9 -> 0.083005116 | CR13: 1000 | CS13: =CR13/CR$4 -> 12603.842 | CT13: =CO13+CS13 -> 185040.13 | CU13: =CT13/$CT$9 -> 0.084331165 | CW13: 600 | CX13: =CW13/CW$4 -> 7924.7445 | CY13: =CT13+CX13 -> 192964.87 | CZ13: =CY13/$CY$9 -> 0.084119853 | DB13: 600 | DC13: =DB13/DB$4 -> 8439.5047 | DD13: =CY13+DC13 -> 201404.38 | DE13: =DD13/$DD$9 -> 0.083860062 | DG13: 500 | DH13: =DG13/DG$4 -> 7111.1623 | DI13: =DD13+DH13 -> 208515.54 | DJ13: =DI13/$DI$9 -> 0.083001481 | DL13: 800 | DM13: =DL13/DL$4 -> 11468.751 | DN13: =DI13+DM13 -> 219984.29 | DO13: =DN13/$DN$9 -> 0.082492088 | DQ13: 800 | DR13: =DQ13/DQ$4 -> 9371.3807 | DS13: =DN13+DR13 -> 229355.67 | DT13: =DS13/$DS$9 -> 0.08297027 | DV13: 500 | DW13: =DV13/DV$4 -> 6002.7638 | DX13: =DS13+DW13 -> 235358.44 | DY13: =DX13/$DX$9 -> 0.082445564 | EA13: 500 | EB13: =EA13/EA$4 -> 6144.3686 | EC13: =DX13+EB13 -> 241502.81 | ED13: =EC13/$EC$9 -> 0.080996205 | EF13: 700 | EG13: =EF13/EF$4 -> 9009.3529 | EH13: =EC13+EG13 -> 250512.16 | EI13: =EH13/$EH$9 -> 0.081896725 | EK13: 500 | EL13: =EK13/EK$4 -> 6573.2691 | EM13: =DS13+EL13 -> 235928.94 | EN13: =EM13/$EM$9 -> 0.082769848 | EO13: =C13+F13+K13+P13+U13+Z13+AE13+AJ13+AO13 -> 4600 | EP13: =AT13+AY13+BD13+BI13+BN13+BS13+BX13+CC13+CH13+CM13+CR13+CW13 -> 10200 | EQ13: =EO13+EP13 -> 14800 | ER13: =DB13+DG13+DL13+DQ13+DV13+EA13+EF13 -> 4400 | ES13: =EQ13+ER13 -> 19200
A14: =RANDBETWEEN(17,44) +A13 -> 1797 | B14: Akindele Abiodun | C14: 400 | D14: 10000 | F14: 200 | G14: =F14/F$4 -> 3897.4326 | H14: =D14+G14 -> 13897.433 | I14: =H14/$H$9 -> 0.085327455 | K14: 500 | L14: =K14/K$4 -> 6576.4788 | M14: =H14+L14 -> 20473.911 | N14: =M14/$M$9 -> 0.083652714 | P14: 500 | Q14: =P14/P$4 -> 7045.1861 | R14: =M14+Q14 -> 27519.097 | S14: =R14/$R$9 -> 0.087306565 | U14: 500 | V14: =U14/U$4 -> 6457.5662 | W14: =R14+V14 -> 33976.664 | X14: =W14/$W$9 -> 0.083634357 | Z14: 500 | AA14: =Z14/Z$4 -> 6912.5494 | AB14: =W14+AA14 -> 40889.213 | AC14: =AB14/$AB$9 -> 0.086014112 | AE14: 500 | AF14: =AE14/AE$4 -> 6278.7099 | AG14: =AB14+AF14 -> 47167.923 | AH14: =AG14/$AG$9 -> 0.081028388 | AJ14: 500 | AK14: =AJ14/AJ$4 -> 6551.4445 | AL14: =AG14+AK14 -> 53719.368 | AM14: =AL14/$AL$9 -> 0.080346637 | AO14: 500 | AP14: =AO14/AO$4 -> 7122.2895 | AQ14: =AL14+AP14 -> 60841.657 | AR14: =AQ14/$AQ$9 -> 0.082080643 | AT14: 500 | AU14: =AT14/AT$4 -> 6218.4706 | AV14: =AQ14+AU14 -> 67060.128 | AW14: =AV14/$AV$9 -> 0.074785115 | AY14: 500 | AZ14: =AY14/AY$4 -> 6244.7479 | BA14: =AV14+AZ14 -> 73304.876 | BB14: =BA14/$BA$9 -> 0.069958941 | BD14: 500 | BE14: =BD14/BD$4 -> 5661.194 | BF14: =BA14+BE14 -> 78966.07 | BG14: =BF14/$BF$9 -> 0.061695323 | BI14: 1500 | BJ14: =BI14/BI$4 -> 18153.489 | BK14: =BF14+BJ14 -> 97119.558 | BL14: =BK14/$BK$9 -> 0.067572417 | BN14: 500 | BO14: =BN14/BN$4 -> 6274.5892 | BP14: =BK14+BO14 -> 103394.15 | BQ14: =BP14/$BP$9 -> 0.066805072 | BS14: 500 | BT14: =BS14/BS$4 -> 6341.2051 | BU14: =BP14+BT14 -> 109735.35 | BV14: =BU14/$BU$9 -> 0.067003964 | BX14: 800 | BY14: =BX14/BX$4 -> 10041.444 | BZ14: =BU14+BY14 -> 119776.8 | CA14: =BZ14/$BZ$9 -> 0.068860438 | CC14: 780 | CD14: =CC14/CC$4 -> 10626.535 | CE14: =BZ14+CD14 -> 130403.33 | CF14: =CE14/$CE$9 -> 0.070925542 | CH14: 800 | CI14: =CH14/CH$4 -> 10324.888 | CJ14: =CE14+CI14 -> 140728.22 | CK14: =CJ14/$CJ$9 -> 0.07051817 | CM14: 800 | CN14: =CM14/CM$4 -> 8497.3466 | CO14: =CJ14+CN14 -> 149225.57 | CP14: =CO14/$CO$9 -> 0.071832244 | CR14: 800 | CS14: =CR14/CR$4 -> 10083.074 | CT14: =CO14+CS14 -> 159308.64 | CU14: =CT14/$CT$9 -> 0.07260416 | CW14: 850 | CX14: =CW14/CW$4 -> 11226.721 | CY14: =CT14+CX14 -> 170535.36 | CZ14: =CY14/$CY$9 -> 0.074342077 | DB14: 850 | DC14: =DB14/DB$4 -> 11955.965 | DD14: =CY14+DC14 -> 182491.33 | DE14: =DD14/$DD$9 -> 0.07598511 | DG14: 800 | DH14: =DG14/DG$4 -> 11377.86 | DI14: =DD14+DH14 -> 193869.19 | DJ14: =DI14/$DI$9 -> 0.077171368 | DL14: 800 | DM14: =DL14/DL$4 -> 11468.751 | DN14: =DI14+DM14 -> 205337.94 | DO14: =DN14/$DN$9 -> 0.076999839 | DQ14: 800 | DR14: =DQ14/DQ$4 -> 9371.3807 | DS14: =DN14+DR14 -> 214709.32 | DT14: =DS14/$DS$9 -> 0.077671896 | DV14: 500 | DW14: =DV14/DV$4 -> 6002.7638 | DX14: =DS14+DW14 -> 220712.08 | DY14: =DX14/$DX$9 -> 0.077314977 | EA14: 800 | EB14: =EA14/EA$4 -> 9830.9898 | EC14: =DX14+EB14 -> 230543.07 | ED14: =EC14/$EC$9 -> 0.077320484 | EF14: 800 | EG14: =EF14/EF$4 -> 10296.403 | EH14: =EC14+EG14 -> 240839.48 | EI14: =EH14/$EH$9 -> 0.078734559 | EK14: 500 | EL14: =EK14/EK$4 -> 6573.2691 | EM14: =DS14+EL14 -> 221282.59 | EN14: =EM14/$EM$9 -> 0.077631536 | EO14: =C14+F14+K14+P14+U14+Z14+AE14+AJ14+AO14 -> 4100 | EP14: =AT14+AY14+BD14+BI14+BN14+BS14+BX14+CC14+CH14+CM14+CR14+CW14 -> 8830 | EQ14: =EO14+EP14 -> 12930 | ER14: =DB14+DG14+DL14+DQ14+DV14+EA14+EF14 -> 5350 | ES14: =EQ14+ER14 -> 18280
A15: =RANDBETWEEN(17,44) +A14 -> 1828 | B15: Dosumu Olurotimi | C15: 400 | D15: 10000 | F15: 200 | G15: =F15/F$4 -> 3897.4326 | H15: =D15+G15 -> 13897.433 | I15: =H15/$H$9 -> 0.085327455 | K15: 500 | L15: =K15/K$4 -> 6576.4788 | M15: =H15+L15 -> 20473.911 | N15: =M15/$M$9 -> 0.083652714 | P15: 500 | Q15: =P15/P$4 -> 7045.1861 | R15: =M15+Q15 -> 27519.097 | S15: =R15/$R$9 -> 0.087306565 | U15: 500 | V15: =U15/U$4 -> 6457.5662 | W15: =R15+V15 -> 33976.664 | X15: =W15/$W$9 -> 0.083634357 | Z15: 500 | AA15: =Z15/Z$4 -> 6912.5494 | AB15: =W15+AA15 -> 40889.213 | AC15: =AB15/$AB$9 -> 0.086014112 | AE15: 500 | AF15: =AE15/AE$4 -> 6278.7099 | AG15: =AB15+AF15 -> 47167.923 | AH15: =AG15/$AG$9 -> 0.081028388 | AJ15: 500 | AK15: =AJ15/AJ$4 -> 6551.4445 | AL15: =AG15+AK15 -> 53719.368 | AM15: =AL15/$AL$9 -> 0.080346637 | AO15: 0 | AP15: =AO15/AO$4 -> 0 | AQ15: =AL15+AP15 -> 53719.368 | AR15: =AQ15/$AQ$9 -> 0.072472061 | AT15: 1500 | AU15: =AT15/AT$4 -> 18655.412 | AV15: =AQ15+AU15 -> 72374.779 | AW15: =AV15/$AV$9 -> 0.080711988 | AY15: 2500 | AZ15: =AY15/AY$4 -> 31223.74 | BA15: =AV15+AZ15 -> 103598.52 | BB15: =BA15/$BA$9 -> 0.098869859 | BD15: 1500 | BE15: =BD15/BD$4 -> 16983.582 | BF15: =BA15+BE15 -> 120582.1 | BG15: =BF15/$BF$9 -> 0.094209472 | BI15: 500 | BJ15: =BI15/BI$4 -> 6051.163 | BK15: =BF15+BJ15 -> 126633.26 | BL15: =BK15/$BK$9 -> 0.088107029 | BN15: 500 | BO15: =BN15/BN$4 -> 6274.5892 | BP15: =BK15+BO15 -> 132907.85 | BQ15: =BP15/$BP$9 -> 0.08587448 | BS15: 0 | BT15: =BS15/BS$4 -> 0 | BU15: =BP15+BT15 -> 132907.85 | BV15: =BU15/$BU$9 -> 0.081153 | BX15: 0 | BY15: =BX15/BX$4 -> 0 | BZ15: =BU15+BY15 -> 132907.85 | CA15: =BZ15/$BZ$9 -> 0.076409566 | CC15: 1000 | CD15: =CC15/CC$4 -> 13623.763 | CE15: =BZ15+CD15 -> 146531.62 | CF15: =CE15/$CE$9 -> 0.079697613 | CH15: 1000 | CI15: =CH15/CH$4 -> 12906.11 | CJ15: =CE15+CI15 -> 159437.73 | CK15: =CJ15/$CJ$9 -> 0.079893405 | CM15: 500 | CN15: =CM15/CM$4 -> 5310.8416 | CO15: =CJ15+CN15 -> 164748.57 | CP15: =CO15/$CO$9 -> 0.079304503 | CR15: 0 | CS15: =CR15/CR$4 -> 0 | CT15: =CO15+CS15 -> 164748.57 | CU15: =CT15/$CT$9 -> 0.075083382 | CW15: 500 | CX15: =CW15/CW$4 -> 6603.9538 | CY15: =CT15+CX15 -> 171352.52 | CZ15: =CY15/$CY$9 -> 0.074698305 | DB15: 500 | DC15: =DB15/DB$4 -> 7032.9206 | DD15: =CY15+DC15 -> 178385.44 | DE15: =DD15/$DD$9 -> 0.074275516 | DG15: 0 | DH15: =DG15/DG$4 -> 0 | DI15: =DD15+DH15 -> 178385.44 | DJ15: =DI15/$DI$9 -> 0.071007925 | DL15: 0 | DM15: =DL15/DL$4 -> 0 | DN15: =DI15+DM15 -> 178385.44 | DO15: =DN15/$DN$9 -> 0.066892901 | DQ15: 1000 | DR15: =DQ15/DQ$4 -> 11714.226 | DS15: =DN15+DR15 -> 190099.67 | DT15: =DS15/$DS$9 -> 0.068769264 | DV15: 0 | DW15: =DV15/DV$4 -> 0 | DX15: =DS15+DW15 -> 190099.67 | DY15: =DX15/$DX$9 -> 0.066591513 | EA15: 1000 | EB15: =EA15/EA$4 -> 12288.737 | EC15: =DX15+EB15 -> 202388.41 | ED15: =EC15/$EC$9 -> 0.067877857 | EF15: 500 | EG15: =EF15/EF$4 -> 6435.2521 | EH15: =EC15+EG15 -> 208823.66 | EI15: =EH15/$EH$9 -> 0.068268038 | EK15: 500 | EL15: =EK15/EK$4 -> 6573.2691 | EM15: =DS15+EL15 -> 196672.94 | EN15: =EM15/$EM$9 -> 0.068997847 | EO15: =C15+F15+K15+P15+U15+Z15+AE15+AJ15+AO15 -> 3600 | EP15: =AT15+AY15+BD15+BI15+BN15+BS15+BX15+CC15+CH15+CM15+CR15+CW15 -> 9500 | EQ15: =EO15+EP15 -> 13100 | ER15: =DB15+DG15+DL15+DQ15+DV15+EA15+EF15 -> 3000 | ES15: =EQ15+ER15 -> 16100
A16: =RANDBETWEEN(17,44) +A15 -> 1863 | B16: Durojaiye Oluwafemi | C16: 400 | D16: 10000 | F16: 200 | G16: =F16/F$4 -> 3897.4326 | H16: =D16+G16 -> 13897.433 | I16: =H16/$H$9 -> 0.085327455 | K16: 500 | L16: =K16/K$4 -> 6576.4788 | M16: =H16+L16 -> 20473.911 | N16: =M16/$M$9 -> 0.083652714 | P16: 500 | Q16: =P16/P$4 -> 7045.1861 | R16: =M16+Q16 -> 27519.097 | S16: =R16/$R$9 -> 0.087306565 | U16: 500 | V16: =U16/U$4 -> 6457.5662 | W16: =R16+V16 -> 33976.664 | X16: =W16/$W$9 -> 0.083634357 | Z16: 500 | AA16: =Z16/Z$4 -> 6912.5494 | AB16: =W16+AA16 -> 40889.213 | AC16: =AB16/$AB$9 -> 0.086014112 | AE16: 500 | AF16: =AE16/AE$4 -> 6278.7099 | AG16: =AB16+AF16 -> 47167.923 | AH16: =AG16/$AG$9 -> 0.081028388 | AJ16: 500 | AK16: =AJ16/AJ$4 -> 6551.4445 | AL16: =AG16+AK16 -> 53719.368 | AM16: =AL16/$AL$9 -> 0.080346637 | AO16: 500 | AP16: =AO16/AO$4 -> 7122.2895 | AQ16: =AL16+AP16 -> 60841.657 | AR16: =AQ16/$AQ$9 -> 0.082080643 | AT16: 0 | AU16: =AT16/AT$4 -> 0 | AV16: =AQ16+AU16 -> 60841.657 | AW16: =AV16/$AV$9 -> 0.067850308 | AY16: 1600 | AZ16: =AY16/AY$4 -> 19983.193 | BA16: =AV16+AZ16 -> 80824.85 | BB16: =BA16/$BA$9 -> 0.077135674 | BD16: 500 | BE16: =BD16/BD$4 -> 5661.194 | BF16: =BA16+BE16 -> 86486.044 | BG16: =BF16/$BF$9 -> 0.067570597 | BI16: 1500 | BJ16: =BI16/BI$4 -> 18153.489 | BK16: =BF16+BJ16 -> 104639.53 | BL16: =BK16/$BK$9 -> 0.072804555 | BN16: 500 | BO16: =BN16/BN$4 -> 6274.5892 | BP16: =BK16+BO16 -> 110914.12 | BQ16: =BP16/$BP$9 -> 0.071663881 | BS16: 0 | BT16: =BS16/BS$4 -> 0 | BU16: =BP16+BT16 -> 110914.12 | BV16: =BU16/$BU$9 -> 0.067723716 | BX16: 1100 | BY16: =BX16/BX$4 -> 13806.985 | BZ16: =BU16+BY16 -> 124721.11 | CA16: =BZ16/$BZ$9 -> 0.071702954 | CC16: 0 | CD16: =CC16/CC$4 -> 0 | CE16: =BZ16+CD16 -> 124721.11 | CF16: =CE16/$CE$9 -> 0.067835016 | CH16: 1500 | CI16: =CH16/CH$4 -> 19359.166 | CJ16: =CE16+CI16 -> 144080.27 | CK16: =CJ16/$CJ$9 -> 0.072197866 | CM16: 700 | CN16: =CM16/CM$4 -> 7435.1782 | CO16: =CJ16+CN16 -> 151515.45 | CP16: =CO16/$CO$9 -> 0.072934519 | CR16: 1000 | CS16: =CR16/CR$4 -> 12603.842 | CT16: =CO16+CS16 -> 164119.29 | CU16: =CT16/$CT$9 -> 0.074796593 | CW16: 500 | CX16: =CW16/CW$4 -> 6603.9538 | CY16: =CT16+CX16 -> 170723.25 | CZ16: =CY16/$CY$9 -> 0.074423983 | DB16: 500 | DC16: =DB16/DB$4 -> 7032.9206 | DD16: =CY16+DC16 -> 177756.17 | DE16: =DD16/$DD$9 -> 0.074013501 | DG16: 0 | DH16: =DG16/DG$4 -> 0 | DI16: =DD16+DH16 -> 177756.17 | DJ16: =DI16/$DI$9 -> 0.070757437 | DL16: 1000 | DM16: =DL16/DL$4 -> 14335.939 | DN16: =DI16+DM16 -> 192092.11 | DO16: =DN16/$DN$9 -> 0.072032774 | DQ16: 700 | DR16: =DQ16/DQ$4 -> 8199.9581 | DS16: =DN16+DR16 -> 200292.07 | DT16: =DS16/$DS$9 -> 0.072456401 | DV16: 600 | DW16: =DV16/DV$4 -> 7203.3166 | DX16: =DS16+DW16 -> 207495.38 | DY16: =DX16/$DX$9 -> 0.072685195 | EA16: 500 | EB16: =EA16/EA$4 -> 6144.3686 | EC16: =DX16+EB16 -> 213639.75 | ED16: =EC16/$EC$9 -> 0.071651379 | EF16: 0 | EG16: =EF16/EF$4 -> 0 | EH16: =EC16+EG16 -> 213639.75 | EI16: =EH16/$EH$9 -> 0.069842502 | EK16: 500 | EL16: =EK16/EK$4 -> 6573.2691 | EM16: =DS16+EL16 -> 206865.33 | EN16: =EM16/$EM$9 -> 0.072573598 | EO16: =C16+F16+K16+P16+U16+Z16+AE16+AJ16+AO16 -> 4100 | EP16: =AT16+AY16+BD16+BI16+BN16+BS16+BX16+CC16+CH16+CM16+CR16+CW16 -> 8900 | EQ16: =EO16+EP16 -> 13000 | ER16: =DB16+DG16+DL16+DQ16+DV16+EA16+EF16 -> 3300 | ES16: =EQ16+ER16 -> 16300
A17: =RANDBETWEEN(17,44) +A16 -> 1901 | B17: Ilori Olatunji | C17: 400 | D17: 10000 | F17: 200 | G17: =F17/F$4 -> 3897.4326 | H17: =D17+G17 -> 13897.433 | I17: =H17/$H$9 -> 0.085327455 | K17: 500 | L17: =K17/K$4 -> 6576.4788 | M17: =H17+L17 -> 20473.911 | N17: =M17/$M$9 -> 0.083652714 | P17: 500 | Q17: =P17/P$4 -> 7045.1861 | R17: =M17+Q17 -> 27519.097 | S17: =R17/$R$9 -> 0.087306565 | U17: 500 | V17: =U17/U$4 -> 6457.5662 | W17: =R17+V17 -> 33976.664 | X17: =W17/$W$9 -> 0.083634357 | Z17: 500 | AA17: =Z17/Z$4 -> 6912.5494 | AB17: =W17+AA17 -> 40889.213 | AC17: =AB17/$AB$9 -> 0.086014112 | AE17: 500 | AF17: =AE17/AE$4 -> 6278.7099 | AG17: =AB17+AF17 -> 47167.923 | AH17: =AG17/$AG$9 -> 0.081028388 | AJ17: 500 | AK17: =AJ17/AJ$4 -> 6551.4445 | AL17: =AG17+AK17 -> 53719.368 | AM17: =AL17/$AL$9 -> 0.080346637 | AO17: 0 | AP17: =AO17/AO$4 -> 0 | AQ17: =AL17+AP17 -> 53719.368 | AR17: =AQ17/$AQ$9 -> 0.072472061 | AT17: 1000 | AU17: =AT17/AT$4 -> 12436.941 | AV17: =AQ17+AU17 -> 66156.309 | AW17: =AV17/$AV$9 -> 0.073777181 | AY17: 500 | AZ17: =AY17/AY$4 -> 6244.7479 | BA17: =AV17+AZ17 -> 72401.057 | BB17: =BA17/$BA$9 -> 0.069096377 | BD17: 5500 | BE17: =BD17/BD$4 -> 62273.134 | BF17: =BA17+BE17 -> 134674.19 | BG17: =BF17/$BF$9 -> 0.10521947 | BI17: 1000 | BJ17: =BI17/BI$4 -> 12102.326 | BK17: =BF17+BJ17 -> 146776.52 | BL17: =BK17/$BK$9 -> 0.102122 | BN17: 500 | BO17: =BN17/BN$4 -> 6274.5892 | BP17: =BK17+BO17 -> 153051.11 | BQ17: =BP17/$BP$9 -> 0.098889447 | BS17: 0 | BT17: =BS17/BS$4 -> 0 | BU17: =BP17+BT17 -> 153051.11 | BV17: =BU17/$BU$9 -> 0.093452388 | BX17: 1000 | BY17: =BX17/BX$4 -> 12551.805 | BZ17: =BU17+BY17 -> 165602.91 | CA17: =BZ17/$BZ$9 -> 0.095206161 | CC17: 500 | CD17: =CC17/CC$4 -> 6811.8815 | CE17: =BZ17+CD17 -> 172414.79 | CF17: =CE17/$CE$9 -> 0.093775307 | CH17: 500 | CI17: =CH17/CH$4 -> 6453.0552 | CJ17: =CE17+CI17 -> 178867.85 | CK17: =CJ17/$CJ$9 -> 0.089629737 | CM17: 500 | CN17: =CM17/CM$4 -> 5310.8416 | CO17: =CJ17+CN17 -> 184178.69 | CP17: =CO17/$CO$9 -> 0.088657519 | CR17: 500 | CS17: =CR17/CR$4 -> 6301.9211 | CT17: =CO17+CS17 -> 190480.61 | CU17: =CT17/$CT$9 -> 0.086810638 | CW17: 500 | CX17: =CW17/CW$4 -> 6603.9538 | CY17: =CT17+CX17 -> 197084.56 | CZ17: =CY17/$CY$9 -> 0.085915764 | DB17: 500 | DC17: =DB17/DB$4 -> 7032.9206 | DD17: =CY17+DC17 -> 204117.48 | DE17: =DD17/$DD$9 -> 0.084989735 | DG17: 0 | DH17: =DG17/DG$4 -> 0 | DI17: =DD17+DH17 -> 204117.48 | DJ17: =DI17/$DI$9 -> 0.081250795 | DL17: 1000 | DM17: =DL17/DL$4 -> 14335.939 | DN17: =DI17+DM17 -> 218453.42 | DO17: =DN17/$DN$9 -> 0.081918026 | DQ17: 0 | DR17: =DQ17/DQ$4 -> 0 | DS17: =DN17+DR17 -> 218453.42 | DT17: =DS17/$DS$9 -> 0.07902634 | DV17: 500 | DW17: =DV17/DV$4 -> 6002.7638 | DX17: =DS17+DW17 -> 224456.19 | DY17: =DX17/$DX$9 -> 0.078626529 | EA17: 1000 | EB17: =EA17/EA$4 -> 12288.737 | EC17: =DX17+EB17 -> 236744.92 | ED17: =EC17/$EC$9 -> 0.079400487 | EF17: 0 | EG17: =EF17/EF$4 -> 0 | EH17: =EC17+EG17 -> 236744.92 | EI17: =EH17/$EH$9 -> 0.07739598 | EK17: 500 | EL17: =EK17/EK$4 -> 6573.2691 | EM17: =DS17+EL17 -> 225026.69 | EN17: =EM17/$EM$9 -> 0.078945062 | EO17: =C17+F17+K17+P17+U17+Z17+AE17+AJ17+AO17 -> 3600 | EP17: =AT17+AY17+BD17+BI17+BN17+BS17+BX17+CC17+CH17+CM17+CR17+CW17 -> 12000 | EQ17: =EO17+EP17 -> 15600 | ER17: =DB17+DG17+DL17+DQ17+DV17+EA17+EF17 -> 3000 | ES17: =EQ17+ER17 -> 18600
A18: =RANDBETWEEN(17,44) +A17 -> 1928 | B18: Makinde Oluremi | C18: 400 | D18: 10000 | F18: 200 | G18: =F18/F$4 -> 3897.4326 | H18: =D18+G18 -> 13897.433 | I18: =H18/$H$9 -> 0.085327455 | K18: 500 | L18: =K18/K$4 -> 6576.4788 | M18: =H18+L18 -> 20473.911 | N18: =M18/$M$9 -> 0.083652714 | P18: 500 | Q18: =P18/P$4 -> 7045.1861 | R18: =M18+Q18 -> 27519.097 | S18: =R18/$R$9 -> 0.087306565 | U18: 500 | V18: =U18/U$4 -> 6457.5662 | W18: =R18+V18 -> 33976.664 | X18: =W18/$W$9 -> 0.083634357 | Z18: 500 | AA18: =Z18/Z$4 -> 6912.5494 | AB18: =W18+AA18 -> 40889.213 | AC18: =AB18/$AB$9 -> 0.086014112 | AE18: 500 | AF18: =AE18/AE$4 -> 6278.7099 | AG18: =AB18+AF18 -> 47167.923 | AH18: =AG18/$AG$9 -> 0.081028388 | AJ18: 500 | AK18: =AJ18/AJ$4 -> 6551.4445 | AL18: =AG18+AK18 -> 53719.368 | AM18: =AL18/$AL$9 -> 0.080346637 | AO18: 500 | AP18: =AO18/AO$4 -> 7122.2895 | AQ18: =AL18+AP18 -> 60841.657 | AR18: =AQ18/$AQ$9 -> 0.082080643 | AT18: 500 | AU18: =AT18/AT$4 -> 6218.4706 | AV18: =AQ18+AU18 -> 67060.128 | AW18: =AV18/$AV$9 -> 0.074785115 | AY18: 1500 | AZ18: =AY18/AY$4 -> 18734.244 | BA18: =AV18+AZ18 -> 85794.371 | BB18: =BA18/$BA$9 -> 0.081878366 | BD18: 3000 | BE18: =BD18/BD$4 -> 33967.164 | BF18: =BA18+BE18 -> 119761.54 | BG18: =BF18/$BF$9 -> 0.093568373 | BI18: 500 | BJ18: =BI18/BI$4 -> 6051.163 | BK18: =BF18+BJ18 -> 125812.7 | BL18: =BK18/$BK$9 -> 0.087536108 | BN18: 500 | BO18: =BN18/BN$4 -> 6274.5892 | BP18: =BK18+BO18 -> 132087.29 | BQ18: =BP18/$BP$9 -> 0.085344296 | BS18: 500 | BT18: =BS18/BS$4 -> 6341.2051 | BU18: =BP18+BT18 -> 138428.49 | BV18: =BU18/$BU$9 -> 0.08452388 | BX18: 500 | BY18: =BX18/BX$4 -> 6275.9024 | BZ18: =BU18+BY18 -> 144704.39 | CA18: =BZ18/$BZ$9 -> 0.083191472 | CC18: 500 | CD18: =CC18/CC$4 -> 6811.8815 | CE18: =BZ18+CD18 -> 151516.28 | CF18: =CE18/$CE$9 -> 0.082408738 | CH18: 500 | CI18: =CH18/CH$4 -> 6453.0552 | CJ18: =CE18+CI18 -> 157969.33 | CK18: =CJ18/$CJ$9 -> 0.0791576 | CM18: 500 | CN18: =CM18/CM$4 -> 5310.8416 | CO18: =CJ18+CN18 -> 163280.17 | CP18: =CO18/$CO$9 -> 0.078597666 | CR18: 500 | CS18: =CR18/CR$4 -> 6301.9211 | CT18: =CO18+CS18 -> 169582.09 | CU18: =CT18/$CT$9 -> 0.077286238 | CW18: 750 | CX18: =CW18/CW$4 -> 9905.9307 | CY18: =CT18+CX18 -> 179488.03 | CZ18: =CY18/$CY$9 -> 0.078244843 | DB18: 750 | DC18: =DB18/DB$4 -> 10549.381 | DD18: =CY18+DC18 -> 190037.41 | DE18: =DD18/$DD$9 -> 0.079127121 | DG18: 500 | DH18: =DG18/DG$4 -> 7111.1623 | DI18: =DD18+DH18 -> 197148.57 | DJ18: =DI18/$DI$9 -> 0.078476755 | DL18: 500 | DM18: =DL18/DL$4 -> 7167.9693 | DN18: =DI18+DM18 -> 204316.54 | DO18: =DN18/$DN$9 -> 0.076616824 | DQ18: 650 | DR18: =DQ18/DQ$4 -> 7614.2468 | DS18: =DN18+DR18 -> 211930.78 | DT18: =DS18/$DS$9 -> 0.076666751 | DV18: 650 | DW18: =DV18/DV$4 -> 7803.593 | DX18: =DS18+DW18 -> 219734.38 | DY18: =DX18/$DX$9 -> 0.076972489 | EA18: 650 | EB18: =EA18/EA$4 -> 7987.6792 | EC18: =DX18+EB18 -> 227722.06 | ED18: =EC18/$EC$9 -> 0.076374361 | EF18: 500 | EG18: =EF18/EF$4 -> 6435.2521 | EH18: =EC18+EG18 -> 234157.31 | EI18: =EH18/$EH$9 -> 0.076550044 | EK18: 500 | EL18: =EK18/EK$4 -> 6573.2691 | EM18: =DS18+EL18 -> 218504.05 | EN18: =EM18/$EM$9 -> 0.076656756 | EO18: =C18+F18+K18+P18+U18+Z18+AE18+AJ18+AO18 -> 4100 | EP18: =AT18+AY18+BD18+BI18+BN18+BS18+BX18+CC18+CH18+CM18+CR18+CW18 -> 9750 | EQ18: =EO18+EP18 -> 13850 | ER18: =DB18+DG18+DL18+DQ18+DV18+EA18+EF18 -> 4200 | ES18: =EQ18+ER18 -> 18050
A19: =RANDBETWEEN(17,44) +A18 -> 1960 | B19: Momodu Jamiu | C19: 400 | D19: 10000 | F19: 200 | G19: =F19/F$4 -> 3897.4326 | H19: =D19+G19 -> 13897.433 | I19: =H19/$H$9 -> 0.085327455 | K19: 500 | L19: =K19/K$4 -> 6576.4788 | M19: =H19+L19 -> 20473.911 | N19: =M19/$M$9 -> 0.083652714 | P19: 500 | Q19: =P19/P$4 -> 7045.1861 | R19: =M19+Q19 -> 27519.097 | S19: =R19/$R$9 -> 0.087306565 | U19: 500 | V19: =U19/U$4 -> 6457.5662 | W19: =R19+V19 -> 33976.664 | X19: =W19/$W$9 -> 0.083634357 | Z19: 500 | AA19: =Z19/Z$4 -> 6912.5494 | AB19: =W19+AA19 -> 40889.213 | AC19: =AB19/$AB$9 -> 0.086014112 | AE19: 500 | AF19: =AE19/AE$4 -> 6278.7099 | AG19: =AB19+AF19 -> 47167.923 | AH19: =AG19/$AG$9 -> 0.081028388 | AJ19: 500 | AK19: =AJ19/AJ$4 -> 6551.4445 | AL19: =AG19+AK19 -> 53719.368 | AM19: =AL19/$AL$9 -> 0.080346637 | AO19: 500 | AP19: =AO19/AO$4 -> 7122.2895 | AQ19: =AL19+AP19 -> 60841.657 | AR19: =AQ19/$AQ$9 -> 0.082080643 | AT19: 500 | AU19: =AT19/AT$4 -> 6218.4706 | AV19: =AQ19+AU19 -> 67060.128 | AW19: =AV19/$AV$9 -> 0.074785115 | AY19: 500 | AZ19: =AY19/AY$4 -> 6244.7479 | BA19: =AV19+AZ19 -> 73304.876 | BB19: =BA19/$BA$9 -> 0.069958941 | BD19: 3000 | BE19: =BD19/BD$4 -> 33967.164 | BF19: =BA19+BE19 -> 107272.04 | BG19: =BF19/$BF$9 -> 0.083810467 | BI19: 500 | BJ19: =BI19/BI$4 -> 6051.163 | BK19: =BF19+BJ19 -> 113323.2 | BL19: =BK19/$BK$9 -> 0.07884635 | BN19: 500 | BO19: =BN19/BN$4 -> 6274.5892 | BP19: =BK19+BO19 -> 119597.79 | BQ19: =BP19/$BP$9 -> 0.077274577 | BS19: 700 | BT19: =BS19/BS$4 -> 8877.6872 | BU19: =BP19+BT19 -> 128475.48 | BV19: =BU19/$BU$9 -> 0.07844661 | BX19: 800 | BY19: =BX19/BX$4 -> 10041.444 | BZ19: =BU19+BY19 -> 138516.92 | CA19: =BZ19/$BZ$9 -> 0.079634255 | CC19: 800 | CD19: =CC19/CC$4 -> 10899.01 | CE19: =BZ19+CD19 -> 149415.93 | CF19: =CE19/$CE$9 -> 0.081266374 | CH19: 800 | CI19: =CH19/CH$4 -> 10324.888 | CJ19: =CE19+CI19 -> 159740.82 | CK19: =CJ19/$CJ$9 -> 0.080045285 | CM19: 800 | CN19: =CM19/CM$4 -> 8497.3466 | CO19: =CJ19+CN19 -> 168238.17 | CP19: =CO19/$CO$9 -> 0.08098428 | CR19: 800 | CS19: =CR19/CR$4 -> 10083.074 | CT19: =CO19+CS19 -> 178321.24 | CU19: =CT19/$CT$9 -> 0.081269064 | CW19: 800 | CX19: =CW19/CW$4 -> 10566.326 | CY19: =CT19+CX19 -> 188887.57 | CZ19: =CY19/$CY$9 -> 0.082342419 | DB19: 800 | DC19: =DB19/DB$4 -> 11252.673 | DD19: =CY19+DC19 -> 200140.24 | DE19: =DD19/$DD$9 -> 0.083333704 | DG19: 800 | DH19: =DG19/DG$4 -> 11377.86 | DI19: =DD19+DH19 -> 211518.1 | DJ19: =DI19/$DI$9 -> 0.084196677 | DL19: 800 | DM19: =DL19/DL$4 -> 11468.751 | DN19: =DI19+DM19 -> 222986.85 | DO19: =DN19/$DN$9 -> 0.08361802 | DQ19: 700 | DR19: =DQ19/DQ$4 -> 8199.9581 | DS19: =DN19+DR19 -> 231186.81 | DT19: =DS19/$DS$9 -> 0.08363269 | DV19: 700 | DW19: =DV19/DV$4 -> 8403.8694 | DX19: =DS19+DW19 -> 239590.68 | DY19: =DX19/$DX$9 -> 0.08392811 | EA19: 700 | EB19: =EA19/EA$4 -> 8602.1161 | EC19: =DX19+EB19 -> 248192.8 | ED19: =EC19/$EC$9 -> 0.083239921 | EF19: 700 | EG19: =EF19/EF$4 -> 9009.3529 | EH19: =EC19+EG19 -> 257202.15 | EI19: =EH19/$EH$9 -> 0.084083797 | EK19: 500 | EL19: =EK19/EK$4 -> 6573.2691 | EM19: =DS19+EL19 -> 237760.08 | EN19: =EM19/$EM$9 -> 0.083412257 | EO19: =C19+F19+K19+P19+U19+Z19+AE19+AJ19+AO19 -> 4100 | EP19: =AT19+AY19+BD19+BI19+BN19+BS19+BX19+CC19+CH19+CM19+CR19+CW19 -> 10500 | EQ19: =EO19+EP19 -> 14600 | ER19: =DB19+DG19+DL19+DQ19+DV19+EA19+EF19 -> 5200 | ES19: =EQ19+ER19 -> 19800
A20: =RANDBETWEEN(17,44) +A19 -> 1999 | B20: Olomola Opeyemi | C20: 400 | D20: 10000 | F20: 200 | G20: =F20/F$4 -> 3897.4326 | H20: =D20+G20 -> 13897.433 | I20: =H20/$H$9 -> 0.085327455 | K20: 500 | L20: =K20/K$4 -> 6576.4788 | M20: =H20+L20 -> 20473.911 | N20: =M20/$M$9 -> 0.083652714 | P20: 500 | Q20: =P20/P$4 -> 7045.1861 | R20: =M20+Q20 -> 27519.097 | S20: =R20/$R$9 -> 0.087306565 | U20: 500 | V20: =U20/U$4 -> 6457.5662 | W20: =R20+V20 -> 33976.664 | X20: =W20/$W$9 -> 0.083634357 | Z20: 500 | AA20: =Z20/Z$4 -> 6912.5494 | AB20: =W20+AA20 -> 40889.213 | AC20: =AB20/$AB$9 -> 0.086014112 | AE20: 500 | AF20: =AE20/AE$4 -> 6278.7099 | AG20: =AB20+AF20 -> 47167.923 | AH20: =AG20/$AG$9 -> 0.081028388 | AJ20: 1000 | AK20: =AJ20/AJ$4 -> 13102.889 | AL20: =AG20+AK20 -> 60270.812 | AM20: =AL20/$AL$9 -> 0.09014546 | AO20: 0 | AP20: =AO20/AO$4 -> 0 | AQ20: =AL20+AP20 -> 60270.812 | AR20: =AQ20/$AQ$9 -> 0.081310524 | AT20: 0 | AU20: =AT20/AT$4 -> 0 | AV20: =AQ20+AU20 -> 60270.812 | AW20: =AV20/$AV$9 -> 0.067213705 | AY20: 1000 | AZ20: =AY20/AY$4 -> 12489.496 | BA20: =AV20+AZ20 -> 72760.308 | BB20: =BA20/$BA$9 -> 0.06943923 | BD20: 0 | BE20: =BD20/BD$4 -> 0 | BF20: =BA20+BE20 -> 72760.308 | BG20: =BF20/$BF$9 -> 0.05684683 | BI20: 3000 | BJ20: =BI20/BI$4 -> 36306.978 | BK20: =BF20+BJ20 -> 109067.29 | BL20: =BK20/$BK$9 -> 0.075885231 | BN20: 1500 | BO20: =BN20/BN$4 -> 18823.768 | BP20: =BK20+BO20 -> 127891.05 | BQ20: =BP20/$BP$9 -> 0.082633023 | BS20: 1500 | BT20: =BS20/BS$4 -> 19023.615 | BU20: =BP20+BT20 -> 146914.67 | BV20: =BU20/$BU$9 -> 0.089705505 | BX20: 1000 | BY20: =BX20/BX$4 -> 12551.805 | BZ20: =BU20+BY20 -> 159466.47 | CA20: =BZ20/$BZ$9 -> 0.091678284 | CC20: 1000 | CD20: =CC20/CC$4 -> 13623.763 | CE20: =BZ20+CD20 -> 173090.24 | CF20: =CE20/$CE$9 -> 0.094142677 | CH20: 500 | CI20: =CH20/CH$4 -> 6453.0552 | CJ20: =CE20+CI20 -> 179543.29 | CK20: =CJ20/$CJ$9 -> 0.089968198 | CM20: 500 | CN20: =CM20/CM$4 -> 5310.8416 | CO20: =CJ20+CN20 -> 184854.13 | CP20: =CO20/$CO$9 -> 0.088982655 | CR20: 500 | CS20: =CR20/CR$4 -> 6301.9211 | CT20: =CO20+CS20 -> 191156.05 | CU20: =CT20/$CT$9 -> 0.087118469 | CW20: 700 | CX20: =CW20/CW$4 -> 9245.5353 | CY20: =CT20+CX20 -> 200401.59 | CZ20: =CY20/$CY$9 -> 0.087361767 | DB20: 700 | DC20: =DB20/DB$4 -> 9846.0888 | DD20: =CY20+DC20 -> 210247.68 | DE20: =DD20/$DD$9 -> 0.087542204 | DG20: 700 | DH20: =DG20/DG$4 -> 9955.6273 | DI20: =DD20+DH20 -> 220203.31 | DJ20: =DI20/$DI$9 -> 0.0876539 | DL20: 700 | DM20: =DL20/DL$4 -> 10035.157 | DN20: =DI20+DM20 -> 230238.46 | DO20: =DN20/$DN$9 -> 0.086337307 | DQ20: 700 | DR20: =DQ20/DQ$4 -> 8199.9581 | DS20: =DN20+DR20 -> 238438.42 | DT20: =DS20/$DS$9 -> 0.086255988 | DV20: 700 | DW20: =DV20/DV$4 -> 8403.8694 | DX20: =DS20+DW20 -> 246842.29 | DY20: =DX20/$DX$9 -> 0.086468334 | EA20: 700 | EB20: =EA20/EA$4 -> 8602.1161 | EC20: =DX20+EB20 -> 255444.41 | ED20: =EC20/$EC$9 -> 0.085671997 | EF20: 700 | EG20: =EF20/EF$4 -> 9009.3529 | EH20: =EC20+EG20 -> 264453.76 | EI20: =EH20/$EH$9 -> 0.086454474 | EK20: 500 | EL20: =EK20/EK$4 -> 6573.2691 | EM20: =DS20+EL20 -> 245011.69 | EN20: =EM20/$EM$9 -> 0.085956306 | EO20: =C20+F20+K20+P20+U20+Z20+AE20+AJ20+AO20 -> 4100 | EP20: =AT20+AY20+BD20+BI20+BN20+BS20+BX20+CC20+CH20+CM20+CR20+CW20 -> 11200 | EQ20: =EO20+EP20 -> 15300 | ER20: =DB20+DG20+DL20+DQ20+DV20+EA20+EF20 -> 4900 | ES20: =EQ20+ER20 -> 20200
A21: =RANDBETWEEN(17,44) +A20 -> 2043 | B21: Olutola Temitope | C21: 400 | D21: 10000 | F21: 200 | G21: =F21/F$4 -> 3897.4326 | H21: =D21+G21 -> 13897.433 | I21: =H21/$H$9 -> 0.085327455 | K21: 525 | L21: =K21/K$4 -> 6905.3027 | M21: =H21+L21 -> 20802.735 | N21: =M21/$M$9 -> 0.084996229 | P21: 500 | Q21: =P21/P$4 -> 7045.1861 | R21: =M21+Q21 -> 27847.921 | S21: =R21/$R$9 -> 0.088349786 | U21: 500 | V21: =U21/U$4 -> 6457.5662 | W21: =R21+V21 -> 34305.488 | X21: =W21/$W$9 -> 0.084443765 | Z21: 0 | AA21: =Z21/Z$4 -> 0 | AB21: =W21+AA21 -> 34305.488 | AC21: =AB21/$AB$9 -> 0.072164658 | AE21: 1000 | AF21: =AE21/AE$4 -> 12557.42 | AG21: =AB21+AF21 -> 46862.907 | AH21: =AG21/$AG$9 -> 0.08050441 | AJ21: 600 | AK21: =AJ21/AJ$4 -> 7861.7335 | AL21: =AG21+AK21 -> 54724.641 | AM21: =AL21/$AL$9 -> 0.081850198 | AO21: 600 | AP21: =AO21/AO$4 -> 8546.7473 | AQ21: =AL21+AP21 -> 63271.388 | AR21: =AQ21/$AQ$9 -> 0.085358561 | AT21: 1000 | AU21: =AT21/AT$4 -> 12436.941 | AV21: =AQ21+AU21 -> 75708.33 | AW21: =AV21/$AV$9 -> 0.084429546 | AY21: 1500 | AZ21: =AY21/AY$4 -> 18734.244 | BA21: =AV21+AZ21 -> 94442.573 | BB21: =BA21/$BA$9 -> 0.090131828 | BD21: 2500 | BE21: =BD21/BD$4 -> 28305.97 | BF21: =BA21+BE21 -> 122748.54 | BG21: =BF21/$BF$9 -> 0.09590209 | BI21: 500 | BJ21: =BI21/BI$4 -> 6051.163 | BK21: =BF21+BJ21 -> 128799.71 | BL21: =BK21/$BK$9 -> 0.089614364 | BN21: 800 | BO21: =BN21/BN$4 -> 10039.343 | BP21: =BK21+BO21 -> 138839.05 | BQ21: =BP21/$BP$9 -> 0.089706747 | BS21: 800 | BT21: =BS21/BS$4 -> 10145.928 | BU21: =BP21+BT21 -> 148984.98 | BV21: =BU21/$BU$9 -> 0.090969627 | BX21: 400 | BY21: =BX21/BX$4 -> 5020.7219 | BZ21: =BU21+BY21 -> 154005.7 | CA21: =BZ21/$BZ$9 -> 0.088538851 | CC21: 1200 | CD21: =CC21/CC$4 -> 16348.516 | CE21: =BZ21+CD21 -> 170354.21 | CF21: =CE21/$CE$9 -> 0.092654572 | CH21: 800 | CI21: =(CH21/CH$4)*1.1 -> 11357.377 | CJ21: =CE21+CI21 -> 181711.59 | CK21: =CJ21/$CJ$9 -> 0.091054722 | CM21: 1000 | CN21: =(CM21/CM$4)*1.1 -> 11683.852 | CO21: =CJ21+CN21 -> 193395.44 | CP21: =CO21/$CO$9 -> 0.093094159 | CR21: 800 | CS21: =(CR21/CR$4)*1.1 -> 11091.381 | CT21: =CO21+CS21 -> 204486.82 | CU21: =CT21/$CT$9 -> 0.093193904 | CW21: 500 | CX21: =(CW21/CW$4)*1.1 -> 7264.3492 | CY21: =CT21+CX21 -> 211751.17 | CZ21: =CY21/$CY$9 -> 0.09230943 | DB21: 600 | DC21: =(DB21/DB$4)*1.1 -> 9283.4552 | DD21: =CY21+DC21 -> 221034.63 | DE21: =DD21/$DD$9 -> 0.092033638 | DG21: 800 | DH21: =(DG21/DG$4)*1.1 -> 12515.646 | DI21: =DD21+DH21 -> 233550.27 | DJ21: =DI21/$DI$9 -> 0.092966781 | DL21: 800 | DM21: =(DL21/DL$4)*1.1 -> 12615.626 | DN21: =DI21+DM21 -> 246165.9 | DO21: =DN21/$DN$9 -> 0.09230995 | DQ21: 800 | DR21: =(DQ21/DQ$4)*1.1 -> 10308.519 | DS21: =DN21+DR21 -> 256474.42 | DT21: =DS21/$DS$9 -> 0.092780577 | DV21: 800 | DW21: =(DV21/DV$4)*1.1 -> 10564.864 | DX21: =DS21+DW21 -> 267039.28 | DY21: =DX21/$DX$9 -> 0.093543298 | EA21: 800 | EB21: =(EA21/EA$4)*1.1 -> 10814.089 | EC21: =DX21+EB21 -> 277853.37 | ED21: =EC21/$EC$9 -> 0.093187608 | EF21: 0 | EG21: =(EF21/EF$4)*1.1 -> 0 | EH21: =EC21+EG21 -> 277853.37 | EI21: =EH21/$EH$9 -> 0.090835037 | EK21: 500 | EL21: =(EK21/EK$4)*1.1 -> 7230.596 | EM21: =DS21+EL21 -> 263705.02 | EN21: =EM21/$EM$9 -> 0.092514398 | EO21: =C21+F21+K21+P21+U21+Z21+AE21+AJ21+AO21 -> 4325 | EP21: =AT21+AY21+BD21+BI21+BN21+BS21+BX21+CC21+CH21+CM21+CR21+CW21 -> 11800 | EQ21: =EO21+EP21 -> 16125 | ER21: =DB21+DG21+DL21+DQ21+DV21+EA21+EF21 -> 4600 | ES21: =EQ21+ER21 -> 20725
A22: =RANDBETWEEN(17,44) +A21 -> 2081 | B22: Shoneye Olumuyiwa | C22: 400 | D22: 10000 | F22: 200 | G22: =F22/F$4 -> 3897.4326 | H22: =D22+G22 -> 13897.433 | I22: =H22/$H$9 -> 0.085327455 | K22: 500 | L22: =K22/K$4 -> 6576.4788 | M22: =H22+L22 -> 20473.911 | N22: =M22/$M$9 -> 0.083652714 | P22: 0 | Q22: =P22/P$4 -> 0 | R22: =M22+Q22 -> 20473.911 | S22: =R22/$R$9 -> 0.064955142 | U22: 1050 | V22: =U22/U$4 -> 13560.889 | W22: =R22+V22 -> 34034.8 | X22: =W22/$W$9 -> 0.083777462 | Z22: 500 | AA22: =Z22/Z$4 -> 6912.5494 | AB22: =W22+AA22 -> 40947.35 | AC22: =AB22/$AB$9 -> 0.086136408 | AE22: 500 | AF22: =AE22/AE$4 -> 6278.7099 | AG22: =AB22+AF22 -> 47226.06 | AH22: =AG22/$AG$9 -> 0.081128259 | AJ22: 500 | AK22: =AJ22/AJ$4 -> 6551.4445 | AL22: =AG22+AK22 -> 53777.504 | AM22: =AL22/$AL$9 -> 0.080433591 | AO22: 500 | AP22: =AO22/AO$4 -> 7122.2895 | AQ22: =AL22+AP22 -> 60899.794 | AR22: =AQ22/$AQ$9 -> 0.082159075 | AT22: 500 | AU22: =AT22/AT$4 -> 6218.4706 | AV22: =AQ22+AU22 -> 67118.264 | AW22: =AV22/$AV$9 -> 0.074849949 | AY22: 500 | AZ22: =AY22/AY$4 -> 6244.7479 | BA22: =AV22+AZ22 -> 73363.012 | BB22: =BA22/$BA$9 -> 0.070014425 | BD22: 500 | BE22: =BD22/BD$4 -> 5661.194 | BF22: =BA22+BE22 -> 79024.206 | BG22: =BF22/$BF$9 -> 0.061740745 | BI22: 500 | BJ22: =BI22/BI$4 -> 6051.163 | BK22: =BF22+BJ22 -> 85075.369 | BL22: =BK22/$BK$9 -> 0.059192489 | BN22: 500 | BO22: =BN22/BN$4 -> 6274.5892 | BP22: =BK22+BO22 -> 91349.958 | BQ22: =BP22/$BP$9 -> 0.059023075 | BS22: 500 | BT22: =BS22/BS$4 -> 6341.2051 | BU22: =BP22+BT22 -> 97691.164 | BV22: =BU22/$BU$9 -> 0.059649831 | BX22: 500 | BY22: =BX22/BX$4 -> 6275.9024 | BZ22: =BU22+BY22 -> 103967.07 | CA22: =BZ22/$BZ$9 -> 0.059771324 | CC22: 500 | CD22: =CC22/CC$4 -> 6811.8815 | CE22: =BZ22+CD22 -> 110778.95 | CF22: =CE22/$CE$9 -> 0.060251964 | CH22: 500 | CI22: =CH22/CH$4 -> 6453.0552 | CJ22: =CE22+CI22 -> 117232 | CK22: =CJ22/$CJ$9 -> 0.058744339 | CM22: 800 | CN22: =CM22/CM$4 -> 8497.3466 | CO22: =CJ22+CN22 -> 125729.35 | CP22: =CO22/$CO$9 -> 0.060521943 | CR22: 500 | CS22: =CR22/CR$4 -> 6301.9211 | CT22: =CO22+CS22 -> 132031.27 | CU22: =CT22/$CT$9 -> 0.060172628 | CW22: 500 | CX22: =CW22/CW$4 -> 6603.9538 | CY22: =CT22+CX22 -> 138635.22 | CZ22: =CY22/$CY$9 -> 0.060435739 | DB22: 500 | DC22: =DB22/DB$4 -> 7032.9206 | DD22: =CY22+DC22 -> 145668.14 | DE22: =DD22/$DD$9 -> 0.0606528 | DG22: 1000 | DH22: =DG22/DG$4 -> 14222.325 | DI22: =DD22+DH22 -> 159890.47 | DJ22: =DI22/$DI$9 -> 0.063645835 | DL22: 2000 | DM22: =DL22/DL$4 -> 28671.877 | DN22: =DI22+DM22 -> 188562.35 | DO22: =DN22/$DN$9 -> 0.070709147 | DQ22: 800 | DR22: =DQ22/DQ$4 -> 9371.3807 | DS22: =DN22+DR22 -> 197933.73 | DT22: =DS22/$DS$9 -> 0.071603264 | DV22: 700 | DW22: =DV22/DV$4 -> 8403.8694 | DX22: =DS22+DW22 -> 206337.6 | DY22: =DX22/$DX$9 -> 0.072279625 | EA22: 800 | EB22: =EA22/EA$4 -> 9830.9898 | EC22: =DX22+EB22 -> 216168.59 | ED22: =EC22/$EC$9 -> 0.07249951 | EF22: 800 | EG22: =EF22/EF$4 -> 10296.403 | EH22: =EC22+EG22 -> 226464.99 | EI22: =EH22/$EH$9 -> 0.074035293 | EK22: 500 | EL22: =EK22/EK$4 -> 6573.2691 | EM22: =DS22+EL22 -> 204507 | EN22: =EM22/$EM$9 -> 0.071746234 | EO22: =C22+F22+K22+P22+U22+Z22+AE22+AJ22+AO22 -> 4150 | EP22: =AT22+AY22+BD22+BI22+BN22+BS22+BX22+CC22+CH22+CM22+CR22+CW22 -> 6300 | EQ22: =EO22+EP22 -> 10450 | ER22: =DB22+DG22+DL22+DQ22+DV22+EA22+EF22 -> 6600 | ES22: =EQ22+ER22 -> 17050
A23: =RANDBETWEEN(17,44) +A22 -> 2103 | B23: Sule Dimeji | C23: 400 | D23: 10000 | F23: 0 | G23: =F23/F$4 -> 0 | H23: =D23+G23 -> 10000 | I23: =H23/$H$9 -> 0.061397999 | K23: 700 | L23: =K23/K$4 -> 9207.0703 | M23: =H23+L23 -> 19207.07 | N23: =M23/$M$9 -> 0.07847663 | P23: 0 | Q23: =P23/P$4 -> 0 | R23: =M23+Q23 -> 19207.07 | S23: =R23/$R$9 -> 0.060935986 | U23: 1000 | V23: =U23/U$4 -> 12915.132 | W23: =R23+V23 -> 32122.203 | X23: =W23/$W$9 -> 0.079069558 | Z23: 0 | AA23: =Z23/Z$4 -> 0 | AB23: =W23+AA23 -> 32122.203 | AC23: =AB23/$AB$9 -> 0.067571923 | AE23: 2500 | AF23: =AE23/AE$4 -> 31393.55 | AG23: =AB23+AF23 -> 63515.752 | AH23: =AG23/$AG$9 -> 0.10911184 | AJ23: 500 | AK23: =AJ23/AJ$4 -> 6551.4445 | AL23: =AG23+AK23 -> 70067.197 | AM23: =AL23/$AL$9 -> 0.10479765 | AO23: 500 | AP23: =AO23/AO$4 -> 7122.2895 | AQ23: =AL23+AP23 -> 77189.486 | AR23: =AQ23/$AQ$9 -> 0.10413528 | AT23: 5500 | AU23: =AT23/AT$4 -> 68403.177 | AV23: =AQ23+AU23 -> 145592.66 | AW23: =AV23/$AV$9 -> 0.1623642 | AY23: 500 | AZ23: =AY23/AY$4 -> 6244.7479 | BA23: =AV23+AZ23 -> 151837.41 | BB23: =BA23/$BA$9 -> 0.14490693 | BD23: 500 | BE23: =BD23/BD$4 -> 5661.194 | BF23: =BA23+BE23 -> 157498.61 | BG23: =BF23/$BF$9 -> 0.12305193 | BI23: 500 | BJ23: =BI23/BI$4 -> 6051.163 | BK23: =BF23+BJ23 -> 163549.77 | BL23: =BK23/$BK$9 -> 0.11379225 | BN23: 500 | BO23: =BN23/BN$4 -> 6274.5892 | BP23: =BK23+BO23 -> 169824.36 | BQ23: =BP23/$BP$9 -> 0.10972699 | BS23: 500 | BT23: =BS23/BS$4 -> 6341.2051 | BU23: =BP23+BT23 -> 176165.56 | BV23: =BU23/$BU$9 -> 0.10756598 | BX23: 500 | BY23: =BX23/BX$4 -> 6275.9024 | BZ23: =BU23+BY23 -> 182441.47 | CA23: =BZ23/$BZ$9 -> 0.10488675 | CC23: 500 | CD23: =CC23/CC$4 -> 6811.8815 | CE23: =BZ23+CD23 -> 189253.35 | CF23: =CE23/$CE$9 -> 0.10293369 | CH23: 2500 | CI23: =CH23/CH$4 -> 32265.276 | CJ23: =CE23+CI23 -> 221518.62 | CK23: =CJ23/$CJ$9 -> 0.11100182 | CM23: 500 | CN23: =CM23/CM$4 -> 5310.8416 | CO23: =CJ23+CN23 -> 226829.46 | CP23: =CO23/$CO$9 -> 0.10918819 | CR23: 800 | CS23: =CR23/CR$4 -> 10083.074 | CT23: =CO23+CS23 -> 236912.54 | CU23: =CT23/$CT$9 -> 0.10797177 | CW23: 800 | CX23: =CW23/CW$4 -> 10566.326 | CY23: =CT23+CX23 -> 247478.86 | CZ23: =CY23/$CY$9 -> 0.10788433 | DB23: 800 | DC23: =DB23/DB$4 -> 11252.673 | DD23: =CY23+DC23 -> 258731.54 | DE23: =DD23/$DD$9 -> 0.10772975 | DG23: 800 | DH23: =DG23/DG$4 -> 11377.86 | DI23: =DD23+DH23 -> 270109.4 | DJ23: =DI23/$DI$9 -> 0.10751947 | DL23: 800 | DM23: =DL23/DL$4 -> 11468.751 | DN23: =DI23+DM23 -> 281578.15 | DO23: =DN23/$DN$9 -> 0.10558922 | DQ23: 800 | DR23: =DQ23/DQ$4 -> 9371.3807 | DS23: =DN23+DR23 -> 290949.53 | DT23: =DS23/$DS$9 -> 0.10525208 | DV23: 800 | DW23: =DV23/DV$4 -> 9604.4221 | DX23: =DS23+DW23 -> 300553.95 | DY23: =DX23/$DX$9 -> 0.10528342 | EA23: 800 | EB23: =EA23/EA$4 -> 9830.9898 | EC23: =DX23+EB23 -> 310384.94 | ED23: =EC23/$EC$9 -> 0.10409818 | EF23: 800 | EG23: =EF23/EF$4 -> 10296.403 | EH23: =EC23+EG23 -> 320681.34 | EI23: =EH23/$EH$9 -> 0.10483624 | EK23: 500 | EL23: =EK23/EK$4 -> 6573.2691 | EM23: =DS23+EL23 -> 297522.8 | EN23: =EM23/$EM$9 -> 0.10437853 | EO23: =C23+F23+K23+P23+U23+Z23+AE23+AJ23+AO23 -> 5600 | EP23: =AT23+AY23+BD23+BI23+BN23+BS23+BX23+CC23+CH23+CM23+CR23+CW23 -> 13600 | EQ23: =EO23+EP23 -> 19200 | ER23: =DB23+DG23+DL23+DQ23+DV23+EA23+EF23 -> 5600 | ES23: =EQ23+ER23 -> 24800
A24: =RANDBETWEEN(17,44) +A23 -> 2143 | B24: Adesina Ajibola | CH24: 2250 | CI24: =CH24/($CC$4*2) -> 15326.733 | CJ24: 15326.733 | CK24: =CJ24/$CJ$9 -> 0.0076801454 | CM24: 0 | CN24: 0 | CO24: 15326.733 | CP24: =CO24/$CO$9 -> 0.0073777817 | CR24: 2750 | CS24: =CR24/($CC$4*2) -> 18732.674 | CT24: =CO24+CS24 -> 34059.408 | CU24: =CT24/$CT$9 -> 0.015522414 | CW24: 0 | CX24: 0 | CY24: =CT24+CX24 -> 34059.408 | CZ24: =CY24/$CY$9 -> 0.014847637 | DB24: 0 | DC24: 0 | DD24: =CY24+DC24 -> 34059.408 | DE24: =DD24/$DD$9 -> 0.014181539 | DG24: 2500 | DH24: 18357.75 | DI24: =DD24+DH24 -> 52417.158 | DJ24: =DI24/$DI$9 -> 0.02086512 | DL24: 1000 | DM24: =DL24/DL$4 -> 14335.939 | DN24: =DI24+DM24 -> 66753.096 | DO24: =DN24/$DN$9 -> 0.025031798 | DQ24: 0 | DR24: =DQ24/DQ$4 -> 0 | DS24: =DN24+DR24 -> 66753.096 | DT24: =DS24/$DS$9 -> 0.024148181 | DV24: 1000 | DW24: =DV24/DV$4 -> 12005.528 | DX24: =DS24+DW24 -> 78758.624 | DY24: =DX24/$DX$9 -> 0.02758898 | EA24: 1000 | EB24: =EA24/EA$4 -> 12288.737 | EC24: =DX24+EB24 -> 91047.361 | ED24: =EC24/$EC$9 -> 0.030535839 | EF24: 0 | EG24: =EF24/EF$4 -> 0 | EH24: =EC24+EG24 -> 91047.361 | EI24: =EH24/$EH$9 -> 0.029764945 | EK24: 500 | EL24: =EK24/EK$4 -> 6573.2691 | EM24: =DS24+EL24 -> 73326.365 | EN24: =EM24/$EM$9 -> 0.025724746 | EO24: =C24+F24+K24+P24+U24+Z24+AE24+AJ24+AO24 -> 0 | EP24: =AT24+AY24+BD24+BI24+BN24+BS24+BX24+CC24+CH24+CM24+CR24+CW24 -> 5000 | EQ24: =EO24+EP24 -> 5000 | ER24: =DB24+DG24+DL24+DQ24+DV24+EA24+EF24 -> 5500 | ES24: =EQ24+ER24 -> 10500
A25: =RANDBETWEEN(17,44) +A23 -> 2123 | B25: Axos Interest | AO25: 92.76 | AT25: 192.05 | AY25: 225.41 | BD25: 276.84 | BI25: 244.6 | BS25: 637.18 | BX25: 372.49 | CH25: 397.89 | CM25: 2.5 | CR25: 0 | CW25: 115.3 | DG25: 92.39 | DL25: 159.89 | DQ25: 80.19 | EA25: 210.36 | EF25: 194.85 | EO25: =C25+F25+K25+P25+U25+Z25+AE25+AJ25+AO25 -> 92.76 | EP25: =AT25+AY25+BD25+BI25+BN25+BS25+BX25+CC25+CH25+CM25+CR25+CW25 -> 2464.26 | EQ25: =EO25+EP25 -> 2557.02 | ER25: =DB25+DG25+DL25+DQ25+DV25+EA25+EF25 -> 737.68 | ES25: =EQ25+ER25 -> 3294.7
A26: =RANDBETWEEN(17,44) +A25 -> 2140 | B26: Misc Income | AM26: =SUM(AM12:AM23) -> 1 | AR26: =SUM(AR12:AR23) -> 1 | AW26: =SUM(AW12:AW23) -> 1 | BB26: =SUM(BB12:BB23) -> 1 | BG26: =SUM(BG12:BG23) -> 1 | BL26: =SUM(BL12:BL23) -> 1 | BQ26: =SUM(BQ12:BQ23) -> 1 | BV26: =SUM(BV12:BV23) -> 1 | CA26: =SUM(CA12:CA23) -> 1 | CH26: 2750 | CM26: 10107.5 | CR26: 0 | CW26: 0 | DB26: 0 | DG26: 0 | DL26: 0 | EO26: =C26+F26+K26+P26+U26+Z26+AE26+AJ26+AO26 -> 0 | EP26: =AT26+AY26+BD26+BI26+BN26+BS26+BX26+CC26+CH26+CM26+CR26+CW26 -> 12857.5 | EQ26: =EO26+EP26 -> 12857.5 | ER26: =DB26+DG26+DL26+DQ26+DV26+EA26+EF26 -> 0 | ES26: =EQ26+ER26 -> 12857.5
A27: =RANDBETWEEN(17,44) +A26 -> 2166 | B27: Income from Crystals | CM27: 0 | CR27: 0 | CW27: 0 | DB27: 0 | DG27: 0 | DL27: 0 | DQ27: 18000 | EO27: =C27+F27+K27+P27+U27+Z27+AE27+AJ27+AO27 -> 0 | EP27: =AT27+AY27+BD27+BI27+BN27+BS27+BX27+CC27+CH27+CM27+CR27+CW27 -> 0 | EQ27: =EO27+EP27 -> 0 | ER27: =DB27+DG27+DL27+DQ27+DV27+EA27+EF27 -> 18000 | ES27: =EQ27+ER27 -> 18000
A28: =RANDBETWEEN(17,44) +A27 -> 2192 | B28: 404 Kirby house Value | AH28: =SUM(AH12:AH26) -> 1 | CM28: 538000 | CR28: 521200 | CW28: 518100 | DB28: 518100 | DG28: 518100 | DL28: 518100 | DQ28: 518100 | DV28: 518100 | EA28: 518100 | EF28: 518100
A29: =RANDBETWEEN(17,44) +A28 -> 2236 | B29: 404 Kirby house Debt | CM29: -373058.43 | CR29: -386250 | CW29: -385892.25 | DB29: -385892.25 | DG29: -385532 | DL29: -383701.05 | DQ29: -382955.61 | DV29: -382580.36 | EA29: -382203.12 | EF29: -382203.12
B30: Note | CH30: Misc = new member form $250 + new member fee $2500 | EO30: =SUM(EO12:EO29) -> 50567.76 | EP30: =SUM(EP11:EP29) -> 143401.76 | EQ30: =SUM(EQ11:EQ29) -> 193969.52 | ER30: =SUM(ER12:ER29) -> 77887.68 | ES30: =SUM(ES11:ES29) -> 271857.2
CF31: =SUM(CF12:CF23) -> 1 | CK31: =SUM(CK12:CK24) -> 1 | CP31: =SUM(CP12:CP24) -> 1 | CU31: =SUM(CU12:CU24) -> 1 | CZ31: =SUM(CZ12:CZ24) -> 1 | DE31: =SUM(DE12:DE24) -> 1 | DJ31: =SUM(DJ12:DJ24) -> 1 | DO31: =SUM(DO12:DO24) -> 1 | DT31: =SUM(DT12:DT24) -> 1 | DY31: =SUM(DY12:DY24) -> 1 | ED31: =SUM(ED12:ED24) -> 1 | EI31: =SUM(EI12:EI24) -> 1 | EN31: =SUM(EN12:EN24) -> 1
EN33: Investment Only | EO33: =SUM(EO12:EO24) -> 50475 | EP33: =SUM(EP12:EP24) -> 128080 | EQ33: =SUM(EQ12:EQ24) -> 178555 | ER33: =SUM(ER12:ER24) -> 59150 | ES33: =SUM(ES12:ES24) -> 237705
CM34: Misc income
CM35: Downpayment refund | CO35: 5000
A36: Notes: Factor Expenses and Profit .Eventually, true valuation is a factor of income, expenses and associated profit | CM36: DJ commision payback | CO36: 5107.5

Sheet Expense Entry
K2: H I G H L I G H T C A T E G O R Y | N2: M O S T C O M M O N T A X R A T E (%)
B3: E X P E N S E
K4: EMPTY | N4: 0.1
B5: - E N T R Y -
E8: T O T A L E X P E N S E S | F8: =SUM(F11:F1001) -> 203431.28 | H8: =SUM(H11:H1001) -> 182253.02 | I8: =SUM(I11:I1001) -> 18233.462
B9: I D | C9: D A T E | D9: C A T E G O R Y | E9: D E S C R I P T I O N | F9: T O T A L A M O U N T | G9: T A X % | H9: N E T A M O U N T | I9: T A X A M O U N T | J9: P A I D W I T H | K9: N O T E S
C11: 45077 | D11: Legal Zoom | E11: Registration | F11: 842.1 | H11: =F11-I11 -> 765.54545 | I11: =F11-(F11/(1+IF(G11="",$N$4,G11))) -> 76.554545 | J11: Bank Account | Q11: =IF(C11="","",MONTH(C11)) -> 5 | R11: =IF(C11="","",YEAR(C11)) -> 2023
C12: 45110 | D12: Google GSuite | E12: Monthly Fees | F12: 12.96 | H12: =F12-I12 -> 11.781818 | I12: =F12-(F12/(1+IF(G12="",$N$4,G12))) -> 1.1781818 | J12: Bank Account | Q12: =IF(C12="","",MONTH(C12)) -> 7 | R12: =IF(C12="","",YEAR(C12)) -> 2023
C13: 45140 | D13: Google GSuite | E13: Monthly Fees | F13: 14.4 | H13: =F13-I13 -> 13.090909 | I13: =F13-(F13/(1+IF(G13="",$N$4,G13))) -> 1.3090909 | J13: Bank Account | Q13: =IF(C13="","",MONTH(C13)) -> 8 | R13: =IF(C13="","",YEAR(C13)) -> 2023
C14: 45174 | D14: Google GSuite | E14: Monthly Fees | F14: 20 | H14: =F14-I14 -> 18.181818 | I14: =F14-(F14/(1+IF(G14="",$N$4,G14))) -> 1.8181818 | J14: Bank Account | Q14: =IF(C14="","",MONTH(C14)) -> 9 | R14: =IF(C14="","",YEAR(C14)) -> 2023
C15: 45201 | D15: Google GSuite | E15: Monthly Fees | F15: 28.8 | H15: =F15-I15 -> 26.181818 | I15: =F15-(F15/(1+IF(G15="",$N$4,G15))) -> 2.6181818 | J15: Bank Account | Q15: =IF(C15="","",MONTH(C15)) -> 10 | R15: =IF(C15="","",YEAR(C15)) -> 2023
C16: 45232 | D16: Google GSuite | E16: Monthly Fees | F16: 28.8 | H16: =F16-I16 -> 26.181818 | I16: =F16-(F16/(1+IF(G16="",$N$4,G16))) -> 2.6181818 | J16: Bank Account | Q16: =IF(C16="","",MONTH(C16)) -> 11 | R16: =IF(C16="","",YEAR(C16)) -> 2023
C17: 45260 | E17: Fee | F17: 1 | H17: =F17-I17 -> 0.90909091 | I17: =F17-(F17/(1+IF(G17="",$N$4,G17))) -> 0.090909091 | J17: Bank Account | Q17: =IF(C17="","",MONTH(C17)) -> 11 | R17: =IF(C17="","",YEAR(C17)) -> 2023
C18: 45261 | D18: Google GSuite | E18: Monthly Fees | F18: 28.8 | H18: =F18-I18 -> 26.181818 | I18: =F18-(F18/(1+IF(G18="",$N$4,G18))) -> 2.6181818 | J18: Bank Account | Q18: =IF(C18="","",MONTH(C18)) -> 12 | R18: =IF(C18="","",YEAR(C18)) -> 2023
C19: 45261 | E19: Bank feee | F19: 1 | H19: =F19-I19 -> 0.90909091 | I19: =F19-(F19/(1+IF(G19="",$N$4,G19))) -> 0.090909091 | J19: Bank Account | Q19: =IF(C19="","",MONTH(C19)) -> 12 | R19: =IF(C19="","",YEAR(C19)) -> 2023
C20: 45272 | E20: Christmas Gift | F20: 502.69 | H20: =F20-I20 -> 456.99091 | I20: =F20-(F20/(1+IF(G20="",$N$4,G20))) -> 45.699091 | J20: Bank Account | Q20: =IF(C20="","",MONTH(C20)) -> 12 | R20: =IF(C20="","",YEAR(C20)) -> 2023
C21: 45278 | E21: Christmas Party | F21: 2150 | H21: =F21-I21 -> 1954.5455 | I21: =F21-(F21/(1+IF(G21="",$N$4,G21))) -> 195.45455 | J21: Bank Account | Q21: =IF(C21="","",MONTH(C21)) -> 12 | R21: =IF(C21="","",YEAR(C21)) -> 2023
C22: 45293 | D22: Google GSuite | E22: Monthly Fees | F22: 28.8 | H22: =F22-I22 -> 26.181818 | I22: =F22-(F22/(1+IF(G22="",$N$4,G22))) -> 2.6181818 | J22: Bank Account | Q22: =IF(C22="","",MONTH(C22)) -> 1 | R22: =IF(C22="","",YEAR(C22)) -> 2024
C23: 45324 | D23: Google GSuite | E23: Monthly Fees | F23: 28.8 | H23: =F23-I23 -> 26.181818 | I23: =F23-(F23/(1+IF(G23="",$N$4,G23))) -> 2.6181818 | J23: Bank Account | Q23: =IF(C23="","",MONTH(C23)) -> 2 | R23: =IF(C23="","",YEAR(C23)) -> 2024
C24: 45335 | E24: Bank feee | F24: 1 | H24: =F24-I24 -> 0.90909091 | I24: =F24-(F24/(1+IF(G24="",$N$4,G24))) -> 0.090909091 | J24: Bank Account | Q24: =IF(C24="","",MONTH(C24)) -> 2 | R24: =IF(C24="","",YEAR(C24)) -> 2024
C25: 45348 | D25: Legal Zoom | E25: Registration | F25: 99 | H25: =F25-I25 -> 90 | I25: =F25-(F25/(1+IF(G25="",$N$4,G25))) -> 9 | J25: Bank Account | Q25: =IF(C25="","",MONTH(C25)) -> 2 | R25: =IF(C25="","",YEAR(C25)) -> 2024
C26: 45384 | D26: Google GSuite | E26: Monthly Fees | F26: 28.8 | H26: =F26-I26 -> 26.181818 | I26: =F26-(F26/(1+IF(G26="",$N$4,G26))) -> 2.6181818 | J26: Bank Account | Q26: =IF(C26="","",MONTH(C26)) -> 4 | R26: =IF(C26="","",YEAR(C26)) -> 2024
C27: 45394 | E27: Bank feee | F27: 1 | H27: =F27-I27 -> 0.90909091 | I27: =F27-(F27/(1+IF(G27="",$N$4,G27))) -> 0.090909091 | J27: Bank Account | Q27: =IF(C27="","",MONTH(C27)) -> 4 | R27: =IF(C27="","",YEAR(C27)) -> 2024
C28: 45414 | D28: Google GSuite | E28: Monthly Fees | F28: 28.8 | H28: =F28-I28 -> 26.181818 | I28: =F28-(F28/(1+IF(G28="",$N$4,G28))) -> 2.6181818 | J28: Bank Account | Q28: =IF(C28="","",MONTH(C28)) -> 5 | R28: =IF(C28="","",YEAR(C28)) -> 2024
C29: 45446 | D29: Google GSuite | E29: Monthly Fees | F29: 28.8 | H29: =F29-I29 -> 26.181818 | I29: =F29-(F29/(1+IF(G29="",$N$4,G29))) -> 2.6181818 | Q29: =IF(C29="","",MONTH(C29)) -> 6 | R29: =IF(C29="","",YEAR(C29)) -> 2024
C30: 45454 | E30: Bank feee | F30: 1 | H30: =F30-I30 -> 0.90909091 | I30: =F30-(F30/(1+IF(G30="",$N$4,G30))) -> 0.090909091 | Q30: =IF(C31="","",MONTH(C31)) -> 6 | R30: =IF(C31="","",YEAR(C31)) -> 2024
C31: 45471 | E31: Registration | F31: 203 | H31: =F31-I31 -> 184.54545 | I31: =F31-(F31/(1+IF(G31="",$N$4,G31))) -> 18.454545 | Q31: =IF(#REF!="","",MONTH(#REF!)) -> #REF! | R31: =IF(#REF!="","",YEAR(#REF!)) -> #REF!
C32: 45475 | D32: Google GSuite | E32: Monthly Fees | F32: 28.8 | H32: =F32-I32 -> 26.181818 | I32: =F32-(F32/(1+IF(G32="",$N$4,G32))) -> 2.6181818 | J32: Bank Account | Q32: =IF(C32="","",MONTH(C32)) -> 7 | R32: =IF(C32="","",YEAR(C32)) -> 2024
C33: 45506 | D33: Google GSuite | E33: Monthly Fees | F33: 28.8 | H33: =F33-I33 -> 26.181818 | I33: =F33-(F33/(1+IF(G33="",$N$4,G33))) -> 2.6181818 | J33: Bank Account | Q33: =IF(C33="","",MONTH(C33)) -> 8 | R33: =IF(C33="","",YEAR(C33)) -> 2024
C34: 45520 | E34: Mortgage Due Diligence Fee | F34: 5000 | H34: =F34-I34 -> 4545.4545 | I34: =F34-(F34/(1+IF(G34="",$N$4,G34))) -> 454.54545 | J34: Bank Account | Q34: =IF(C34="","",MONTH(C34)) -> 8 | R34: =IF(C34="","",YEAR(C34)) -> 2024
C35: 45520 | E35: Mortgage Earnest Money | F35: 5000 | H35: =F35-I35 -> 4545.4545 | I35: =F35-(F35/(1+IF(G35="",$N$4,G35))) -> 454.54545 | J35: Bank Account | Q35: =IF(C35="","",MONTH(C35)) -> 8 | R35: =IF(C35="","",YEAR(C35)) -> 2024
C36: 45520 | E36: Bank fee | F36: 10 | H36: =F36-I36 -> 9.0909091 | I36: =F36-(F36/(1+IF(G36="",$N$4,G36))) -> 0.90909091 | J36: Bank Account | Q36: =IF(C36="","",MONTH(C36)) -> 8 | R36: =IF(C36="","",YEAR(C36)) -> 2024
C37: 45520 | E37: Bank fee | F37: 30 | H37: =F37-I37 -> 27.272727 | I37: =F37-(F37/(1+IF(G37="",$N$4,G37))) -> 2.7272727 | J37: Bank Account | Q37: =IF(C37="","",MONTH(C37)) -> 8 | R37: =IF(C37="","",YEAR(C37)) -> 2024
C38: 45530 | E38: Ipostal | F38: 14.99 | H38: =F38-I38 -> 13.627273 | I38: =F38-(F38/(1+IF(G38="",$N$4,G38))) -> 1.3627273 | J38: Bank Account | Q38: =IF(C38="","",MONTH(C38)) -> 8 | R38: =IF(C38="","",YEAR(C38)) -> 2024
C39: 45537 | D39: Google GSuite | E39: Monthly Fees | F39: 28.8 | H39: =F39-I39 -> 26.181818 | I39: =F39-(F39/(1+IF(G39="",$N$4,G39))) -> 2.6181818 | J39: Bank Account | Q39: =IF(C39="","",MONTH(C39)) -> 9 | R39: =IF(C39="","",YEAR(C39)) -> 2024
C40: 45554 | E40: Sec of State Fee | F40: 23 | H40: =F40-I40 -> 20.909091 | I40: =F40-(F40/(1+IF(G40="",$N$4,G40))) -> 2.0909091 | J40: Bank Account | Q40: =IF(C40="","",MONTH(C40)) -> 9 | R40: =IF(C40="","",YEAR(C40)) -> 2024
C41: 45554 | E41: Check of Book fee | F41: 40.92 | H41: =F41-I41 -> 37.2 | I41: =F41-(F41/(1+IF(G41="",$N$4,G41))) -> 3.72 | J41: Bank Account | Q41: =IF(C41="","",MONTH(C41)) -> 9 | R41: =IF(C41="","",YEAR(C41)) -> 2024
C42: 45554 | E42: Check of Book fee | F42: 40.92 | H42: =F42-I42 -> 37.2 | I42: =F42-(F42/(1+IF(G42="",$N$4,G42))) -> 3.72 | J42: Bank Account | Q42: =IF(C42="","",MONTH(C42)) -> 9 | R42: =IF(C42="","",YEAR(C42)) -> 2024
C43: 45555 | E43: Appraisal Fee | F43: 840 | H43: =F43-I43 -> 763.63636 | I43: =F43-(F43/(1+IF(G43="",$N$4,G43))) -> 76.363636 | Q43: =IF(C43="","",MONTH(C43)) -> 9 | R43: =IF(C43="","",YEAR(C43)) -> 2024
C44: 45555 | E44: Bank fee | F44: 25 | H44: =F44-I44 -> 22.727273 | I44: =F44-(F44/(1+IF(G44="",$N$4,G44))) -> 2.2727273 | Q44: =IF(C44="","",MONTH(C44)) -> 9 | R44: =IF(C44="","",YEAR(C44)) -> 2024
C45: 45560 | E45: Ipostal | F45: 14.99 | H45: =F45-I45 -> 13.627273 | I45: =F45-(F45/(1+IF(G45="",$N$4,G45))) -> 1.3627273 | Q45: =IF(C45="","",MONTH(C45)) -> 9 | R45: =IF(C45="","",YEAR(C45)) -> 2024
C46: 45561 | E46: Home Inspector | F46: 500 | H46: =F46-I46 -> 454.54545 | I46: =F46-(F46/(1+IF(G46="",$N$4,G46))) -> 45.454545 | Q46: =IF(C46="","",MONTH(C46)) -> 9 | R46: =IF(C46="","",YEAR(C46)) -> 2024
C47: 45562 | E47: Legal Zoom | F47: 200 | H47: =F47-I47 -> 181.81818 | I47: =F47-(F47/(1+IF(G47="",$N$4,G47))) -> 18.181818 | Q47: =IF(C47="","",MONTH(C47)) -> 9 | R47: =IF(C47="","",YEAR(C47)) -> 2024
C48: 45567 | D48: Google GSuite | E48: Monthly Fees | F48: 28.8 | H48: =F48-I48 -> 26.181818 | I48: =F48-(F48/(1+IF(G48="",$N$4,G48))) -> 2.6181818 | Q48: =IF(C48="","",MONTH(C48)) -> 10 | R48: =IF(C48="","",YEAR(C48)) -> 2024
C49: 45567 | E49: Home Insurance | F49: 199 | H49: =F49-I49 -> 180.90909 | I49: =F49-(F49/(1+IF(G49="",$N$4,G49))) -> 18.090909 | Q49: =IF(C49="","",MONTH(C49)) -> 10 | R49: =IF(C49="","",YEAR(C49)) -> 2024
C50: 45572 | E50: Sec of State Fee | F50: 13 | H50: =F50-I50 -> 11.818182 | I50: =F50-(F50/(1+IF(G50="",$N$4,G50))) -> 1.1818182 | Q50: =IF(C50="","",MONTH(C50)) -> 10 | R50: =IF(C50="","",YEAR(C50)) -> 2024
C51: 45573 | E51: 404 Kirby house down payment | F51: 136941.57 | H51: =F51-I51 -> 124492.34 | I51: =F51-(F51/(1+IF(G51="",$N$4,G51))) -> 12449.234 | Q51: =IF(C51="","",MONTH(C51)) -> 10 | R51: =IF(C51="","",YEAR(C51)) -> 2024
C52: 45573 | E52: wiire transfer fee | F52: 30 | H52: =F52-I52 -> 27.272727 | I52: =F52-(F52/(1+IF(G52="",$N$4,G52))) -> 2.7272727 | Q52: =IF(C52="","",MONTH(C52)) -> 10 | R52: =IF(C52="","",YEAR(C52)) -> 2024
C53: 45590 | E53: Ipostal | F53: 14.99 | H53: =F53-I53 -> 13.627273 | I53: =F53-(F53/(1+IF(G53="",$N$4,G53))) -> 1.3627273 | Q53: =IF(C53="","",MONTH(C53)) -> 10 | R53: =IF(C53="","",YEAR(C53)) -> 2024
C54: 45600 | D54: Google GSuite | E54: Monthly Fees | F54: 28.8 | H54: =F54-I54 -> 26.181818 | I54: =F54-(F54/(1+IF(G54="",$N$4,G54))) -> 2.6181818 | Q54: =IF(C54="","",MONTH(C54)) -> 11 | R54: =IF(C54="","",YEAR(C54)) -> 2024
C55: 45614 | E55: 404 Kirby house Mortgage | F55: 2892 | H55: =F55-I55 -> 2629.0909 | I55: =F55-(F55/(1+IF(G55="",$N$4,G55))) -> 262.90909 | Q55: =IF(C55="","",MONTH(C55)) -> 11 | R55: =IF(C55="","",YEAR(C55)) -> 2024
C56: 45615 | E56: Bank fee | F56: 1 | H56: =F56-I56 -> 0.90909091 | I56: =F56-(F56/(1+IF(G56="",$N$4,G56))) -> 0.090909091 | Q56: =IF(C56="","",MONTH(C56)) -> 11 | R56: =IF(C56="","",YEAR(C56)) -> 2024
C57: 45616 | E57: Ipostal Notary | F57: 25 | H57: =F57-I57 -> 22.727273 | I57: =F57-(F57/(1+IF(G57="",$N$4,G57))) -> 2.2727273 | Q57: =IF(C57="","",MONTH(C57)) -> 11 | R57: =IF(C57="","",YEAR(C57)) -> 2024
C58: 45621 | E58: Ipostal | F58: 14.99 | H58: =F58-I58 -> 13.627273 | I58: =F58-(F58/(1+IF(G58="",$N$4,G58))) -> 1.3627273 | Q58: =IF(C58="","",MONTH(C58)) -> 11 | R58: =IF(C58="","",YEAR(C58)) -> 2024
C59: 45614 | E59: 404 Kirby house window | F59: 555.2 | H59: =F59-I59 -> 504.72727 | I59: =F59-(F59/(1+IF(G59="",$N$4,G59))) -> 50.472727 | Q59: =IF(C59="","",MONTH(C59)) -> 11 | R59: =IF(C59="","",YEAR(C59)) -> 2024
C60: 45628 | D60: Google GSuite | E60: Monthly Fees | F60: 28.8 | H60: =F60-I60 -> 26.181818 | I60: =F60-(F60/(1+IF(G60="",$N$4,G60))) -> 2.6181818 | Q60: =IF(C60="","",MONTH(C60)) -> 12 | R60: =IF(C60="","",YEAR(C60)) -> 2024
C61: 45643 | E61: 404 Kirby house Mortgage | F61: 2892 | H61: =F61-I61 -> 2629.0909 | I61: =F61-(F61/(1+IF(G61="",$N$4,G61))) -> 262.90909 | Q61: =IF(C61="","",MONTH(C61)) -> 12 | R61: =IF(C61="","",YEAR(C61)) -> 2024
C62: 45649 | E62: December Party expenses | F62: 603.04 | H62: =F62-I62 -> 548.21818 | I62: =F62-(F62/(1+IF(G62="",$N$4,G62))) -> 54.821818 | Q62: =IF(C62="","",MONTH(C62)) -> 12 | R62: =IF(C62="","",YEAR(C62)) -> 2024
C63: 45649 | E63: Zilllow Advert | F63: 30 | H63: =F63-I63 -> 27.272727 | I63: =F63-(F63/(1+IF(G63="",$N$4,G63))) -> 2.7272727 | Q63: =IF(C63="","",MONTH(C63)) -> 12 | R63: =IF(C63="","",YEAR(C63)) -> 2024
C64: 45650 | E64: Ipostal | F64: 14.99 | H64: =F64-I64 -> 13.627273 | I64: =F64-(F64/(1+IF(G64="",$N$4,G64))) -> 1.3627273 | Q64: =IF(C64="","",MONTH(C64)) -> 12 | R64: =IF(C64="","",YEAR(C64)) -> 2024
C65: 45659 | D65: Google GSuite | E65: Monthly Fees | F65: 28.8 | H65: =F65-I65 -> 26.181818 | I65: =F65-(F65/(1+IF(G65="",$N$4,G65))) -> 2.6181818 | Q65: =IF(C65="","",MONTH(C65)) -> 1 | R65: =IF(C65="","",YEAR(C65)) -> 2025
C66: 45673 | E66: 404 Kirby house Mortgage | F66: 2892 | H66: =F66-I66 -> 2629.0909 | I66: =F66-(F66/(1+IF(G66="",$N$4,G66))) -> 262.90909 | Q66: =IF(C66="","",MONTH(C66)) -> 1 | R66: =IF(C66="","",YEAR(C66)) -> 2025
C67: 45684 | E67: Ipostal | F67: 14.99 | H67: =F67-I67 -> 13.627273 | I67: =F67-(F67/(1+IF(G67="",$N$4,G67))) -> 1.3627273 | Q67: =IF(C67="","",MONTH(C67)) -> 1 | R67: =IF(C67="","",YEAR(C67)) -> 2025
C68: 45674 | E68: Hall Rental | F68: 250 | H68: =F68-I68 -> 227.27273 | I68: =F68-(F68/(1+IF(G68="",$N$4,G68))) -> 22.727273 | Q68: =IF(C68="","",MONTH(C68)) -> 1 | R68: =IF(C68="","",YEAR(C68)) -> 2025
C69: 45687 | E69: 404 Kirby house Utility | F69: 157.57 | H69: =F69-I69 -> 143.24545 | I69: =F69-(F69/(1+IF(G69="",$N$4,G69))) -> 14.324545 | Q69: =IF(C69="","",MONTH(C69)) -> 1 | R69: =IF(C69="","",YEAR(C69)) -> 2025
C70: 45686 | E70: 404 Kirby house Fence | F70: 7300 | H70: =F70-I70 -> 6636.3636 | I70: =F70-(F70/(1+IF(G70="",$N$4,G70))) -> 663.63636 | Q70: =IF(C70="","",MONTH(C70)) -> 1 | R70: =IF(C70="","",YEAR(C70)) -> 2025
C71: 45691 | D71: Google GSuite | E71: Monthly Fees | F71: 28.8 | H71: =F71-I71 -> 26.181818 | I71: =F71-(F71/(1+IF(G71="",$N$4,G71))) -> 2.6181818 | Q71: =IF(C71="","",MONTH(C71)) -> 2 | R71: =IF(C71="","",YEAR(C71)) -> 2025
C72: 45712 | E72: 404 Kirby house Mortgage | F72: 2892 | H72: =F72-I72 -> 2629.0909 | I72: =F72-(F72/(1+IF(G72="",$N$4,G72))) -> 262.90909 | Q72: =IF(C72="","",MONTH(C72)) -> 2 | R72: =IF(C72="","",YEAR(C72)) -> 2025
C73: 45713 | E73: Ipostal | F73: 14.99 | H73: =F73-I73 -> 13.627273 | I73: =F73-(F73/(1+IF(G73="",$N$4,G73))) -> 1.3627273 | Q73: =IF(C73="","",MONTH(C73)) -> 2 | R73: =IF(C73="","",YEAR(C73)) -> 2025
C74: 45713 | E74: QBooks Monthly Fee | F74: 32.5 | H74: =F74-I74 -> 29.545455 | I74: =F74-(F74/(1+IF(G74="",$N$4,G74))) -> 2.9545455 | Q74: =IF(C74="","",MONTH(C74)) -> 2 | R74: =IF(C74="","",YEAR(C74)) -> 2025
C75: 45716 | E75: Turbo Tax | F75: 603 | H75: =F75-I75 -> 548.18182 | I75: =F75-(F75/(1+IF(G75="",$N$4,G75))) -> 54.818182 | Q75: =IF(C75="","",MONTH(C75)) -> 2 | R75: =IF(C75="","",YEAR(C75)) -> 2025
C76: 45719 | E76: Dividends Payment | F76: 225.63 | H76: =F76-I76 -> 205.11818 | I76: =F76-(F76/(1+IF(G76="",$N$4,G76))) -> 20.511818 | Q76: =IF(C76="","",MONTH(C76)) -> 3 | R76: =IF(C76="","",YEAR(C76)) -> 2025
C77: 45721 | E77: 404 Kirby house Mortgage | F77: 2891.12 | H77: =F77-I77 -> 2628.2909 | I77: =F77-(F77/(1+IF(G77="",$N$4,G77))) -> 262.82909 | Q77: =IF(C77="","",MONTH(C77)) -> 3 | R77: =IF(C77="","",YEAR(C77)) -> 2025
C78: 45734 | E78: 404 Kirby house Mortgage | F78: 2892 | H78: =F78-I78 -> 2629.0909 | I78: =F78-(F78/(1+IF(G78="",$N$4,G78))) -> 262.90909 | Q78: =IF(C78="","",MONTH(C78)) -> 3 | R78: =IF(C78="","",YEAR(C78)) -> 2025
C79: 45735 | E79: Electrical Repairs | F79: 180 | H79: =F79-I79 -> 163.63636 | I79: =F79-(F79/(1+IF(G79="",$N$4,G79))) -> 16.363636 | Q79: =IF(C79="","",MONTH(C79)) -> 3 | R79: =IF(C79="","",YEAR(C79)) -> 2025
C80: 45735 | E80: Zillow Post | F80: 29.9 | H80: =F80-I80 -> 27.181818 | I80: =F80-(F80/(1+IF(G80="",$N$4,G80))) -> 2.7181818 | Q80: =IF(C80="","",MONTH(C80)) -> 3 | R80: =IF(C80="","",YEAR(C80)) -> 2025
C81: 45737 | E81: Ipostal Notary | F81: 25 | H81: =F81-I81 -> 22.727273 | I81: =F81-(F81/(1+IF(G81="",$N$4,G81))) -> 2.2727273 | Q81: =IF(C81="","",MONTH(C81)) -> 3 | R81: =IF(C81="","",YEAR(C81)) -> 2025
C82: 45741 | E82: QBooks Monthly Fee | F82: 32.5 | H82: =F82-I82 -> 29.545455 | I82: =F82-(F82/(1+IF(G82="",$N$4,G82))) -> 2.9545455 | Q82: =IF(C82="","",MONTH(C82)) -> 3 | R82: =IF(C82="","",YEAR(C82)) -> 2025
C83: 45741 | E83: Ipostal | F83: 14.99 | H83: =F83-I83 -> 13.627273 | I83: =F83-(F83/(1+IF(G83="",$N$4,G83))) -> 1.3627273 | Q83: =IF(C83="","",MONTH(C83)) -> 3 | R83: =IF(C83="","",YEAR(C83)) -> 2025
C84: 45720 | D84: Google GSuite | E84: Monthly Fees | F84: 28.8 | H84: =F84-I84 -> 26.181818 | I84: =F84-(F84/(1+IF(G84="",$N$4,G84))) -> 2.6181818 | Q84: =IF(C85="","",MONTH(C85)) -> 4 | R84: =IF(C85="","",YEAR(C85)) -> 2025
C85: 45748 | E85: 404 Kirby house Mortgage | F85: 2891.12 | H85: =F85-I85 -> 2628.2909 | I85: =F85-(F85/(1+IF(G85="",$N$4,G85))) -> 262.82909 | Q85: =IF(C84="","",MONTH(C84)) -> 3 | R85: =IF(C84="","",YEAR(C84)) -> 2025
C86: 45751 | D86: Google GSuite | E86: Monthly Fees | F86: 28.8 | H86: =F86-I86 -> 26.181818 | I86: =F86-(F86/(1+IF(G86="",$N$4,G86))) -> 2.6181818 | Q86: =IF(#REF!="","",MONTH(#REF!)) -> #REF! | R86: =IF(#REF!="","",YEAR(#REF!)) -> #REF!
C87: 45761 | E87: 404 Kirby house Utility | F87: 114.1 | H87: =F89-I87 -> 145.45455 | I87: =F89-(F89/(1+IF(G87="",$N$4,G87))) -> 14.545455 | Q87: =IF(C87="","",MONTH(C87)) -> 4 | R87: =IF(C87="","",YEAR(C87)) -> 2025
C88: 45765 | E88: 404 Kirby house Mortgage | F88: 2892 | H88: =F90-I88 -> 29.545455 | I88: =F90-(F90/(1+IF(G88="",$N$4,G88))) -> 2.9545455 | Q88: =IF(C86="","",MONTH(C86)) -> 4 | R88: =IF(C86="","",YEAR(C86)) -> 2025
C89: 45770 | E89: 404 Kirby house Maintenance | F89: 160 | H89: =F86-I89 -> 26.181818 | I89: =F86-(F86/(1+IF(G89="",$N$4,G89))) -> 2.6181818 | Q89: =IF(C89="","",MONTH(C89)) -> 4 | R89: =IF(C89="","",YEAR(C89)) -> 2025
C90: 45772 | E90: QBooks Monthly Fee | F90: 32.5 | H90: =F90-I90 -> 22.127273 | I90: =F87-(F87/(1+IF(G90="",$N$4,G90))) -> 10.372727 | Q90: =IF(C90="","",MONTH(C90)) -> 4 | R90: =IF(C90="","",YEAR(C90)) -> 2025
C91: 45772 | E91: Ipostal | F91: 14.99 | H91: =F91-I91 -> 13.627273 | I91: =F91-(F91/(1+IF(G91="",$N$4,G91))) -> 1.3627273 | Q91: =IF(C91="","",MONTH(C91)) -> 4 | R91: =IF(C91="","",YEAR(C91)) -> 2025
C92: 45777 | E92: Transportation to Durham | F92: 355.27 | H92: =F92-I92 -> 322.97273 | I92: =F92-(F92/(1+IF(G92="",$N$4,G92))) -> 32.297273 | Q92: =IF(C92="","",MONTH(C92)) -> 4 | R92: =IF(C92="","",YEAR(C92)) -> 2025
C93: 45778 | E93: 404 Kirby house Mortgage | F93: 2891.12 | H93: =F93-I93 -> 2628.2909 | I93: =F93-(F93/(1+IF(G93="",$N$4,G93))) -> 262.82909 | Q93: =IF(C93="","",MONTH(C93)) -> 5 | R93: =IF(C93="","",YEAR(C93)) -> 2025
C94: 45779 | D94: Google GSuite | E94: Monthly Fees | F94: 28.8 | H94: =F94-I94 -> 26.181818 | I94: =F94-(F94/(1+IF(G94="",$N$4,G94))) -> 2.6181818 | Q94: =IF(C94="","",MONTH(C94)) -> 5 | R94: =IF(C94="","",YEAR(C94)) -> 2025
C95: 45790 | E95: 404 Kirby house Utility | F95: 52 | H95: =F95-I95 -> 47.272727 | I95: =F95-(F95/(1+IF(G95="",$N$4,G95))) -> 4.7272727 | Q95: =IF(C95="","",MONTH(C95)) -> 5 | R95: =IF(C95="","",YEAR(C95)) -> 2025
C96: 45779 | E96: Lawn Service | F96: 175 | H96: =F96-I96 -> 159.09091 | I96: =F96-(F96/(1+IF(G96="",$N$4,G96))) -> 15.909091 | Q96: =IF(C96="","",MONTH(C96)) -> 5 | R96: =IF(C96="","",YEAR(C96)) -> 2025
C97: 45804 | E97: QBooks Monthly Fee | F97: 65 | H97: =F97-I97 -> 59.090909 | I97: =F97-(F97/(1+IF(G97="",$N$4,G97))) -> 5.9090909 | Q97: =IF(C97="","",MONTH(C97)) -> 5 | R97: =IF(C97="","",YEAR(C97)) -> 2025
C98: 45804 | E98: Ipostal | F98: 14.99 | H98: =F98-I98 -> 13.627273 | I98: =F98-(F98/(1+IF(G98="",$N$4,G98))) -> 1.3627273 | Q98: =IF(C98="","",MONTH(C98)) -> 5 | R98: =IF(C98="","",YEAR(C98)) -> 2025
C99: 45810 | D99: Google GSuite | E99: Monthly Fees | F99: 28.8 | H99: =F99-I99 -> 26.181818 | I99: =F99-(F99/(1+IF(G99="",$N$4,G99))) -> 2.6181818 | Q99: =IF(C99="","",MONTH(C99)) -> 6 | R99: =IF(C99="","",YEAR(C99)) -> 2025
C100: 45810 | E100: 404 Kirby house Mortgage | F100: 2891.12 | H100: =F100-I100 -> 2628.2909 | I100: =F100-(F100/(1+IF(G100="",$N$4,G100))) -> 262.82909 | Q100: =IF(C100="","",MONTH(C100)) -> 6 | R100: =IF(C100="","",YEAR(C100)) -> 2025
C101: 45810 | E101: Bank Fee | F101: 39 | H101: =F101-I101 -> 35.454545 | I101: =F101-(F101/(1+IF(G101="",$N$4,G101))) -> 3.5454545 | Q101: =IF(C101="","",MONTH(C101)) -> 6 | R101: =IF(C101="","",YEAR(C101)) -> 2025
C102: 45817 | E102: Lawn Service | F102: 175 | H102: =F102-I102 -> 159.09091 | I102: =F102-(F102/(1+IF(G102="",$N$4,G102))) -> 15.909091 | Q102: =IF(C102="","",MONTH(C102)) -> 6 | R102: =IF(C102="","",YEAR(C102)) -> 2025
C103: 45824 | E103: Bank Fee | F103: 1 | H103: =F103-I103 -> 0.90909091 | I103: =F103-(F103/(1+IF(G103="",$N$4,G103))) -> 0.090909091 | Q103: =IF(C103="","",MONTH(C103)) -> 6 | R103: =IF(C103="","",YEAR(C103)) -> 2025
C104: 45825 | E104: 404 Kirby house Mortgage | F104: 2891.12 | H104: =F104-I104 -> 2628.2909 | I104: =F104-(F104/(1+IF(G104="",$N$4,G104))) -> 262.82909 | Q104: =IF(C104="","",MONTH(C104)) -> 6 | R104: =IF(C104="","",YEAR(C104)) -> 2025
...

Sheet Monthly
B3: M O N T H L Y
B5: - O V E R V I E W -
K8: M O N T H
C9: T O T A L I N C O M E | K9: 45413
K10: =MONTH(K9) -> 5 | O10: =K9 -> 45413 | S10: =YEAR(K9) -> 2024
C11: =IF(D11="","",'Setup Page'!$W$4) -> $ | D11: ='Back-End Page'!C43 -> 0 | K11: A M O U N T
K12: T O T A L
K14: I N C O M E | Y14: E X P E N S E S
C15: T O T A L E X P E N S E S | AN15: I N C O M E E N T R Y | AV15: E X P E N S E E N T R Y
K16: C A T E G O R I E S | S16: A M O U N T | Y16: C A T E G O R I E S | AG16: A M O U N T
C17: =IF(D17="","",'Setup Page'!$W$4) -> $ | D17: ='Back-End Page'!C88 -> 28.8 | K17: ='Setup Page'!C18 -> Investment | S17: =IF(K17="","",'Setup Page'!$W$4) -> $ | T17: =IF($K$12="T O T A L",SUMIFS('Income Entry'!$F$11:$F59,'Income Entry'!$L$11:$L59,K17,'Income Entry'!$S$11:$S59,$K$10,'Income Entry'!$T$11:$T59,$S$10),IF($K$12="N E T",SUMIFS('Income Entry'!$H$11:$H59,'Income Entry'!$L$11:$L59,K17,'Income Entry'!$S$11:$S59,$K$10,'Income Entry'!$T$11:$T59,$S$10),IF($K$12="T A X",SUMIFS('Income Entry'!$I$11:$I59,'Income Entry'!$L$11:$L59,K17,'Income Entry'!$S$11:$S59,$K$10,'Income Entry'!$T$11:$T59,$S$10),""))) -> 0 | Y17: ='Setup Page'!P18 -> Virtual Address | AG17: =IF(Y17="","",'Setup Page'!$W$4) -> $ | AH17: =IF($K$12="T O T A L",SUMIFS('Expense Entry'!$F$11:$F59,'Expense Entry'!$D$11:$D59,Y17,'Expense Entry'!$Q$11:$Q59,$K$10,'Expense Entry'!$R$11:$R59,$S$10),IF($K$12="N E T",SUMIFS('Expense Entry'!$H$11:$H59,'Expense Entry'!$D$11:$D59,Y17,'Expense Entry'!$Q$11:$Q59,$K$10,'Expense Entry'!$R$11:$R59,$S$10),IF($K$12="T A X",SUMIFS('Expense Entry'!$I$11:$I59,'Expense Entry'!$D$11:$D59,Y17,'Expense Entry'!$Q$11:$Q59,$K$10,'Expense Entry'!$R$11:$R59,$S$10),""))) -> 0
K18: ='Setup Page'!C19 -> Fines | S18: =IF(K18="","",'Setup Page'!$W$4) -> $ | T18: =IF($K$12="T O T A L",SUMIFS('Income Entry'!$F$11:$F59,'Income Entry'!$L$11:$L59,K18,'Income Entry'!$S$11:$S59,$K$10,'Income Entry'!$T$11:$T59,$S$10),IF($K$12="N E T",SUMIFS('Income Entry'!$H$11:$H59,'Income Entry'!$L$11:$L59,K18,'Income Entry'!$S$11:$S59,$K$10,'Income Entry'!$T$11:$T59,$S$10),IF($K$12="T A X",SUMIFS('Income Entry'!$I$11:$I59,'Income Entry'!$L$11:$L59,K18,'Income Entry'!$S$11:$S59,$K$10,'Income Entry'!$T$11:$T59,$S$10),""))) -> 0 | Y18: ='Setup Page'!P19 -> Legal Zoom | AG18: =IF(Y18="","",'Setup Page'!$W$4) -> $ | AH18: =IF($K$12="T O T A L",SUMIFS('Expense Entry'!$F$11:$F59,'Expense Entry'!$D$11:$D59,Y18,'Expense Entry'!$Q$11:$Q59,$K$10,'Expense Entry'!$R$11:$R59,$S$10),IF($K$12="N E T",SUMIFS('Expense Entry'!$H$11:$H59,'Expense Entry'!$D$11:$D59,Y18,'Expense Entry'!$Q$11:$Q59,$K$10,'Expense Entry'!$R$11:$R59,$S$10),IF($K$12="T A X",SUMIFS('Expense Entry'!$I$11:$I59,'Expense Entry'!$D$11:$D59,Y18,'Expense Entry'!$Q$11:$Q59,$K$10,'Expense Entry'!$R$11:$R59,$S$10),""))) -> 0
K19: ='Setup Page'!C20 | S19: =IF(K19="","",'Setup Page'!$W$4) | T19: =IF($K$12="T O T A L",SUMIFS('Income Entry'!$F$11:$F59,'Income Entry'!$L$11:$L59,K19,'Income Entry'!$S$11:$S59,$K$10,'Income Entry'!$T$11:$T59,$S$10),IF($K$12="N E T",SUMIFS('Income Entry'!$H$11:$H59,'Income Entry'!$L$11:$L59,K19,'Income Entry'!$S$11:$S59,$K$10,'Income Entry'!$T$11:$T59,$S$10),IF($K$12="T A X",SUMIFS('Income Entry'!$I$11:$I59,'Income Entry'!$L$11:$L59,K19,'Income Entry'!$S$11:$S59,$K$10,'Income Entry'!$T$11:$T59,$S$10),""))) -> 0 | Y19: ='Setup Page'!P20 -> Google GSuite | AG19: =IF(Y19="","",'Setup Page'!$W$4) -> $ | AH19: =IF($K$12="T O T A L",SUMIFS('Expense Entry'!$F$11:$F59,'Expense Entry'!$D$11:$D59,Y19,'Expense Entry'!$Q$11:$Q59,$K$10,'Expense Entry'!$R$11:$R59,$S$10),IF($K$12="N E T",SUMIFS('Expense Entry'!$H$11:$H59,'Expense Entry'!$D$11:$D59,Y19,'Expense Entry'!$Q$11:$Q59,$K$10,'Expense Entry'!$R$11:$R59,$S$10),IF($K$12="T A X",SUMIFS('Expense Entry'!$I$11:$I59,'Expense Entry'!$D$11:$D59,Y19,'Expense Entry'!$Q$11:$Q59,$K$10,'Expense Entry'!$R$11:$R59,$S$10),""))) -> 28.8
K20: ='Setup Page'!C21 | S20: =IF(K20="","",'Setup Page'!$W$4) | T20: =IF($K$12="T O T A L",SUMIFS('Income Entry'!$F$11:$F59,'Income Entry'!$L$11:$L59,K20,'Income Entry'!$S$11:$S59,$K$10,'Income Entry'!$T$11:$T59,$S$10),IF($K$12="N E T",SUMIFS('Income Entry'!$H$11:$H59,'Income Entry'!$L$11:$L59,K20,'Income Entry'!$S$11:$S59,$K$10,'Income Entry'!$T$11:$T59,$S$10),IF($K$12="T A X",SUMIFS('Income Entry'!$I$11:$I59,'Income Entry'!$L$11:$L59,K20,'Income Entry'!$S$11:$S59,$K$10,'Income Entry'!$T$11:$T59,$S$10),""))) -> 0 | Y20: ='Setup Page'!P21 | AG20: =IF(Y20="","",'Setup Page'!$W$4) | AH20: =IF($K$12="T O T A L",SUMIFS('Expense Entry'!$F$11:$F59,'Expense Entry'!$D$11:$D59,Y20,'Expense Entry'!$Q$11:$Q59,$K$10,'Expense Entry'!$R$11:$R59,$S$10),IF($K$12="N E T",SUMIFS('Expense Entry'!$H$11:$H59,'Expense Entry'!$D$11:$D59,Y20,'Expense Entry'!$Q$11:$Q59,$K$10,'Expense Entry'!$R$11:$R59,$S$10),IF($K$12="T A X",SUMIFS('Expense Entry'!$I$11:$I59,'Expense Entry'!$D$11:$D59,Y20,'Expense Entry'!$Q$11:$Q59,$K$10,'Expense Entry'!$R$11:$R59,$S$10),""))) -> 0
C21: I N C O M E A F T E R T A X | K21: ='Setup Page'!C22 | S21: =IF(K21="","",'Setup Page'!$W$4) | T21: =IF($K$12="T O T A L",SUMIFS('Income Entry'!$F$11:$F59,'Income Entry'!$L$11:$L59,K21,'Income Entry'!$S$11:$S59,$K$10,'Income Entry'!$T$11:$T59,$S$10),IF($K$12="N E T",SUMIFS('Income Entry'!$H$11:$H59,'Income Entry'!$L$11:$L59,K21,'Income Entry'!$S$11:$S59,$K$10,'Income Entry'!$T$11:$T59,$S$10),IF($K$12="T A X",SUMIFS('Income Entry'!$I$11:$I59,'Income Entry'!$L$11:$L59,K21,'Income Entry'!$S$11:$S59,$K$10,'Income Entry'!$T$11:$T59,$S$10),""))) -> 0 | Y21: ='Setup Page'!P22 | AG21: =IF(Y21="","",'Setup Page'!$W$4) | AH21: =IF($K$12="T O T A L",SUMIFS('Expense Entry'!$F$11:$F59,'Expense Entry'!$D$11:$D59,Y21,'Expense Entry'!$Q$11:$Q59,$K$10,'Expense Entry'!$R$11:$R59,$S$10),IF($K$12="N E T",SUMIFS('Expense Entry'!$H$11:$H59,'Expense Entry'!$D$11:$D59,Y21,'Expense Entry'!$Q$11:$Q59,$K$10,'Expense Entry'!$R$11:$R59,$S$10),IF($K$12="T A X",SUMIFS('Expense Entry'!$I$11:$I59,'Expense Entry'!$D$11:$D59,Y21,'Expense Entry'!$Q$11:$Q59,$K$10,'Expense Entry'!$R$11:$R59,$S$10),""))) -> 0
K22: ='Setup Page'!C23 | S22: =IF(K22="","",'Setup Page'!$W$4) | T22: =IF($K$12="T O T A L",SUMIFS('Income Entry'!$F$11:$F59,'Income Entry'!$L$11:$L59,K22,'Income Entry'!$S$11:$S59,$K$10,'Income Entry'!$T$11:$T59,$S$10),IF($K$12="N E T",SUMIFS('Income Entry'!$H$11:$H59,'Income Entry'!$L$11:$L59,K22,'Income Entry'!$S$11:$S59,$K$10,'Income Entry'!$T$11:$T59,$S$10),IF($K$12="T A X",SUMIFS('Income Entry'!$I$11:$I59,'Income Entry'!$L$11:$L59,K22,'Income Entry'!$S$11:$S59,$K$10,'Income Entry'!$T$11:$T59,$S$10),""))) -> 0 | Y22: ='Setup Page'!P23 | AG22: =IF(Y22="","",'Setup Page'!$W$4) | AH22: =IF($K$12="T O T A L",SUMIFS('Expense Entry'!$F$11:$F59,'Expense Entry'!$D$11:$D59,Y22,'Expense Entry'!$Q$11:$Q59,$K$10,'Expense Entry'!$R$11:$R59,$S$10),IF($K$12="N E T",SUMIFS('Expense Entry'!$H$11:$H59,'Expense Entry'!$D$11:$D59,Y22,'Expense Entry'!$Q$11:$Q59,$K$10,'Expense Entry'!$R$11:$R59,$S$10),IF($K$12="T A X",SUMIFS('Expense Entry'!$I$11:$I59,'Expense Entry'!$D$11:$D59,Y22,'Expense Entry'!$Q$11:$Q59,$K$10,'Expense Entry'!$R$11:$R59,$S$10),""))) -> 0
C23: =IF(D23="","",'Setup Page'!$W$4) -> $ | D23: ='Back-End Page'!D43 -> 0 | K23: ='Setup Page'!C24 | S23: =IF(K23="","",'Setup Page'!$W$4) | T23: =IF($K$12="T O T A L",SUMIFS('Income Entry'!$F$11:$F59,'Income Entry'!$L$11:$L59,K23,'Income Entry'!$S$11:$S59,$K$10,'Income Entry'!$T$11:$T59,$S$10),IF($K$12="N E T",SUMIFS('Income Entry'!$H$11:$H59,'Income Entry'!$L$11:$L59,K23,'Income Entry'!$S$11:$S59,$K$10,'Income Entry'!$T$11:$T59,$S$10),IF($K$12="T A X",SUMIFS('Income Entry'!$I$11:$I59,'Income Entry'!$L$11:$L59,K23,'Income Entry'!$S$11:$S59,$K$10,'Income Entry'!$T$11:$T59,$S$10),""))) -> 0 | Y23: ='Setup Page'!P24 | AG23: =IF(Y23="","",'Setup Page'!$W$4) | AH23: =IF($K$12="T O T A L",SUMIFS('Expense Entry'!$F$11:$F59,'Expense Entry'!$D$11:$D59,Y23,'Expense Entry'!$Q$11:$Q59,$K$10,'Expense Entry'!$R$11:$R59,$S$10),IF($K$12="N E T",SUMIFS('Expense Entry'!$H$11:$H59,'Expense Entry'!$D$11:$D59,Y23,'Expense Entry'!$Q$11:$Q59,$K$10,'Expense Entry'!$R$11:$R59,$S$10),IF($K$12="T A X",SUMIFS('Expense Entry'!$I$11:$I59,'Expense Entry'!$D$11:$D59,Y23,'Expense Entry'!$Q$11:$Q59,$K$10,'Expense Entry'!$R$11:$R59,$S$10),""))) -> 0
K24: ='Setup Page'!C25 | S24: =IF(K24="","",'Setup Page'!$W$4) | T24: =IF($K$12="T O T A L",SUMIFS('Income Entry'!$F$11:$F59,'Income Entry'!$L$11:$L59,K24,'Income Entry'!$S$11:$S59,$K$10,'Income Entry'!$T$11:$T59,$S$10),IF($K$12="N E T",SUMIFS('Income Entry'!$H$11:$H59,'Income Entry'!$L$11:$L59,K24,'Income Entry'!$S$11:$S59,$K$10,'Income Entry'!$T$11:$T59,$S$10),IF($K$12="T A X",SUMIFS('Income Entry'!$I$11:$I59,'Income Entry'!$L$11:$L59,K24,'Income Entry'!$S$11:$S59,$K$10,'Income Entry'!$T$11:$T59,$S$10),""))) -> 0 | Y24: ='Setup Page'!P25 | AG24: =IF(Y24="","",'Setup Page'!$W$4) | AH24: =IF($K$12="T O T A L",SUMIFS('Expense Entry'!$F$11:$F59,'Expense Entry'!$D$11:$D59,Y24,'Expense Entry'!$Q$11:$Q59,$K$10,'Expense Entry'!$R$11:$R59,$S$10),IF($K$12="N E T",SUMIFS('Expense Entry'!$H$11:$H59,'Expense Entry'!$D$11:$D59,Y24,'Expense Entry'!$Q$11:$Q59,$K$10,'Expense Entry'!$R$11:$R59,$S$10),IF($K$12="T A X",SUMIFS('Expense Entry'!$I$11:$I59,'Expense Entry'!$D$11:$D59,Y24,'Expense Entry'!$Q$11:$Q59,$K$10,'Expense Entry'!$R$11:$R59,$S$10),""))) -> 0
K25: ='Setup Page'!C26 | S25: =IF(K25="","",'Setup Page'!$W$4) | T25: =IF($K$12="T O T A L",SUMIFS('Income Entry'!$F$11:$F59,'Income Entry'!$L$11:$L59,K25,'Income Entry'!$S$11:$S59,$K$10,'Income Entry'!$T$11:$T59,$S$10),IF($K$12="N E T",SUMIFS('Income Entry'!$H$11:$H59,'Income Entry'!$L$11:$L59,K25,'Income Entry'!$S$11:$S59,$K$10,'Income Entry'!$T$11:$T59,$S$10),IF($K$12="T A X",SUMIFS('Income Entry'!$I$11:$I59,'Income Entry'!$L$11:$L59,K25,'Income Entry'!$S$11:$S59,$K$10,'Income Entry'!$T$11:$T59,$S$10),""))) -> 0 | Y25: ='Setup Page'!P26 | AG25: =IF(Y25="","",'Setup Page'!$W$4) | AH25: =IF($K$12="T O T A L",SUMIFS('Expense Entry'!$F$11:$F59,'Expense Entry'!$D$11:$D59,Y25,'Expense Entry'!$Q$11:$Q59,$K$10,'Expense Entry'!$R$11:$R59,$S$10),IF($K$12="N E T",SUMIFS('Expense Entry'!$H$11:$H59,'Expense Entry'!$D$11:$D59,Y25,'Expense Entry'!$Q$11:$Q59,$K$10,'Expense Entry'!$R$11:$R59,$S$10),IF($K$12="T A X",SUMIFS('Expense Entry'!$I$11:$I59,'Expense Entry'!$D$11:$D59,Y25,'Expense Entry'!$Q$11:$Q59,$K$10,'Expense Entry'!$R$11:$R59,$S$10),""))) -> 0
K26: ='Setup Page'!C27 | S26: =IF(K26="","",'Setup Page'!$W$4) | T26: =IF($K$12="T O T A L",SUMIFS('Income Entry'!$F$11:$F59,'Income Entry'!$L$11:$L59,K26,'Income Entry'!$S$11:$S59,$K$10,'Income Entry'!$T$11:$T59,$S$10),IF($K$12="N E T",SUMIFS('Income Entry'!$H$11:$H59,'Income Entry'!$L$11:$L59,K26,'Income Entry'!$S$11:$S59,$K$10,'Income Entry'!$T$11:$T59,$S$10),IF($K$12="T A X",SUMIFS('Income Entry'!$I$11:$I59,'Income Entry'!$L$11:$L59,K26,'Income Entry'!$S$11:$S59,$K$10,'Income Entry'!$T$11:$T59,$S$10),""))) -> 0 | Y26: ='Setup Page'!P27 | AG26: =IF(Y26="","",'Setup Page'!$W$4) | AH26: =IF($K$12="T O T A L",SUMIFS('Expense Entry'!$F$11:$F59,'Expense Entry'!$D$11:$D59,Y26,'Expense Entry'!$Q$11:$Q59,$K$10,'Expense Entry'!$R$11:$R59,$S$10),IF($K$12="N E T",SUMIFS('Expense Entry'!$H$11:$H59,'Expense Entry'!$D$11:$D59,Y26,'Expense Entry'!$Q$11:$Q59,$K$10,'Expense Entry'!$R$11:$R59,$S$10),IF($K$12="T A X",SUMIFS('Expense Entry'!$I$11:$I59,'Expense Entry'!$D$11:$D59,Y26,'Expense Entry'!$Q$11:$Q59,$K$10,'Expense Entry'!$R$11:$R59,$S$10),""))) -> 0
C27: M O N T H ' S P R O F I T | K27: ='Setup Page'!C28 | S27: =IF(K27="","",'Setup Page'!$W$4) | T27: =IF($K$12="T O T A L",SUMIFS('Income Entry'!$F$11:$F59,'Income Entry'!$L$11:$L59,K27,'Income Entry'!$S$11:$S59,$K$10,'Income Entry'!$T$11:$T59,$S$10),IF($K$12="N E T",SUMIFS('Income Entry'!$H$11:$H59,'Income Entry'!$L$11:$L59,K27,'Income Entry'!$S$11:$S59,$K$10,'Income Entry'!$T$11:$T59,$S$10),IF($K$12="T A X",SUMIFS('Income Entry'!$I$11:$I59,'Income Entry'!$L$11:$L59,K27,'Income Entry'!$S$11:$S59,$K$10,'Income Entry'!$T$11:$T59,$S$10),""))) -> 0 | Y27: ='Setup Page'!P28 | AG27: =IF(Y27="","",'Setup Page'!$W$4) | AH27: =IF($K$12="T O T A L",SUMIFS('Expense Entry'!$F$11:$F59,'Expense Entry'!$D$11:$D59,Y27,'Expense Entry'!$Q$11:$Q59,$K$10,'Expense Entry'!$R$11:$R59,$S$10),IF($K$12="N E T",SUMIFS('Expense Entry'!$H$11:$H59,'Expense Entry'!$D$11:$D59,Y27,'Expense Entry'!$Q$11:$Q59,$K$10,'Expense Entry'!$R$11:$R59,$S$10),IF($K$12="T A X",SUMIFS('Expense Entry'!$I$11:$I59,'Expense Entry'!$D$11:$D59,Y27,'Expense Entry'!$Q$11:$Q59,$K$10,'Expense Entry'!$R$11:$R59,$S$10),""))) -> 0
K28: ='Setup Page'!C29 | S28: =IF(K28="","",'Setup Page'!$W$4) | T28: =IF($K$12="T O T A L",SUMIFS('Income Entry'!$F$11:$F59,'Income Entry'!$L$11:$L59,K28,'Income Entry'!$S$11:$S59,$K$10,'Income Entry'!$T$11:$T59,$S$10),IF($K$12="N E T",SUMIFS('Income Entry'!$H$11:$H59,'Income Entry'!$L$11:$L59,K28,'Income Entry'!$S$11:$S59,$K$10,'Income Entry'!$T$11:$T59,$S$10),IF($K$12="T A X",SUMIFS('Income Entry'!$I$11:$I59,'Income Entry'!$L$11:$L59,K28,'Income Entry'!$S$11:$S59,$K$10,'Income Entry'!$T$11:$T59,$S$10),""))) -> 0 | Y28: ='Setup Page'!P29 | AG28: =IF(Y28="","",'Setup Page'!$W$4) | AH28: =IF($K$12="T O T A L",SUMIFS('Expense Entry'!$F$11:$F59,'Expense Entry'!$D$11:$D59,Y28,'Expense Entry'!$Q$11:$Q59,$K$10,'Expense Entry'!$R$11:$R59,$S$10),IF($K$12="N E T",SUMIFS('Expense Entry'!$H$11:$H59,'Expense Entry'!$D$11:$D59,Y28,'Expense Entry'!$Q$11:$Q59,$K$10,'Expense Entry'!$R$11:$R59,$S$10),IF($K$12="T A X",SUMIFS('Expense Entry'!$I$11:$I59,'Expense Entry'!$D$11:$D59,Y28,'Expense Entry'!$Q$11:$Q59,$K$10,'Expense Entry'!$R$11:$R59,$S$10),""))) -> 0
C29: =IF(D29="","",'Setup Page'!$W$4) -> $ | D29: =D23-D17 -> -28.8 | K29: ='Setup Page'!C30 | S29: =IF(K29="","",'Setup Page'!$W$4) | T29: =IF($K$12="T O T A L",SUMIFS('Income Entry'!$F$11:$F59,'Income Entry'!$L$11:$L59,K29,'Income Entry'!$S$11:$S59,$K$10,'Income Entry'!$T$11:$T59,$S$10),IF($K$12="N E T",SUMIFS('Income Entry'!$H$11:$H59,'Income Entry'!$L$11:$L59,K29,'Income Entry'!$S$11:$S59,$K$10,'Income Entry'!$T$11:$T59,$S$10),IF($K$12="T A X",SUMIFS('Income Entry'!$I$11:$I59,'Income Entry'!$L$11:$L59,K29,'Income Entry'!$S$11:$S59,$K$10,'Income Entry'!$T$11:$T59,$S$10),""))) -> 0 | Y29: ='Setup Page'!P30 | AG29: =IF(Y29="","",'Setup Page'!$W$4) | AH29: =IF($K$12="T O T A L",SUMIFS('Expense Entry'!$F$11:$F59,'Expense Entry'!$D$11:$D59,Y29,'Expense Entry'!$Q$11:$Q59,$K$10,'Expense Entry'!$R$11:$R59,$S$10),IF($K$12="N E T",SUMIFS('Expense Entry'!$H$11:$H59,'Expense Entry'!$D$11:$D59,Y29,'Expense Entry'!$Q$11:$Q59,$K$10,'Expense Entry'!$R$11:$R59,$S$10),IF($K$12="T A X",SUMIFS('Expense Entry'!$I$11:$I59,'Expense Entry'!$D$11:$D59,Y29,'Expense Entry'!$Q$11:$Q59,$K$10,'Expense Entry'!$R$11:$R59,$S$10),""))) -> 0
K30: ='Setup Page'!C31 | S30: =IF(K30="","",'Setup Page'!$W$4) | T30: =IF($K$12="T O T A L",SUMIFS('Income Entry'!$F$11:$F59,'Income Entry'!$L$11:$L59,K30,'Income Entry'!$S$11:$S59,$K$10,'Income Entry'!$T$11:$T59,$S$10),IF($K$12="N E T",SUMIFS('Income Entry'!$H$11:$H59,'Income Entry'!$L$11:$L59,K30,'Income Entry'!$S$11:$S59,$K$10,'Income Entry'!$T$11:$T59,$S$10),IF($K$12="T A X",SUMIFS('Income Entry'!$I$11:$I59,'Income Entry'!$L$11:$L59,K30,'Income Entry'!$S$11:$S59,$K$10,'Income Entry'!$T$11:$T59,$S$10),""))) -> 0 | Y30: ='Setup Page'!P31 | AG30: =IF(Y30="","",'Setup Page'!$W$4) | AH30: =IF($K$12="T O T A L",SUMIFS('Expense Entry'!$F$11:$F59,'Expense Entry'!$D$11:$D59,Y30,'Expense Entry'!$Q$11:$Q59,$K$10,'Expense Entry'!$R$11:$R59,$S$10),IF($K$12="N E T",SUMIFS('Expense Entry'!$H$11:$H59,'Expense Entry'!$D$11:$D59,Y30,'Expense Entry'!$Q$11:$Q59,$K$10,'Expense Entry'!$R$11:$R59,$S$10),IF($K$12="T A X",SUMIFS('Expense Entry'!$I$11:$I59,'Expense Entry'!$D$11:$D59,Y30,'Expense Entry'!$Q$11:$Q59,$K$10,'Expense Entry'!$R$11:$R59,$S$10),""))) -> 0
K31: ='Setup Page'!C32 | S31: =IF(K31="","",'Setup Page'!$W$4) | T31: =IF($K$12="T O T A L",SUMIFS('Income Entry'!$F$11:$F59,'Income Entry'!$L$11:$L59,K31,'Income Entry'!$S$11:$S59,$K$10,'Income Entry'!$T$11:$T59,$S$10),IF($K$12="N E T",SUMIFS('Income Entry'!$H$11:$H59,'Income Entry'!$L$11:$L59,K31,'Income Entry'!$S$11:$S59,$K$10,'Income Entry'!$T$11:$T59,$S$10),IF($K$12="T A X",SUMIFS('Income Entry'!$I$11:$I59,'Income Entry'!$L$11:$L59,K31,'Income Entry'!$S$11:$S59,$K$10,'Income Entry'!$T$11:$T59,$S$10),""))) -> 0 | Y31: ='Setup Page'!P32 | AG31: =IF(Y31="","",'Setup Page'!$W$4) | AH31: =IF($K$12="T O T A L",SUMIFS('Expense Entry'!$F$11:$F59,'Expense Entry'!$D$11:$D59,Y31,'Expense Entry'!$Q$11:$Q59,$K$10,'Expense Entry'!$R$11:$R59,$S$10),IF($K$12="N E T",SUMIFS('Expense Entry'!$H$11:$H59,'Expense Entry'!$D$11:$D59,Y31,'Expense Entry'!$Q$11:$Q59,$K$10,'Expense Entry'!$R$11:$R59,$S$10),IF($K$12="T A X",SUMIFS('Expense Entry'!$I$11:$I59,'Expense Entry'!$D$11:$D59,Y31,'Expense Entry'!$Q$11:$Q59,$K$10,'Expense Entry'!$R$11:$R59,$S$10),""))) -> 0
K32: ='Setup Page'!C33 | S32: =IF(K32="","",'Setup Page'!$W$4) | T32: =IF($K$12="T O T A L",SUMIFS('Income Entry'!$F$11:$F59,'Income Entry'!$L$11:$L59,K32,'Income Entry'!$S$11:$S59,$K$10,'Income Entry'!$T$11:$T59,$S$10),IF($K$12="N E T",SUMIFS('Income Entry'!$H$11:$H59,'Income Entry'!$L$11:$L59,K32,'Income Entry'!$S$11:$S59,$K$10,'Income Entry'!$T$11:$T59,$S$10),IF($K$12="T A X",SUMIFS('Income Entry'!$I$11:$I59,'Income Entry'!$L$11:$L59,K32,'Income Entry'!$S$11:$S59,$K$10,'Income Entry'!$T$11:$T59,$S$10),""))) -> 0 | Y32: ='Setup Page'!P33 | AG32: =IF(Y32="","",'Setup Page'!$W$4) | AH32: =IF($K$12="T O T A L",SUMIFS('Expense Entry'!$F$11:$F59,'Expense Entry'!$D$11:$D59,Y32,'Expense Entry'!$Q$11:$Q59,$K$10,'Expense Entry'!$R$11:$R59,$S$10),IF($K$12="N E T",SUMIFS('Expense Entry'!$H$11:$H59,'Expense Entry'!$D$11:$D59,Y32,'Expense Entry'!$Q$11:$Q59,$K$10,'Expense Entry'!$R$11:$R59,$S$10),IF($K$12="T A X",SUMIFS('Expense Entry'!$I$11:$I59,'Expense Entry'!$D$11:$D59,Y32,'Expense Entry'!$Q$11:$Q59,$K$10,'Expense Entry'!$R$11:$R59,$S$10),""))) -> 0
C33: M O N T H ' S P R O F I T G O A L | K33: ='Setup Page'!C34 | S33: =IF(K33="","",'Setup Page'!$W$4) | T33: =IF($K$12="T O T A L",SUMIFS('Income Entry'!$F$11:$F59,'Income Entry'!$L$11:$L59,K33,'Income Entry'!$S$11:$S59,$K$10,'Income Entry'!$T$11:$T59,$S$10),IF($K$12="N E T",SUMIFS('Income Entry'!$H$11:$H59,'Income Entry'!$L$11:$L59,K33,'Income Entry'!$S$11:$S59,$K$10,'Income Entry'!$T$11:$T59,$S$10),IF($K$12="T A X",SUMIFS('Income Entry'!$I$11:$I59,'Income Entry'!$L$11:$L59,K33,'Income Entry'!$S$11:$S59,$K$10,'Income Entry'!$T$11:$T59,$S$10),""))) -> 0 | Y33: ='Setup Page'!P34 | AG33: =IF(Y33="","",'Setup Page'!$W$4) | AH33: =IF($K$12="T O T A L",SUMIFS('Expense Entry'!$F$11:$F59,'Expense Entry'!$D$11:$D59,Y33,'Expense Entry'!$Q$11:$Q59,$K$10,'Expense Entry'!$R$11:$R59,$S$10),IF($K$12="N E T",SUMIFS('Expense Entry'!$H$11:$H59,'Expense Entry'!$D$11:$D59,Y33,'Expense Entry'!$Q$11:$Q59,$K$10,'Expense Entry'!$R$11:$R59,$S$10),IF($K$12="T A X",SUMIFS('Expense Entry'!$I$11:$I59,'Expense Entry'!$D$11:$D59,Y33,'Expense Entry'!$Q$11:$Q59,$K$10,'Expense Entry'!$R$11:$R59,$S$10),""))) -> 0
K34: ='Setup Page'!C35 | S34: =IF(K34="","",'Setup Page'!$W$4) | T34: =IF($K$12="T O T A L",SUMIFS('Income Entry'!$F$11:$F59,'Income Entry'!$L$11:$L59,K34,'Income Entry'!$S$11:$S59,$K$10,'Income Entry'!$T$11:$T59,$S$10),IF($K$12="N E T",SUMIFS('Income Entry'!$H$11:$H59,'Income Entry'!$L$11:$L59,K34,'Income Entry'!$S$11:$S59,$K$10,'Income Entry'!$T$11:$T59,$S$10),IF($K$12="T A X",SUMIFS('Income Entry'!$I$11:$I59,'Income Entry'!$L$11:$L59,K34,'Income Entry'!$S$11:$S59,$K$10,'Income Entry'!$T$11:$T59,$S$10),""))) -> 0 | Y34: ='Setup Page'!P35 | AG34: =IF(Y34="","",'Setup Page'!$W$4) | AH34: =IF($K$12="T O T A L",SUMIFS('Expense Entry'!$F$11:$F59,'Expense Entry'!$D$11:$D59,Y34,'Expense Entry'!$Q$11:$Q59,$K$10,'Expense Entry'!$R$11:$R59,$S$10),IF($K$12="N E T",SUMIFS('Expense Entry'!$H$11:$H59,'Expense Entry'!$D$11:$D59,Y34,'Expense Entry'!$Q$11:$Q59,$K$10,'Expense Entry'!$R$11:$R59,$S$10),IF($K$12="T A X",SUMIFS('Expense Entry'!$I$11:$I59,'Expense Entry'!$D$11:$D59,Y34,'Expense Entry'!$Q$11:$Q59,$K$10,'Expense Entry'!$R$11:$R59,$S$10),""))) -> 0
C35: =IF(D35="","",'Setup Page'!$W$4) -> $ | D35: =VLOOKUP(O10,'Setup Page'!AS18:AT29,2,FALSE) -> 6000 | K35: ='Setup Page'!C36 | S35: =IF(K35="","",'Setup Page'!$W$4) | T35: =IF($K$12="T O T A L",SUMIFS('Income Entry'!$F$11:$F59,'Income Entry'!$L$11:$L59,K35,'Income Entry'!$S$11:$S59,$K$10,'Income Entry'!$T$11:$T59,$S$10),IF($K$12="N E T",SUMIFS('Income Entry'!$H$11:$H59,'Income Entry'!$L$11:$L59,K35,'Income Entry'!$S$11:$S59,$K$10,'Income Entry'!$T$11:$T59,$S$10),IF($K$12="T A X",SUMIFS('Income Entry'!$I$11:$I59,'Income Entry'!$L$11:$L59,K35,'Income Entry'!$S$11:$S59,$K$10,'Income Entry'!$T$11:$T59,$S$10),""))) -> 0 | Y35: ='Setup Page'!P36 | AG35: =IF(Y35="","",'Setup Page'!$W$4) | AH35: =IF($K$12="T O T A L",SUMIFS('Expense Entry'!$F$11:$F59,'Expense Entry'!$D$11:$D59,Y35,'Expense Entry'!$Q$11:$Q59,$K$10,'Expense Entry'!$R$11:$R59,$S$10),IF($K$12="N E T",SUMIFS('Expense Entry'!$H$11:$H59,'Expense Entry'!$D$11:$D59,Y35,'Expense Entry'!$Q$11:$Q59,$K$10,'Expense Entry'!$R$11:$R59,$S$10),IF($K$12="T A X",SUMIFS('Expense Entry'!$I$11:$I59,'Expense Entry'!$D$11:$D59,Y35,'Expense Entry'!$Q$11:$Q59,$K$10,'Expense Entry'!$R$11:$R59,$S$10),""))) -> 0
K36: ='Setup Page'!C37 | S36: =IF(K36="","",'Setup Page'!$W$4) | T36: =IF($K$12="T O T A L",SUMIFS('Income Entry'!$F$11:$F59,'Income Entry'!$L$11:$L59,K36,'Income Entry'!$S$11:$S59,$K$10,'Income Entry'!$T$11:$T59,$S$10),IF($K$12="N E T",SUMIFS('Income Entry'!$H$11:$H59,'Income Entry'!$L$11:$L59,K36,'Income Entry'!$S$11:$S59,$K$10,'Income Entry'!$T$11:$T59,$S$10),IF($K$12="T A X",SUMIFS('Income Entry'!$I$11:$I59,'Income Entry'!$L$11:$L59,K36,'Income Entry'!$S$11:$S59,$K$10,'Income Entry'!$T$11:$T59,$S$10),""))) -> 0 | Y36: ='Setup Page'!P37 | AG36: =IF(Y36="","",'Setup Page'!$W$4) | AH36: =IF($K$12="T O T A L",SUMIFS('Expense Entry'!$F$11:$F59,'Expense Entry'!$D$11:$D59,Y36,'Expense Entry'!$Q$11:$Q59,$K$10,'Expense Entry'!$R$11:$R59,$S$10),IF($K$12="N E T",SUMIFS('Expense Entry'!$H$11:$H59,'Expense Entry'!$D$11:$D59,Y36,'Expense Entry'!$Q$11:$Q59,$K$10,'Expense Entry'!$R$11:$R59,$S$10),IF($K$12="T A X",SUMIFS('Expense Entry'!$I$11:$I59,'Expense Entry'!$D$11:$D59,Y36,'Expense Entry'!$Q$11:$Q59,$K$10,'Expense Entry'!$R$11:$R59,$S$10),""))) -> 0
K37: ='Setup Page'!C38 | S37: =IF(K37="","",'Setup Page'!$W$4) | T37: =IF($K$12="T O T A L",SUMIFS('Income Entry'!$F$11:$F59,'Income Entry'!$L$11:$L59,K37,'Income Entry'!$S$11:$S59,$K$10,'Income Entry'!$T$11:$T59,$S$10),IF($K$12="N E T",SUMIFS('Income Entry'!$H$11:$H59,'Income Entry'!$L$11:$L59,K37,'Income Entry'!$S$11:$S59,$K$10,'Income Entry'!$T$11:$T59,$S$10),IF($K$12="T A X",SUMIFS('Income Entry'!$I$11:$I59,'Income Entry'!$L$11:$L59,K37,'Income Entry'!$S$11:$S59,$K$10,'Income Entry'!$T$11:$T59,$S$10),""))) -> 0 | Y37: ='Setup Page'!P38 | AG37: =IF(Y37="","",'Setup Page'!$W$4) | AH37: =IF($K$12="T O T A L",SUMIFS('Expense Entry'!$F$11:$F59,'Expense Entry'!$D$11:$D59,Y37,'Expense Entry'!$Q$11:$Q59,$K$10,'Expense Entry'!$R$11:$R59,$S$10),IF($K$12="N E T",SUMIFS('Expense Entry'!$H$11:$H59,'Expense Entry'!$D$11:$D59,Y37,'Expense Entry'!$Q$11:$Q59,$K$10,'Expense Entry'!$R$11:$R59,$S$10),IF($K$12="T A X",SUMIFS('Expense Entry'!$I$11:$I59,'Expense Entry'!$D$11:$D59,Y37,'Expense Entry'!$Q$11:$Q59,$K$10,'Expense Entry'!$R$11:$R59,$S$10),""))) -> 0
K38: ='Setup Page'!C39 | S38: =IF(K38="","",'Setup Page'!$W$4) | T38: =IF($K$12="T O T A L",SUMIFS('Income Entry'!$F$11:$F59,'Income Entry'!$L$11:$L59,K38,'Income Entry'!$S$11:$S59,$K$10,'Income Entry'!$T$11:$T59,$S$10),IF($K$12="N E T",SUMIFS('Income Entry'!$H$11:$H59,'Income Entry'!$L$11:$L59,K38,'Income Entry'!$S$11:$S59,$K$10,'Income Entry'!$T$11:$T59,$S$10),IF($K$12="T A X",SUMIFS('Income Entry'!$I$11:$I59,'Income Entry'!$L$11:$L59,K38,'Income Entry'!$S$11:$S59,$K$10,'Income Entry'!$T$11:$T59,$S$10),""))) -> 0 | Y38: ='Setup Page'!P39 | AG38: =IF(Y38="","",'Setup Page'!$W$4) | AH38: =IF($K$12="T O T A L",SUMIFS('Expense Entry'!$F$11:$F59,'Expense Entry'!$D$11:$D59,Y38,'Expense Entry'!$Q$11:$Q59,$K$10,'Expense Entry'!$R$11:$R59,$S$10),IF($K$12="N E T",SUMIFS('Expense Entry'!$H$11:$H59,'Expense Entry'!$D$11:$D59,Y38,'Expense Entry'!$Q$11:$Q59,$K$10,'Expense Entry'!$R$11:$R59,$S$10),IF($K$12="T A X",SUMIFS('Expense Entry'!$I$11:$I59,'Expense Entry'!$D$11:$D59,Y38,'Expense Entry'!$Q$11:$Q59,$K$10,'Expense Entry'!$R$11:$R59,$S$10),""))) -> 0
K39: ='Setup Page'!C40 | S39: =IF(K39="","",'Setup Page'!$W$4) | T39: =IF($K$12="T O T A L",SUMIFS('Income Entry'!$F$11:$F59,'Income Entry'!$L$11:$L59,K39,'Income Entry'!$S$11:$S59,$K$10,'Income Entry'!$T$11:$T59,$S$10),IF($K$12="N E T",SUMIFS('Income Entry'!$H$11:$H59,'Income Entry'!$L$11:$L59,K39,'Income Entry'!$S$11:$S59,$K$10,'Income Entry'!$T$11:$T59,$S$10),IF($K$12="T A X",SUMIFS('Income Entry'!$I$11:$I59,'Income Entry'!$L$11:$L59,K39,'Income Entry'!$S$11:$S59,$K$10,'Income Entry'!$T$11:$T59,$S$10),""))) -> 0 | Y39: ='Setup Page'!P40 | AG39: =IF(Y39="","",'Setup Page'!$W$4) | AH39: =IF($K$12="T O T A L",SUMIFS('Expense Entry'!$F$11:$F59,'Expense Entry'!$D$11:$D59,Y39,'Expense Entry'!$Q$11:$Q59,$K$10,'Expense Entry'!$R$11:$R59,$S$10),IF($K$12="N E T",SUMIFS('Expense Entry'!$H$11:$H59,'Expense Entry'!$D$11:$D59,Y39,'Expense Entry'!$Q$11:$Q59,$K$10,'Expense Entry'!$R$11:$R59,$S$10),IF($K$12="T A X",SUMIFS('Expense Entry'!$I$11:$I59,'Expense Entry'!$D$11:$D59,Y39,'Expense Entry'!$Q$11:$Q59,$K$10,'Expense Entry'!$R$11:$R59,$S$10),""))) -> 0
K40: ='Setup Page'!C41 | S40: =IF(K40="","",'Setup Page'!$W$4) | T40: =IF($K$12="T O T A L",SUMIFS('Income Entry'!$F$11:$F59,'Income Entry'!$L$11:$L59,K40,'Income Entry'!$S$11:$S59,$K$10,'Income Entry'!$T$11:$T59,$S$10),IF($K$12="N E T",SUMIFS('Income Entry'!$H$11:$H59,'Income Entry'!$L$11:$L59,K40,'Income Entry'!$S$11:$S59,$K$10,'Income Entry'!$T$11:$T59,$S$10),IF($K$12="T A X",SUMIFS('Income Entry'!$I$11:$I59,'Income Entry'!$L$11:$L59,K40,'Income Entry'!$S$11:$S59,$K$10,'Income Entry'!$T$11:$T59,$S$10),""))) -> 0 | Y40: ='Setup Page'!P41 | AG40: =IF(Y40="","",'Setup Page'!$W$4) | AH40: =IF($K$12="T O T A L",SUMIFS('Expense Entry'!$F$11:$F59,'Expense Entry'!$D$11:$D59,Y40,'Expense Entry'!$Q$11:$Q59,$K$10,'Expense Entry'!$R$11:$R59,$S$10),IF($K$12="N E T",SUMIFS('Expense Entry'!$H$11:$H59,'Expense Entry'!$D$11:$D59,Y40,'Expense Entry'!$Q$11:$Q59,$K$10,'Expense Entry'!$R$11:$R59,$S$10),IF($K$12="T A X",SUMIFS('Expense Entry'!$I$11:$I59,'Expense Entry'!$D$11:$D59,Y40,'Expense Entry'!$Q$11:$Q59,$K$10,'Expense Entry'!$R$11:$R59,$S$10),""))) -> 0
K41: ='Setup Page'!C42 | S41: =IF(K41="","",'Setup Page'!$W$4) | T41: =IF($K$12="T O T A L",SUMIFS('Income Entry'!$F$11:$F59,'Income Entry'!$L$11:$L59,K41,'Income Entry'!$S$11:$S59,$K$10,'Income Entry'!$T$11:$T59,$S$10),IF($K$12="N E T",SUMIFS('Income Entry'!$H$11:$H59,'Income Entry'!$L$11:$L59,K41,'Income Entry'!$S$11:$S59,$K$10,'Income Entry'!$T$11:$T59,$S$10),IF($K$12="T A X",SUMIFS('Income Entry'!$I$11:$I59,'Income Entry'!$L$11:$L59,K41,'Income Entry'!$S$11:$S59,$K$10,'Income Entry'!$T$11:$T59,$S$10),""))) -> 0 | Y41: ='Setup Page'!P42 | AG41: =IF(Y41="","",'Setup Page'!$W$4) | AH41: =IF($K$12="T O T A L",SUMIFS('Expense Entry'!$F$11:$F59,'Expense Entry'!$D$11:$D59,Y41,'Expense Entry'!$Q$11:$Q59,$K$10,'Expense Entry'!$R$11:$R59,$S$10),IF($K$12="N E T",SUMIFS('Expense Entry'!$H$11:$H59,'Expense Entry'!$D$11:$D59,Y41,'Expense Entry'!$Q$11:$Q59,$K$10,'Expense Entry'!$R$11:$R59,$S$10),IF($K$12="T A X",SUMIFS('Expense Entry'!$I$11:$I59,'Expense Entry'!$D$11:$D59,Y41,'Expense Entry'!$Q$11:$Q59,$K$10,'Expense Entry'!$R$11:$R59,$S$10),""))) -> 0
K42: ='Setup Page'!C43 | S42: =IF(K42="","",'Setup Page'!$W$4) | T42: =IF($K$12="T O T A L",SUMIFS('Income Entry'!$F$11:$F59,'Income Entry'!$L$11:$L59,K42,'Income Entry'!$S$11:$S59,$K$10,'Income Entry'!$T$11:$T59,$S$10),IF($K$12="N E T",SUMIFS('Income Entry'!$H$11:$H59,'Income Entry'!$L$11:$L59,K42,'Income Entry'!$S$11:$S59,$K$10,'Income Entry'!$T$11:$T59,$S$10),IF($K$12="T A X",SUMIFS('Income Entry'!$I$11:$I59,'Income Entry'!$L$11:$L59,K42,'Income Entry'!$S$11:$S59,$K$10,'Income Entry'!$T$11:$T59,$S$10),""))) -> 0 | Y42: ='Setup Page'!P43 | AG42: =IF(Y42="","",'Setup Page'!$W$4) | AH42: =IF($K$12="T O T A L",SUMIFS('Expense Entry'!$F$11:$F59,'Expense Entry'!$D$11:$D59,Y42,'Expense Entry'!$Q$11:$Q59,$K$10,'Expense Entry'!$R$11:$R59,$S$10),IF($K$12="N E T",SUMIFS('Expense Entry'!$H$11:$H59,'Expense Entry'!$D$11:$D59,Y42,'Expense Entry'!$Q$11:$Q59,$K$10,'Expense Entry'!$R$11:$R59,$S$10),IF($K$12="T A X",SUMIFS('Expense Entry'!$I$11:$I59,'Expense Entry'!$D$11:$D59,Y42,'Expense Entry'!$Q$11:$Q59,$K$10,'Expense Entry'!$R$11:$R59,$S$10),""))) -> 0
K43: ='Setup Page'!C44 | S43: =IF(K43="","",'Setup Page'!$W$4) | T43: =IF($K$12="T O T A L",SUMIFS('Income Entry'!$F$11:$F59,'Income Entry'!$L$11:$L59,K43,'Income Entry'!$S$11:$S59,$K$10,'Income Entry'!$T$11:$T59,$S$10),IF($K$12="N E T",SUMIFS('Income Entry'!$H$11:$H59,'Income Entry'!$L$11:$L59,K43,'Income Entry'!$S$11:$S59,$K$10,'Income Entry'!$T$11:$T59,$S$10),IF($K$12="T A X",SUMIFS('Income Entry'!$I$11:$I59,'Income Entry'!$L$11:$L59,K43,'Income Entry'!$S$11:$S59,$K$10,'Income Entry'!$T$11:$T59,$S$10),""))) -> 0 | Y43: ='Setup Page'!P44 | AG43: =IF(Y43="","",'Setup Page'!$W$4) | AH43: =IF($K$12="T O T A L",SUMIFS('Expense Entry'!$F$11:$F59,'Expense Entry'!$D$11:$D59,Y43,'Expense Entry'!$Q$11:$Q59,$K$10,'Expense Entry'!$R$11:$R59,$S$10),IF($K$12="N E T",SUMIFS('Expense Entry'!$H$11:$H59,'Expense Entry'!$D$11:$D59,Y43,'Expense Entry'!$Q$11:$Q59,$K$10,'Expense Entry'!$R$11:$R59,$S$10),IF($K$12="T A X",SUMIFS('Expense Entry'!$I$11:$I59,'Expense Entry'!$D$11:$D59,Y43,'Expense Entry'!$Q$11:$Q59,$K$10,'Expense Entry'!$R$11:$R59,$S$10),""))) -> 0
K44: ='Setup Page'!C45 | S44: =IF(K44="","",'Setup Page'!$W$4) | T44: =IF($K$12="T O T A L",SUMIFS('Income Entry'!$F$11:$F59,'Income Entry'!$L$11:$L59,K44,'Income Entry'!$S$11:$S59,$K$10,'Income Entry'!$T$11:$T59,$S$10),IF($K$12="N E T",SUMIFS('Income Entry'!$H$11:$H59,'Income Entry'!$L$11:$L59,K44,'Income Entry'!$S$11:$S59,$K$10,'Income Entry'!$T$11:$T59,$S$10),IF($K$12="T A X",SUMIFS('Income Entry'!$I$11:$I59,'Income Entry'!$L$11:$L59,K44,'Income Entry'!$S$11:$S59,$K$10,'Income Entry'!$T$11:$T59,$S$10),""))) -> 0 | Y44: ='Setup Page'!P45 | AG44: =IF(Y44="","",'Setup Page'!$W$4) | AH44: =IF($K$12="T O T A L",SUMIFS('Expense Entry'!$F$11:$F59,'Expense Entry'!$D$11:$D59,Y44,'Expense Entry'!$Q$11:$Q59,$K$10,'Expense Entry'!$R$11:$R59,$S$10),IF($K$12="N E T",SUMIFS('Expense Entry'!$H$11:$H59,'Expense Entry'!$D$11:$D59,Y44,'Expense Entry'!$Q$11:$Q59,$K$10,'Expense Entry'!$R$11:$R59,$S$10),IF($K$12="T A X",SUMIFS('Expense Entry'!$I$11:$I59,'Expense Entry'!$D$11:$D59,Y44,'Expense Entry'!$Q$11:$Q59,$K$10,'Expense Entry'!$R$11:$R59,$S$10),""))) -> 0
K45: ='Setup Page'!C46 | S45: =IF(K45="","",'Setup Page'!$W$4) | T45: =IF($K$12="T O T A L",SUMIFS('Income Entry'!$F$11:$F59,'Income Entry'!$L$11:$L59,K45,'Income Entry'!$S$11:$S59,$K$10,'Income Entry'!$T$11:$T59,$S$10),IF($K$12="N E T",SUMIFS('Income Entry'!$H$11:$H59,'Income Entry'!$L$11:$L59,K45,'Income Entry'!$S$11:$S59,$K$10,'Income Entry'!$T$11:$T59,$S$10),IF($K$12="T A X",SUMIFS('Income Entry'!$I$11:$I59,'Income Entry'!$L$11:$L59,K45,'Income Entry'!$S$11:$S59,$K$10,'Income Entry'!$T$11:$T59,$S$10),""))) -> 0 | Y45: ='Setup Page'!P46 | AG45: =IF(Y45="","",'Setup Page'!$W$4) | AH45: =IF($K$12="T O T A L",SUMIFS('Expense Entry'!$F$11:$F59,'Expense Entry'!$D$11:$D59,Y45,'Expense Entry'!$Q$11:$Q59,$K$10,'Expense Entry'!$R$11:$R59,$S$10),IF($K$12="N E T",SUMIFS('Expense Entry'!$H$11:$H59,'Expense Entry'!$D$11:$D59,Y45,'Expense Entry'!$Q$11:$Q59,$K$10,'Expense Entry'!$R$11:$R59,$S$10),IF($K$12="T A X",SUMIFS('Expense Entry'!$I$11:$I59,'Expense Entry'!$D$11:$D59,Y45,'Expense Entry'!$Q$11:$Q59,$K$10,'Expense Entry'!$R$11:$R59,$S$10),""))) -> 0
K46: ='Setup Page'!C47 | S46: =IF(K46="","",'Setup Page'!$W$4) | T46: =IF($K$12="T O T A L",SUMIFS('Income Entry'!$F$11:$F59,'Income Entry'!$L$11:$L59,K46,'Income Entry'!$S$11:$S59,$K$10,'Income Entry'!$T$11:$T59,$S$10),IF($K$12="N E T",SUMIFS('Income Entry'!$H$11:$H59,'Income Entry'!$L$11:$L59,K46,'Income Entry'!$S$11:$S59,$K$10,'Income Entry'!$T$11:$T59,$S$10),IF($K$12="T A X",SUMIFS('Income Entry'!$I$11:$I59,'Income Entry'!$L$11:$L59,K46,'Income Entry'!$S$11:$S59,$K$10,'Income Entry'!$T$11:$T59,$S$10),""))) -> 0 | Y46: ='Setup Page'!P47 | AG46: =IF(Y46="","",'Setup Page'!$W$4) | AH46: =IF($K$12="T O T A L",SUMIFS('Expense Entry'!$F$11:$F59,'Expense Entry'!$D$11:$D59,Y46,'Expense Entry'!$Q$11:$Q59,$K$10,'Expense Entry'!$R$11:$R59,$S$10),IF($K$12="N E T",SUMIFS('Expense Entry'!$H$11:$H59,'Expense Entry'!$D$11:$D59,Y46,'Expense Entry'!$Q$11:$Q59,$K$10,'Expense Entry'!$R$11:$R59,$S$10),IF($K$12="T A X",SUMIFS('Expense Entry'!$I$11:$I59,'Expense Entry'!$D$11:$D59,Y46,'Expense Entry'!$Q$11:$Q59,$K$10,'Expense Entry'!$R$11:$R59,$S$10),""))) -> 0
K47: ='Setup Page'!C48 | S47: =IF(K47="","",'Setup Page'!$W$4) | T47: =IF($K$12="T O T A L",SUMIFS('Income Entry'!$F$11:$F59,'Income Entry'!$L$11:$L59,K47,'Income Entry'!$S$11:$S59,$K$10,'Income Entry'!$T$11:$T59,$S$10),IF($K$12="N E T",SUMIFS('Income Entry'!$H$11:$H59,'Income Entry'!$L$11:$L59,K47,'Income Entry'!$S$11:$S59,$K$10,'Income Entry'!$T$11:$T59,$S$10),IF($K$12="T A X",SUMIFS('Income Entry'!$I$11:$I59,'Income Entry'!$L$11:$L59,K47,'Income Entry'!$S$11:$S59,$K$10,'Income Entry'!$T$11:$T59,$S$10),""))) -> 0 | Y47: ='Setup Page'!P48 | AG47: =IF(Y47="","",'Setup Page'!$W$4) | AH47: =IF($K$12="T O T A L",SUMIFS('Expense Entry'!$F$11:$F59,'Expense Entry'!$D$11:$D59,Y47,'Expense Entry'!$Q$11:$Q59,$K$10,'Expense Entry'!$R$11:$R59,$S$10),IF($K$12="N E T",SUMIFS('Expense Entry'!$H$11:$H59,'Expense Entry'!$D$11:$D59,Y47,'Expense Entry'!$Q$11:$Q59,$K$10,'Expense Entry'!$R$11:$R59,$S$10),IF($K$12="T A X",SUMIFS('Expense Entry'!$I$11:$I59,'Expense Entry'!$D$11:$D59,Y47,'Expense Entry'!$Q$11:$Q59,$K$10,'Expense Entry'!$R$11:$R59,$S$10),""))) -> 0
K48: ='Setup Page'!C49 | S48: =IF(K48="","",'Setup Page'!$W$4) | T48: =IF($K$12="T O T A L",SUMIFS('Income Entry'!$F$11:$F59,'Income Entry'!$L$11:$L59,K48,'Income Entry'!$S$11:$S59,$K$10,'Income Entry'!$T$11:$T59,$S$10),IF($K$12="N E T",SUMIFS('Income Entry'!$H$11:$H59,'Income Entry'!$L$11:$L59,K48,'Income Entry'!$S$11:$S59,$K$10,'Income Entry'!$T$11:$T59,$S$10),IF($K$12="T A X",SUMIFS('Income Entry'!$I$11:$I59,'Income Entry'!$L$11:$L59,K48,'Income Entry'!$S$11:$S59,$K$10,'Income Entry'!$T$11:$T59,$S$10),""))) -> 0 | Y48: ='Setup Page'!P49 | AG48: =IF(Y48="","",'Setup Page'!$W$4) | AH48: =IF($K$12="T O T A L",SUMIFS('Expense Entry'!$F$11:$F59,'Expense Entry'!$D$11:$D59,Y48,'Expense Entry'!$Q$11:$Q59,$K$10,'Expense Entry'!$R$11:$R59,$S$10),IF($K$12="N E T",SUMIFS('Expense Entry'!$H$11:$H59,'Expense Entry'!$D$11:$D59,Y48,'Expense Entry'!$Q$11:$Q59,$K$10,'Expense Entry'!$R$11:$R59,$S$10),IF($K$12="T A X",SUMIFS('Expense Entry'!$I$11:$I59,'Expense Entry'!$D$11:$D59,Y48,'Expense Entry'!$Q$11:$Q59,$K$10,'Expense Entry'!$R$11:$R59,$S$10),""))) -> 0
